Workbook
Name param_proc_rezerva: Parametri!$B$18
Name param_plafon_rezerva: Parametri!$B$19
Name param_prag_mf: Parametri!$B$20
Name param_proc_vehicul: Parametri!$B$21
Name param_plafon_amo_auto: Parametri!$B$22
Name param_cota_cas: Parametri!$B$23
Name param_cota_cass: Parametri!$B$24
Name param_cota_impozit: Parametri!$B$25
Name param_cota_cam: Parametri!$B$26
Name param_cota_impozit_profit: Parametri!$B$27
Name param_cota_impozit_dividend: Parametri!$B$28

Sheet Instructiuni
A1: MODULE DECLARATIVE — instrucțiuni de utilizare
A3: Ce este acest fișier
A4: Cele 23 module declarative care execută fluxurile din „Plan de conturi”. Fluxul explică de ce; modulul face înregistrarea. Completezi câteva variabile într-o foaie de input și ies jurnalele și nota de export.
A5: Toate foile se generează din depozit, la fiecare build. Nu se editează structura aici: o modificare făcută în fișier se pierde la următorul `make`.
A7: Cum se folosește ORICE modul
A8: 1. CatalogModule — pune Activ=DA pe modulele de care ai nevoie luna asta.
A9: 2. Declarații_<MODUL> — completează doar celulele galbene cu scris albastru. Restul sunt formule.
A10: 3. Reguli_<MODUL> — nu se completează. E regula contabilă sau fiscală, cu temeiul ei, plus ce anume rupe corelațiile. Se citește când rezultatul te surprinde.
A11: 4. Jurnale_<MODUL> — verifică fiecare celulă Check. Trebuie OK înainte de a lua rezultatul de bun.
A12: 5. NotaExport_<MODUL> — filtrează Include=DA și înregistrează în program.
A14: Două tipare de foi
A15: Declarații → Reguli → Jurnale → NotaExport — tiparul obișnuit, pentru modulele care produc înregistrări.
... A24: Modulul nu inventează conturi. Folosește doar conturile din politica declarată + rolurile din Plan de conturi. Porțile de calitate (ΣDr=ΣCr, stare terminală, pas revelator) rămân aceleași ca în foaia Fluxuri.

Sheet Parametri
A1: PARAMETRI GLOBALI — un singur loc pentru identitate și setări comune
A2: Completezi o dată. Toate foile Declarații_* citesc de aici. La client nou: schimbi doar aici.
A4: Identitate (date demonstrative — înlocuiește la utilizare reală)
A5: Denumire societate | B5: SC EXEMPLU SRL
A6: CUI | B6: RO00000000
A7: Luna curentă (YYYY-MM) | B7: 2026-07
A9: Setări contabile comune
A10: Cotă TVA standard | B10: 0.21
A11: Cotă TVA redusă | B11: 0.11
A13: Notă: valorile de mai sus sunt placeholder. Nu sunt date reale de client. Modulele Declarații_* referențiază Parametri!B5 / B6 / B7.
A15: Parametri globali — referiți prin nume definit (param_*)
A16: Numele din coloana C se folosește direct în formule. Schimbă valoarea aici o singură dată; toate modulele o preiau.
A17: Parametru | B17: Valoare | C17: Nume definit · temei
A18: Procent rezervă legală (din profitul brut) | B18: 0.05 | C18: param_proc_rezerva — art. 26 alin. (1) lit. a) Cod fiscal
A19: Plafon rezervă legală (din capitalul vărsat) | B19: 0.2 | C19: param_plafon_rezerva — art. 183 Legea 31/1990 — capital subscris ȘI VĂRSAT
A20: Prag mijloc fix (lei) | B20: 5000 | C20: param_prag_mf — OUG 8/2026, de la 25.02.2026; se actualizează anual cu inflația
A21: Procent de deducere vehicule (regim mixt) | B21: 0.5 | C21: param_proc_vehicul — art. 298 CF (TVA) și art. 25 alin. (3) lit. l) CF (cheltuieli)
A22: Plafon amortizare autoturism (lei/lună) | B22: 1500 | C22: param_plafon_amo_auto — art. 28 alin. (14) CF — NU se cumulează cu limitarea de 50%
A23: CAS — pensie (pe brut) | B23: 0.25 | C23: param_cota_cas — art. 138 CF
A24: CASS — sănătate (pe brut + tichete) | B24: 0.1 | C24: param_cota_cass — art. 156 CF — tichetele intră în bază, dar NU în baza CAS
A25: Impozit pe venit (pe venit net + tichete) | B25: 0.1 | C25: param_cota_impozit — art. 78 CF
A26: CAM — asigurare de muncă (pe brut) | B26: 0.0225 | C26: param_cota_cam — art. 220^3 CF — cheltuiala angajatorului, nu reținere
A27: Impozit pe profit | B27: 0.16 | C27: param_cota_impozit_profit — art. 17 CF — folosit la cuantificarea efectului unei cheltuieli nedeductibile
A28: Impozit pe dividende | B28: 0.16 | C28: param_cota_impozit_dividend — art. 43 CF, modificat prin L. 141/2025 — cota urmează data DISTRIBUIRII

Sheet CatalogModule
A1: CATALOG MODULE DECLARATIVE — sumonare fluxuri
A2: Bifează / activează modulele pentru luna curentă. Fiecare modul activ își trage variabilele din Declarații și emite blocuri în Jurnale + NotaExport.
A3: Arhitectură: Declarații (input galben) → Reguli (tabele fixe) → Registru (dacă e cazul) → Jurnale (auto) → NotaExport (1 rând = 1 înregistrare).
A5: Activ | B5: Cod modul | C5: Flux(uri) acoperite | D5: Tip | E5: Variabile obligatorii | F5: Porți declarative | G5: Blocuri jurnal emise | H5: Status
A6: DA | B6: MOD_INCHIDERE_TVA | C6: F-405 | D6: Lunar (fără linii) | E6: Rulaj 4426, Rulaj 4427, Luna | F6: — | G6: B1 Închidere 4426/4427 → 4423/4424 | H6: IMPLEMENTAT
A7: NU | B7: MOD_APROV_TRANZIT | C7: F-302 | D7: Eveniment + stingere | E7: Sumă netă, TVA, Cont stoc, Furnizor, Data factură, Data recepție | F7: Tranzit vs. direct | G7: B1 Factură→32x; B2 Recepție 30x=32x | H7: IMPLEMENTAT
A8: DA | B8: MOD_SALARII | C8: F-413 | D8: Lunar, pe registru de angajați | E8: Brut, tichete, avans, pe angajat; cotele CAS/CASS/impozit/CAM | F8: Fără deducere personală și fără facilități sectoriale — vezi Reguli, tabelul C | G8: B1 Plata avansului; B2 Costurile lunii; B3 Plăți (net, taxe, CAM) | H8: IMPLEMENTAT
A9: NU | B9: MOD_DECONT | C9: F-502 | D9: Pe decont | E9: Linii de decont (furnizor, sumă, natură, tip document, CUI), avans, cote | F9: Plătitor de TVA; % deducere vehicule; matricea document × CUI | G9: B1 Avans; B2 Cheltuieli + TVA; B3 Regularizare avans; B4 Plată / restituire | H9: IMPLEMENTAT
A10: NU | B10: MOD_LEASING_FIN | C10: F-108 | D10: Pe contract + lunar | E10: Valoare contract, avans, rată, dobândă, comision, CASCO, regim vehicul, durată | F10: MIXT 50% / EXCLUSIV 100% / EXCEPTAT; capitalizare vs. cheltuială pentru TVA nededusă | G10: B1 Avans; B2 TVA avans; B3 Intrare + 167; B4 Stingere avans; B5 Factura lunară; B6 Corecție TVA 50%; B7 Limitare 50% cheltuieli; B8 Amortizare | H10: IMPLEMENTAT
A11: NU | B11: MOD_VANZ_AMANUNT | C11: F-316, F-318, F-317 | D11: Pe gestiune + cotă | E11: Cost, Adaos %, Cotă TVA, Gestiune | F11: En-gros vs Amănunt | G11: B1 Aprovizionare PVA; B2 TVA ded.; B3 Descărcare; B4 Venit; B5 Închidere TVA | H11: IMPLEMENTAT
A12: NU | B12: MOD_TVA_INCASARE | C12: F-401 | D12: Pe factură | E12: Sumă netă, TVA, Tip (achiziție/vânzare), Data plată/încasare | F12: 4428.INC activ | G12: B1 Factură→4428.INC; B2 Plată/Încasare→4426/4427 | H12: IMPLEMENTAT
A13: NU | B13: MOD_INCHIDERE_EX | C13: F-104 | D13: Anual | E13: Rulaje cls.6, Rulaje cls.7, Impozit/IMCA | F13: — | G13: B1 Închidere 6xx; B2 Închidere 7xx; B3 Impozit; B4 Report 117 | H13: IMPLEMENTAT
A14: NU | B14: MOD_INTERMEDIAR | C14: F-408, F-501, F-411 | D14: Eveniment discret | E14: Sumă, Cont intermediar (408/418/581/473), Cont final, Document | F14: Un set de Declarații = un tip + o operațiune; modulul nu amestecă tipurile | G14: B1 Deschidere intermediar; B2 Stingere | H14: IMPLEMENTAT
A15: NU | B15: MOD_NEUTRALIZARE | C15: F-311, F-312, F-209 | D15: Pe stadiu producție | E15: Cost acumulat, Cont stoc (331/332/231), Cont venit (711/712/722) | F15: — | G15: B1 Costuri→stoc; B2 Neutralizare; B3 Finalizare/livrare | H15: IMPLEMENTAT
A17: NU | B17: MOD_CAPITALURI | C17: F-103, F-105 | D17: Anual (31.12 + ianuarie) | E17: Sold 121, rulaj 691, capital vărsat 1012, sold 1061, pierdere reportată | F17: Dublu plafon rezervă legală; pierdere reportată de acoperit înainte de dividende | G17: B1 Rezervă legală; B2 Închidere 121; B3 Dividende; B4 Corecție 1174 | H17: IMPLEMENTAT
... A29: DA | B29: MOD_INCHIDERE_LUNARA | C29: F-422, F-413 | D29: Lunar, pe balanța de verificare | E29: Rulaj debitor, rulaj creditor și sold pentru conturile cu cadență; restul de plată de pe stat; soldul din decontul de TVA | F29: Verifică solduri, nu documente — vezi Reguli, tabelul C | G29: V1 Obligații lunare (rulaj = sold); V2 Datoria față de salariați; V3 Conturi care trebuie golite; V4 Verificarea CAM pe cifre | H29: IMPLEMENTAT
A31: REGULĂ DE SUMONARE
A32: 1. În CatalogModule setezi Activ=DA doar pe modulele necesare lunii.
A33: 2. Completezi variabilele din foaia Declarații_Modul (galben).
A34: 3. Jurnalele și NotaExport se populează automat doar pentru modulele active.
A35: 4. Verifici Check=0 pe fiecare bloc; filtrezi NotaExport pe Include=DA și imporți.
A36: Nu se creează conturi noi din modul — se folosesc doar conturile din politica declarată + planul de conturi pe rol.

Sheet Declarații_CAPITALURI
A1: MOD_CAPITALURI — Declarații (input)
A2: Completează doar celulele galbene cu scris albastru. Restul sunt formule sau text fix.
A4: 1. Antet
A5: Societate | B5: =Parametri!B5 -> SC EXEMPLU SRL
A6: Exercițiu financiar (anul N) | B6: 2026
A7: Data notei de repartizare (31.12.N) | B7: 2026-12-31
A8: Data notei de închidere (ianuarie N+1) | B8: 2027-01-05
A10: 2. Date din balanță
A11: Sold creditor 121 (după închiderea cls. 6 și 7) | B11: 2500
A12: Rulaj 691 (cheltuiala cu impozitul pe profit) | B12: 0
A13: Capital social subscris ȘI VĂRSAT (1012) | B13: 5000 | C13: Partea nevărsată din 1011 NU intră în plafon
A14: Sold 1061 deja constituit | B14: 0
A15: Pierdere contabilă reportată de acoperit (1171 sold D) | B15: 0
A16: Capitaluri proprii (activ net) din bilanț | B16: 5000 | C16: Se ia din bilanț, nu din balanță — vezi C-20
A18: 3. Rezerva legală — dublul plafon (nu edita)
A19: Profit contabil brut (121 + 691) | B19: =B11+B12 -> 2500
A20: Limita fiscală: 5% din profitul brut | B20: =B19*param_proc_rezerva -> 125 | C20: art. 26 alin. (1) lit. a) Cod fiscal
A21: Limita juridică: 20% din capitalul vărsat | B21: =B13*param_plafon_rezerva -> 1000 | C21: art. 183 Legea 31/1990
A22: Spațiu rămas până la plafon | B22: =MAX(0,B21-B14) -> 1000
A23: Rezervă legală de constituit | B23: =MIN(B20,B22) -> 125
A24: Check plafon rezervă | B24: =B14+B23 -> 125 | C24: =IF(B14+B23<=B21+0.001,"OK — sub plafonul de 20%","EROARE — depășire plafon") -> OK — sub plafonul de 20%
A26: 4. Repartizare
A27: Profit rămas după rezerva legală | B27: =B11-B23 -> 2375
A28: Disponibil de distribuit ca dividende | B28: =MAX(0,B27-B15) -> 2375
A29: Check pierdere reportată | B29: =B15 -> 0 | C29: =IF(B15>0,"ATENȚIE — acoperă întâi pierderea reportată (L. 239/2025)","OK — fără pierdere reportată") -> OK — fără pierdere reportată
A30: Check activ net ≥ ½ capital social (C-20) | B30: =B16 -> 5000 | C30: =IF(B16>=B13/2,"OK — activ net ≥ ½ capital social","BLOCAJ — L. 239/2025: fără dividende și fără restituiri de împrumuturi de la asociați până la reîntregire") -> OK — activ net ≥ ½ capital social
A32: 5. Corecție erori exerciții anterioare (1174)
A33: Bază corecție, fără TVA (0 dacă nu e cazul) | B33: 0
A34: TVA aferentă corecției | B34: 0
A35: Check 1174 | B35: =B33 -> 0 | C35: =IF(B33=0,"— fără corecție în această perioadă","1174 se închide obligatoriu în 1171 până la 31.12 (C-18) + D101 rectificativ") -> — fără corecție în această perioadă
A37: 6. Conturi (din planul pe rol)
A38: Cont rezultat | B38: 121
A39: Cont repartizarea profitului | B39: 129
A40: Cont rezervă legală | B40: 1061
A41: Cont rezultat reportat (analitic pe an) | B41: 1171.2026
A42: Cont dividende de plată | B42: 457
A43: Cont corecții exerciții anterioare | B43: 1174
A44: Cont furnizor | B44: 401.RO
A45: Cont TVA deductibilă | B45: 4426
A47: 7. Sufix generat
A48: Sufix | B48: ="— repartizare rezultat " & B6 -> — repartizare rezultat 2026
A50: Modul activ în CatalogModule? | B50: =IF(INDEX(CatalogModule!$A$1:$A$200,MATCH("MOD_CAPITALURI",CatalogModule!$B$1:$B$200,0))="DA","ACTIV — jurnalele se generează","INACTIV — jurnalele rămân goale") -> INACTIV — jurnalele rămân goale

Sheet Reguli_CAPITALURI
A1: MOD_CAPITALURI — Reguli (tabele fixe)
A2: Regula juridică/fiscală e dată, nu formulă. Se editează doar când se schimbă legea.
A4: Tabel A — Secvența de repartizare
A5: Pas | B5: Cont Dr | C5: Cont Cr | D5: Sumă (sursă) | E5: Condiție | F5: Temei / observație
A6: 1 | B6: 129 | C6: 1061 | D6: MIN(5% × profit brut; 20% × capital vărsat − rezerva existentă) | E6: La 31.12.N | F6: art. 183 L. 31/1990 + art. 26 alin. (1) lit. a) CF
A7: 2 | B7: 121 | C7: 129 | D7: cât rezerva constituită | E7: În ianuarie N+1 | F7: 129 are sold DEBITOR → se închide prin creditare. NU `129 = 1171`
A8: 3 | B8: 121 | C8: 1171 | D8: profit rămas nerepartizat | E8: În ianuarie N+1 | F8: 1171 cu analitic PE AN (C-21)
A9: 4 | B9: 1171 | C9: 457 | D9: dividende aprobate | E9: După hotărârea AGA | F9: Impozit 16% pentru distribuiri de la 01.01.2026 (L. 141/2025); cota urmează data DISTRIBUIRII, nu a plății
A10: 5 | B10: 1174 | C10: 401 | D10: corecție eroare semnificativă an anterior | E10: Dacă e cazul | F10: Nu prin 628. Obligatoriu D101 rectificativ
A11: 6 | B11: 1171 | C11: 1174 | D11: cât baza corecției | E11: După AGA | F11: 1174 e tranzitoriu — nu poate rămâne cu sold (C-18)
A13: Tabel B — Ordinea condițiilor înainte de dividende
A14: # | B14: Condiție | C14: Efect dacă nu e îndeplinită | F14: Temei
A15: 1 | B15: Rezerva legală constituită | C15: Nu se pot distribui dividende | F15: art. 183 L. 31/1990
A16: 2 | B16: Pierderea contabilă reportată acoperită integral | C16: Nu se pot distribui dividende | F16: art. 67 L. 31/1990
A17: 3 | B17: Activ net ≥ ½ din capitalul social subscris | C17: Blocaj dividende ȘI blocaj restituire împrumuturi de la asociați; amenzi 10.000–300.000 lei; răspundere solidară pentru obligațiile fiscale | F17: L. 239/2025 (modifică L. 31/1990)
A19: Tabel C — Porți de calitate
A20: • ΣDr = ΣCr pe fiecare bloc
A21: • După înregistrare: sold 121 = 0 și sold 129 = 0 (C-16)
A22: • Sold 1061 ≤ 20% × capital vărsat (C-17)
A23: • Sold 1174 = 0 la 31.12 (C-18)
A24: • 1171 are analitic pe an, cu sens D/C explicit (C-21)
A25: • Modulul nu creează conturi noi — folosește conturile din Declarații

Sheet Jurnale_CAPITALURI
A1: MOD_CAPITALURI — Jurnale (generate automat)
A2: Nu se scrie nimic manual. Toate sumele și descrierile derivă din Declarații_CAPITALURI.
A4: Bloc 1 — Constituirea rezervei legale (31.12.N)
A5: Data jurnal: | B5: =Declarații_CAPITALURI!B7 -> 2026-12-31
A7: Nr | B7: Cont Dr | C7: Sumă Dr | D7: Descriere Dr | E7: Cont Cr | F7: Sumă Cr | G7: Descriere Cr
A8: 1 | B8: =Declarații_CAPITALURI!B39 -> 129 | C8: =Declarații_CAPITALURI!B23 -> 125 | D8: ="Repartizare profit la rezerva legală " & Declarații_CAPITALURI!B48 -> Repartizare profit la rezerva legală — repartizare rezultat 2026 | E8: =Declarații_CAPITALURI!B40 -> 1061 | F8: =Declarații_CAPITALURI!B23 -> 125 | G8: ="Rezervă legală constituită " & Declarații_CAPITALURI!B48 -> Rezervă legală constituită — repartizare rezultat 2026
A10: Bloc 2 — Închiderea contului 121 (ianuarie N+1)
A11: Data jurnal: | B11: =Declarații_CAPITALURI!B8 -> 2027-01-05
A13: Nr | B13: Cont Dr | C13: Sumă Dr | D13: Descriere Dr | E13: Cont Cr | F13: Sumă Cr | G13: Descriere Cr
A14: 1 | B14: =Declarații_CAPITALURI!B38 -> 121 | C14: =Declarații_CAPITALURI!B23 -> 125 | D14: ="Închidere 121 — partea repartizată " & Declarații_CAPITALURI!B48 -> Închidere 121 — partea repartizată — repartizare rezultat 2026 | E14: =Declarații_CAPITALURI!B39 -> 129 | F14: =Declarații_CAPITALURI!B23 -> 125 | G14: ="Stingere repartizare " & Declarații_CAPITALURI!B48 -> Stingere repartizare — repartizare rezultat 2026
A15: 2 | B15: =Declarații_CAPITALURI!B38 -> 121 | C15: =Declarații_CAPITALURI!B27 -> 2375 | D15: ="Închidere 121 — profit reportat " & Declarații_CAPITALURI!B48 -> Închidere 121 — profit reportat — repartizare rezultat 2026 | E15: =Declarații_CAPITALURI!B41 -> 1171.2026 | F15: =Declarații_CAPITALURI!B27 -> 2375 | G15: ="Report rezultat pe an " & Declarații_CAPITALURI!B48 -> Report rezultat pe an — repartizare rezultat 2026
A17: Bloc 3 — Dividende (după hotărârea AGA)
A18: Nr | B18: Cont Dr | C18: Sumă Dr | D18: Descriere Dr | E18: Cont Cr | F18: Sumă Cr | G18: Descriere Cr
A19: 1 | B19: =Declarații_CAPITALURI!B41 -> 1171.2026 | C19: =Declarații_CAPITALURI!B28 -> 2375 | D19: ="Dividende aprobate AGA " & Declarații_CAPITALURI!B48 -> Dividende aprobate AGA — repartizare rezultat 2026 | E19: =Declarații_CAPITALURI!B42 -> 457 | F19: =Declarații_CAPITALURI!B28 -> 2375 | G19: ="Dividende de plată " & Declarații_CAPITALURI!B48 -> Dividende de plată — repartizare rezultat 2026
A21: Bloc 4 — Corecție eroare exercițiu anterior (1174)
A22: Nr | B22: Cont Dr | C22: Sumă Dr | D22: Descriere Dr | E22: Cont Cr | F22: Sumă Cr | G22: Descriere Cr
A23: 1 | B23: =Declarații_CAPITALURI!B43 -> 1174 | C23: =Declarații_CAPITALURI!B33 -> 0 | D23: ="Corecție eroare exercițiu anterior " & Declarații_CAPITALURI!B48 -> Corecție eroare exercițiu anterior — repartizare rezultat 2026 | E23: =Declarații_CAPITALURI!B44 -> 401.RO | F23: =Declarații_CAPITALURI!B33 -> 0 | G23: ="Datorie furnizor din corecție " & Declarații_CAPITALURI!B48 -> Datorie furnizor din corecție — repartizare rezultat 2026
A24: 2 | B24: =Declarații_CAPITALURI!B45 -> 4426 | C24: =Declarații_CAPITALURI!B34 -> 0 | D24: ="TVA din corecție — se deduce în decontul curent " & Declarații_CAPITALURI!B48 -> TVA din corecție — se deduce în decontul curent — repartizare rezultat 2026 | E24: =Declarații_CAPITALURI!B44 -> 401.RO | F24: =Declarații_CAPITALURI!B34 -> 0 | G24: ="Datorie furnizor — TVA " & Declarații_CAPITALURI!B48 -> Datorie furnizor — TVA — repartizare rezultat 2026
A25: 3 | B25: =Declarații_CAPITALURI!B41 -> 1171.2026 | C25: =Declarații_CAPITALURI!B33 -> 0 | D25: ="Închiderea contului tranzitoriu 1174 " & Declarații_CAPITALURI!B48 -> Închiderea contului tranzitoriu 1174 — repartizare rezultat 2026 | E25: =Declarații_CAPITALURI!B43 -> 1174 | F25: =Declarații_CAPITALURI!B33 -> 0 | G25: ="Stingere 1174 " & Declarații_CAPITALURI!B48 -> Stingere 1174 — repartizare rezultat 2026
A27: Sumar și controale
A28: Total Dr | B28: =C8+C14+C15+C19+C23+C24+C25 -> 5000
A29: Total Cr | B29: =F8+F14+F15+F19+F23+F24+F25 -> 5000
A30: Check Σ (structural) | B30: =B28-B29 -> 0 | C30: =IF(ABS(B28-B29)<0.01,"OK — notele se închid","EROARE") -> OK — notele se închid
A31: Check închidere 121 (C-16) | B31: =Declarații_CAPITALURI!B11-(C14+C15) -> 0 | C31: =IF(ABS(Declarații_CAPITALURI!B11-(C14+C15))<0.01,"OK — 121 se închide integral","EROARE — 121 rămâne cu sold") -> OK — 121 se închide integral
A32: Check plafon rezervă (C-17) | B32: =Declarații_CAPITALURI!B14+C8 -> 125 | C32: =IF(Declarații_CAPITALURI!B14+C8<=Declarații_CAPITALURI!B21+0.001,"OK — sub 20% din capitalul vărsat","EROARE — depășire plafon") -> OK — sub 20% din capitalul vărsat
A33: Check 1174 (C-18) | B33: =C23-C25 -> 0 | C33: =IF(ABS(C23-C25)<0.01,"OK — 1174 se închide în 1171","EROARE — 1174 rămâne cu sold") -> OK — 1174 se închide în 1171
A34: Stare terminală așteptată: sold 121 = 0, sold 129 = 0, sold 1174 = 0, sold 1061 ≤ 20% × capital vărsat, 1171 cu analitic pe an.

Sheet NotaExport_CAPITALURI
A1: MOD_CAPITALURI — Notă pentru import (1 rând = 1 înregistrare)
A2: Filtrează pe coloana Include = DA înainte de import. Echilibrul se verifică pe bloc în Jurnale, nu pe totalul listei.
A4: Nr | B4: Bloc | C4: Data | D4: Cont Dr | E4: Cont Cr | F4: Sumă | G4: Descriere | H4: Document | I4: Include
A5: 1 | B5: Bloc 1 — Rezervă legală | C5: =Declarații_CAPITALURI!B7 -> 2026-12-31 | D5: =Jurnale_CAPITALURI!B8 -> 129 | E5: =Jurnale_CAPITALURI!E8 -> 1061 | F5: =Jurnale_CAPITALURI!C8 -> 125 | G5: =Jurnale_CAPITALURI!D8 -> Repartizare profit la rezerva legală — repartizare rezultat 2026 | H5: Notă contabilă 31.12 | I5: =IF(F5>0,"DA","NU") -> DA
A6: 2 | B6: Bloc 2 — Închidere 121 | C6: =Declarații_CAPITALURI!B8 -> 2027-01-05 | D6: =Jurnale_CAPITALURI!B14 -> 121 | E6: =Jurnale_CAPITALURI!E14 -> 129 | F6: =Jurnale_CAPITALURI!C14 -> 125 | G6: =Jurnale_CAPITALURI!D14 -> Închidere 121 — partea repartizată — repartizare rezultat 2026 | H6: Notă de închidere | I6: =IF(F6>0,"DA","NU") -> DA
A7: 3 | B7: Bloc 2 — Închidere 121 | C7: =Declarații_CAPITALURI!B8 -> 2027-01-05 | D7: =Jurnale_CAPITALURI!B15 -> 121 | E7: =Jurnale_CAPITALURI!E15 -> 1171.2026 | F7: =Jurnale_CAPITALURI!C15 -> 2375 | G7: =Jurnale_CAPITALURI!D15 -> Închidere 121 — profit reportat — repartizare rezultat 2026 | H7: Notă de închidere | I7: =IF(F7>0,"DA","NU") -> DA
A8: 4 | B8: Bloc 3 — Dividende | C8: =Declarații_CAPITALURI!B8 -> 2027-01-05 | D8: =Jurnale_CAPITALURI!B19 -> 1171.2026 | E8: =Jurnale_CAPITALURI!E19 -> 457 | F8: =Jurnale_CAPITALURI!C19 -> 2375 | G8: =Jurnale_CAPITALURI!D19 -> Dividende aprobate AGA — repartizare rezultat 2026 | H8: Hotărâre AGA | I8: =IF(F8>0,"DA","NU") -> DA
A9: 5 | B9: Bloc 4 — Corecție 1174 | C9: =Declarații_CAPITALURI!B8 -> 2027-01-05 | D9: =Jurnale_CAPITALURI!B23 -> 1174 | E9: =Jurnale_CAPITALURI!E23 -> 401.RO | F9: =Jurnale_CAPITALURI!C23 -> 0 | G9: =Jurnale_CAPITALURI!D23 -> Corecție eroare exercițiu anterior — repartizare rezultat 2026 | H9: Factură an anterior | I9: =IF(F9>0,"DA","NU") -> NU
A10: 6 | B10: Bloc 4 — Corecție 1174 | C10: =Declarații_CAPITALURI!B8 -> 2027-01-05 | D10: =Jurnale_CAPITALURI!B24 -> 4426 | E10: =Jurnale_CAPITALURI!E24 -> 401.RO | F10: =Jurnale_CAPITALURI!C24 -> 0 | G10: =Jurnale_CAPITALURI!D24 -> TVA din corecție — se deduce în decontul curent — repartizare rezultat 2026 | H10: Factură an anterior | I10: =IF(F10>0,"DA","NU") -> NU
A11: 7 | B11: Bloc 4 — Corecție 1174 | C11: =Declarații_CAPITALURI!B8 -> 2027-01-05 | D11: =Jurnale_CAPITALURI!B25 -> 1171.2026 | E11: =Jurnale_CAPITALURI!E25 -> 1174 | F11: =Jurnale_CAPITALURI!C25 -> 0 | G11: =Jurnale_CAPITALURI!D25 -> Închiderea contului tranzitoriu 1174 — repartizare rezultat 2026 | H11: Notă contabilă | I11: =IF(F11>0,"DA","NU") -> NU
A13: Rânduri de importat (Include=DA) | B13: =COUNTIF(I5:I11,"DA") -> 4
A14: Check global (trebuie 0) | B14: =Jurnale_CAPITALURI!B28-Jurnale_CAPITALURI!B29 -> 0 | C14: =IF(ABS(Jurnale_CAPITALURI!B28-Jurnale_CAPITALURI!B29)<0.01,"OK","EROARE") -> OK

Sheet Declarații_INCHIDERE_EX
A1: MOD_INCHIDERE_EX — Declarații (input)
A2: Modul anual. Completezi rulajele din balanță (sau totaluri din SAGA). Jurnalele închid cls.6 → 121, cls.7 → 121, calculează impozit / IMCA, repartizează 129 și reportează 117.
A4: 1. Antet
A5: Societate | B5: =Parametri!B5 -> SC EXEMPLU SRL
A6: CUI | B6: =Parametri!B6 -> RO00000000
A7: An exercițiu | B7: 2026
A8: Data jurnal închidere (31.12) | B8: 2026-12-31
A10: 2. Rulaje de închis (din balanță / totaluri SAGA)
A11: Total rulaj debitor cls.6 (cheltuieli) | B11: 185000
A12: Total rulaj creditor cls.7 (venituri) | B12: 245000
A14: 3. Impozit pe profit / IMCA
A15: Regim (PROFIT / MICRO / IMCA) | B15: PROFIT
A16: Baza impozabilă (sau cifră afaceri IMCA) | B16: 60000
A17: Cotă (0.16 / 0.01 / 0.03 etc.) | B17: 0.16
A18: Impozit calculat | B18: =B16*B17 -> 9600
A19: Cont cheltuială impozit (691 / 697 / 4417) | B19: 691
A20: Cont datorie impozit (441 / 4417) | B20: 441
A22: 4. Repartizare rezultat
A23: Rezultat înainte de impozit (7−6) | B23: =B12-B11 -> 60000
A24: Rezultat net (după impozit) | B24: =B23-B18 -> 50400
A25: Repartizare la rezerve / dividende etc. (opțional) | B25: 0
A26: Reportat pe 117 (sold final 121/129) | B26: =B24-B25 -> 50400
A28: 5. Politică conturi rezultat
A29: Cont profit și pierdere | B29: 121
A30: Cont repartizare profit | B30: 129
A31: Cont rezultat reportat | B31: 117
A33: 6. Sufix
A34: Sufix | B34: ="— închidere exercițiu " & B7 -> — închidere exercițiu 2026
A36: 7. Control
A37: Modul activ? | B37: =IF(INDEX(CatalogModule!$A$1:$A$200,MATCH("MOD_INCHIDERE_EX",CatalogModule!$B$1:$B$200,0))="DA","ACTIV","INACTIV") -> INACTIV
A38: Notă | B38: În practică se închid conturile de cheltuieli/venituri pe analitice (sau pe grupe). Aici se lucrează pe totaluri — un singur rând pe clasă.

Sheet Reguli_INCHIDERE_EX
A1: MOD_INCHIDERE_EX — Reguli (tabele fixe)
A2: Secvența de închidere e standard OMFP 1802. Detalierea pe conturi analitice se face în SAGA; modulul lucrează pe totaluri de clasă pentru generarea notei de principiu.
A4: Tabel A — Secvența de închidere
A5: Pas | B5: Bloc | C5: Cont Dr | D5: Cont Cr | E5: Sumă | F5: Observație
A6: 1 | B6: B1 Închidere cheltuieli | C6: 121 | D6: 6xx (total) | E6: Rulaj D cls.6 | F6: Neutralizare rezultat — cheltuieli
A7: 2 | B7: B2 Închidere venituri | C7: 7xx (total) | D7: 121 | E7: Rulaj C cls.7 | F7: Neutralizare rezultat — venituri
A8: 3 | B8: B3 Impozit | C8: 691/697 | D8: 441/4417 | E8: Impozit calculat | F8: Cheltuială cu impozitul → datorie
A9: 4 | B9: B3b Închidere 691 | C9: 121 | D9: 691 | E9: Impozit | F9: Impozitul intră în rezultatul net
A10: 5 | B10: B4 Repartizare (opțional) | C10: 129 | D10: 106/457… | E10: Sumă repartizată | F10: Doar dacă AGA / decizie există
A11: 6 | B11: B5 Report | C11: 121 | D11: 117 | E11: Sold final 121 | F11: Dacă profit; invers dacă pierdere
A13: Tabel B — Conturi din plan pe rol
A14: Cont | B14: Denumire | C14: Rol | D14: Observație
A15: 121 | B15: Profit sau pierdere | C15: Colectare rezultat | D15: Se închide anual; fără sold după report pe 117
A16: 129 | B16: Repartizarea profitului | C16: Colectare / tranzit | D16: Se folosește doar la repartizare formală
A17: 117 | B17: Rezultatul reportat | C17: Patrimonial — Capital | D17: Sold permanent până la acoperire / repartizare
A18: 691 | B18: Cheltuieli cu impozitul pe profit | C18: Neutralizare rezultat | D18: Se închide în 121
A19: 697 | B19: Cheltuieli cu impozitul pe venit micro | C19: Neutralizare rezultat | D19: Alternativă la 691
A20: 441 | B20: Impozit pe profit | C20: Patrimonial — Datorie | D20: Datorie către buget
A21: 4417 | B21: Impozit pe venit micro / alte impozite | C21: Patrimonial — Datorie | D21: Conform OMF actualizat
A23: Tabel C — Porți de calitate
A24: • ΣDr = ΣCr pe fiecare bloc
A25: • După B1+B2: sold 6xx = 0, sold 7xx = 0
A26: • Sold 121 înainte de report = rezultat net
A27: • După B5: sold 121 = 0, sold 117 reflectă reportul
A28: • Modulul nu înlocuiește D101 / declarația de impozit — produce doar nota contabilă
A30: Temei legal
A31: Ce se sprijină pe el | B31: Temei
A32: Veniturile și cheltuielile se închid prin 121 la sfârșitul exercițiului | B32: OMFP 1802/2014 — funcțiunea contului 121
A33: Cota de impozit pe profit | B33: art. 17 Cod fiscal
A34: Rezultatul rămas se reportează pe 117 până la repartizare sau acoperire | B34: OMFP 1802/2014 — funcțiunea contului 117

Sheet Jurnale_INCHIDERE_EX
A1: MOD_INCHIDERE_EX — Jurnale (generate automat)
A2: Toate sumele derivă din Declarații. În SAGA se detaliază pe conturi analitice; aici e nota de principiu pe totaluri de clasă.
A4: Data jurnal: | B4: =Declarații_INCHIDERE_EX!B8 -> 2026-12-31
A6: Bloc 1 — Închidere cheltuieli (cls.6 → 121)
A7: Nr | B7: Cont Dr | C7: Sumă Dr | D7: Descriere Dr | E7: Cont Cr | F7: Sumă Cr | G7: Descriere Cr
A8: 1 | B8: =Declarații_INCHIDERE_EX!B29 -> 121 | C8: =Declarații_INCHIDERE_EX!B11 -> 185000 | D8: ="Închidere cheltuieli cls.6 " & Declarații_INCHIDERE_EX!B34 -> Închidere cheltuieli cls.6 — închidere exercițiu 2026 | E8: 6xx | F8: =Declarații_INCHIDERE_EX!B11 -> 185000 | G8: ="Stingere rulaj cheltuieli " & Declarații_INCHIDERE_EX!B34 -> Stingere rulaj cheltuieli — închidere exercițiu 2026
A9: Check B1 | B9: =C8-F8 -> 0 | C9: =IF(ABS(B9)<0.01,"OK","EROARE") -> OK
A11: Bloc 2 — Închidere venituri (cls.7 → 121)
A12: Nr | B12: Cont Dr | C12: Sumă Dr | D12: Descriere Dr | E12: Cont Cr | F12: Sumă Cr | G12: Descriere Cr
A13: 1 | B13: 7xx | C13: =Declarații_INCHIDERE_EX!B12 -> 245000 | D13: ="Închidere venituri cls.7 " & Declarații_INCHIDERE_EX!B34 -> Închidere venituri cls.7 — închidere exercițiu 2026 | E13: =Declarații_INCHIDERE_EX!B29 -> 121 | F13: =Declarații_INCHIDERE_EX!B12 -> 245000 | G13: ="Stingere rulaj venituri " & Declarații_INCHIDERE_EX!B34 -> Stingere rulaj venituri — închidere exercițiu 2026
A14: Check B2 | B14: =C13-F13 -> 0 | C14: =IF(ABS(B14)<0.01,"OK","EROARE") -> OK
A16: Bloc 3 — Cheltuială cu impozitul + închiderea ei în 121
A17: Nr | B17: Cont Dr | C17: Sumă Dr | D17: Descriere Dr | E17: Cont Cr | F17: Sumă Cr | G17: Descriere Cr
A18: 1 | B18: =Declarații_INCHIDERE_EX!B19 -> 691 | C18: =Declarații_INCHIDERE_EX!B18 -> 9600 | D18: ="Cheltuială impozit " & Declarații_INCHIDERE_EX!B34 -> Cheltuială impozit — închidere exercițiu 2026 | E18: =Declarații_INCHIDERE_EX!B20 -> 441 | F18: =Declarații_INCHIDERE_EX!B18 -> 9600 | G18: ="Datorie impozit buget " & Declarații_INCHIDERE_EX!B34 -> Datorie impozit buget — închidere exercițiu 2026
A19: 2 | B19: =Declarații_INCHIDERE_EX!B29 -> 121 | C19: =Declarații_INCHIDERE_EX!B18 -> 9600 | D19: ="Închidere cheltuială impozit în rezultat " & Declarații_INCHIDERE_EX!B34 -> Închidere cheltuială impozit în rezultat — închidere exercițiu 2026 | E19: =Declarații_INCHIDERE_EX!B19 -> 691 | F19: =Declarații_INCHIDERE_EX!B18 -> 9600 | G19: ="Stingere 691 " & Declarații_INCHIDERE_EX!B34 -> Stingere 691 — închidere exercițiu 2026
A20: Check B3 | B20: =(C18+C19)-(F18+F19) -> 0 | C20: =IF(ABS(B20)<0.01,"OK","EROARE") -> OK
A22: Bloc 4 — Report rezultat net pe 117
A23: Nr | B23: Cont Dr | C23: Sumă Dr | D23: Descriere Dr | E23: Cont Cr | F23: Sumă Cr | G23: Descriere Cr
A24: 1 | B24: =IF(Declarații_INCHIDERE_EX!B26>=0,Declarații_INCHIDERE_EX!B29,Declarații_INCHIDERE_EX!B31) -> 121 | C24: =ABS(Declarații_INCHIDERE_EX!B26) -> 50400 | D24: =IF(Declarații_INCHIDERE_EX!B26>=0,"Report profit pe 117 ","Report pierdere pe 117 ") & Declarații_INCHIDERE_EX!B34 -> Report profit pe 117 — închidere exercițiu 2026 | E24: =IF(Declarații_INCHIDERE_EX!B26>=0,Declarații_INCHIDERE_EX!B31,Declarații_INCHIDERE_EX!B29) -> 117 | F24: =ABS(Declarații_INCHIDERE_EX!B26) -> 50400 | G24: =IF(Declarații_INCHIDERE_EX!B26>=0,"Rezultat reportat (profit) ","Rezultat reportat (pierdere) ") & Declarații_INCHIDERE_EX!B34 -> Rezultat reportat (profit) — închidere exercițiu 2026
A25: Check B4 | B25: =C24-F24 -> 0 | C25: =IF(ABS(B25)<0.01,"OK","EROARE") -> OK
A27: Stare terminală așteptată
A28: Sold 6xx=0 | Sold 7xx=0 | Sold 121=0 | Sold 691=0 | 441 = impozit datorat | 117 = rezultat net reportat
A30: Check global | B30: =ABS(B9)+ABS(B14)+ABS(B20)+ABS(B25) -> 0 | C30: =IF(B30<0.01,"OK — toate blocurile se închid","EROARE — cel puțin un bloc dezechilibrat") -> OK — toate blocurile se închid

Sheet NotaExport_INCHIDERE_EX
A1: MOD_INCHIDERE_EX — Notă pentru import
A2: Filtrează Include=DA. În SAGA se detaliază 6xx/7xx pe conturi individuale; aceste rânduri sunt nota de principiu.
A4: Nr | B4: Bloc | C4: Data | D4: Cont Dr | E4: Cont Cr | F4: Sumă | G4: Descriere | H4: Document | I4: Include
A5: 1 | B5: B1 Cheltuieli | C5: =Declarații_INCHIDERE_EX!B8 -> 2026-12-31 | D5: =Jurnale_INCHIDERE_EX!B8 -> 121 | E5: =Jurnale_INCHIDERE_EX!E8 -> 6xx | F5: =Jurnale_INCHIDERE_EX!C8 -> 185000 | G5: =Jurnale_INCHIDERE_EX!D8 -> Închidere cheltuieli cls.6 — închidere exercițiu 2026 | H5: Închidere exercițiu | I5: =IF(F5>0,"DA","NU") -> DA
A6: 2 | B6: B2 Venituri | C6: =Declarații_INCHIDERE_EX!B8 -> 2026-12-31 | D6: =Jurnale_INCHIDERE_EX!B13 -> 7xx | E6: =Jurnale_INCHIDERE_EX!E13 -> 121 | F6: =Jurnale_INCHIDERE_EX!C13 -> 245000 | G6: =Jurnale_INCHIDERE_EX!D13 -> Închidere venituri cls.7 — închidere exercițiu 2026 | H6: Închidere exercițiu | I6: =IF(F6>0,"DA","NU") -> DA
A7: 3 | B7: B3 Impozit | C7: =Declarații_INCHIDERE_EX!B8 -> 2026-12-31 | D7: =Jurnale_INCHIDERE_EX!B18 -> 691 | E7: =Jurnale_INCHIDERE_EX!E18 -> 441 | F7: =Jurnale_INCHIDERE_EX!C18 -> 9600 | G7: =Jurnale_INCHIDERE_EX!D18 -> Cheltuială impozit — închidere exercițiu 2026 | H7: Închidere exercițiu | I7: =IF(F7>0,"DA","NU") -> DA
A8: 4 | B8: B3 Înch.691 | C8: =Declarații_INCHIDERE_EX!B8 -> 2026-12-31 | D8: =Jurnale_INCHIDERE_EX!B19 -> 121 | E8: =Jurnale_INCHIDERE_EX!E19 -> 691 | F8: =Jurnale_INCHIDERE_EX!C19 -> 9600 | G8: =Jurnale_INCHIDERE_EX!D19 -> Închidere cheltuială impozit în rezultat — închidere exercițiu 2026 | H8: Închidere exercițiu | I8: =IF(F8>0,"DA","NU") -> DA
A9: 5 | B9: B4 Report 117 | C9: =Declarații_INCHIDERE_EX!B8 -> 2026-12-31 | D9: =Jurnale_INCHIDERE_EX!B24 -> 121 | E9: =Jurnale_INCHIDERE_EX!E24 -> 117 | F9: =Jurnale_INCHIDERE_EX!C24 -> 50400 | G9: =Jurnale_INCHIDERE_EX!D24 -> Report profit pe 117 — închidere exercițiu 2026 | H9: Închidere exercițiu | I9: =IF(F9>0,"DA","NU") -> DA
A11: Rânduri de importat | B11: =COUNTIF(I5:I9,"DA") -> 5
A12: Check global | B12: =Jurnale_INCHIDERE_EX!B30 -> 0 | C12: =IF(ABS(B12)<0.01,"OK","EROARE") -> OK

Sheet Declarații_PROVIZION
A1: MOD_PROVIZION — Declarații (input)
A2: Tipul provizionului comandă contul ȘI deductibilitatea. Valorile implicite reproduc monografia din F-106 (litigiu, 8.000 lei).
A4: 1. Antet
A5: Societate | B5: =Parametri!B5 -> SC EXEMPLU SRL
A6: Obiectul provizionului | B6: Litigiu comercial cu clientul X
A7: Data constituirii | B7: 2026-12-31 | C7: Exercițiul în care s-a NĂSCUT obligația, nu cel în care se plătește
A8: Data reluării | B8: 2027-04-30
A10: 2. Provizionul
A11: Tip (LITIGII / GARANTII / RESTRUCTURARE / IMPOZITE / TERMINARE / ALTE) | B11: LITIGII
A12: Sumă estimată | B12: 8000 | C12: Estimare credibilă la data bilanțului; se revizuiește la fiecare bilanț
A14: 3. Cheltuiala efectivă (anul următor)
A15: Sumă facturată efectiv | B15: 8000
A16: TVA pe factură | B16: =ROUND(B15*Parametri!B10,2) -> 1680
A18: 4. Calcul automat (nu edita)
A19: Cont provizion | B19: =IFERROR(VLOOKUP(B11,Reguli_PROVIZION!$A$6:$E$11,3,FALSE),"?") -> 1511
A20: Deductibil fiscal? | B20: =IFERROR(VLOOKUP(B11,Reguli_PROVIZION!$A$6:$E$11,4,FALSE),"?") -> NU
A21: Temei | B21: =IFERROR(VLOOKUP(B11,Reguli_PROVIZION!$A$6:$E$11,5,FALSE),"tip necunoscut") -> art. 26 CF nu îl enumeră printre cele deductibile
A22: Efect fiscal la constituire | B22: =IF(B20="DA",0,ROUND(B12*param_cota_impozit_profit,2)) -> 1280 | C22: Impozit suplimentar de plătit dacă provizionul e nedeductibil
A24: 5. Conturi
A25: Cont cheltuială cu provizioane | B25: 6812
A26: Cont venit din reluarea provizioanelor | B26: 7812
A27: Cont cheltuială efectivă | B27: 628 | C27: Contul real al cheltuielii — NU contul de provizion
A28: Cont TVA deductibilă | B28: 4426
A29: Cont furnizor | B29: 401
A31: 6. Controale
A32: Check tip recunoscut | B32: =B19 -> 1511 | C32: =IF(B19="?","EROARE — tip de provizion necunoscut","OK — cont " & B19) -> OK — cont 1511
A33: Check deductibilitate | B33: =B22 -> 1280 | C33: =IF(B20="DA","OK — deductibil: " & B21,"NEDEDUCTIBIL (" & B21 & "). Impozit suplimentar: " & TEXT(B22,"0.00") & " lei") -> NEDEDUCTIBIL (art. 26 CF nu îl enumeră printre cele deductibile). Impozit suplimentar: 1280.00 lei
A34: Reminder: NU e optimizare fiscală | B34: ="regulă" -> regulă | C34: =IF(B20="DA","Deductibil — dar tot nu e optimizare: doar mută cheltuiala în exercițiul corect.","Nedeductibil la constituire, iar reluarea e venit neimpozabil. Efect fiscal net pe doi ani: zero. Nu-l vinde clientului ca optimizare.") -> Nedeductibil la constituire, iar reluarea e venit neimpozabil. Efect fiscal net pe doi ani: zero. Nu-l vinde clientului ca optimizare.
A35: Reminder: factura NU atinge contul de provizion | B35: =B15 -> 8000 | C35: ="Blocul 2 înregistrează factura pe contul REAL de cheltuială. Provizionul se reia separat, în blocul 3. Cele două nu se compensează." -> Blocul 2 înregistrează factura pe contul REAL de cheltuială. Provizionul se reia separat, în blocul 3. Cele două nu se compensează.
A36: Check estimare vs. realizat | B36: =B15-B12 -> 0 | C36: =IF(ABS(B36)<0.01,"OK — estimarea s-a confirmat",IF(B36>0,"Cheltuiala a depășit provizionul cu " & TEXT(B36,"0.00") & " lei — diferența rămâne cheltuială a anului curent","Provizionul a fost supraestimat cu " & TEXT(-B36,"0.00") & " lei — reluarea rămâne la valoarea constituită")) -> OK — estimarea s-a confirmat
A38: 7. Sufix generat
A39: Sufix | B39: =" - " & B6 -> - Litigiu comercial cu clientul X

Sheet Reguli_PROVIZION
A1: MOD_PROVIZION — Reguli (tabele fixe)
A2: Tabelul A e citit de formulele din Declarații. Se editează doar când se schimbă art. 26 din Codul fiscal.
A4: Tabel A — Tipuri de provizion, cont și deductibilitate
A5: Cod | B5: Denumire | C5: Cont | D5: Deductibil | E5: Temei
A6: LITIGII | B6: Provizioane pentru litigii | C6: 1511 | D6: NU | E6: art. 26 CF nu îl enumeră printre cele deductibile
A7: GARANTII | B7: Provizioane pentru garanții acordate clienților | C7: 1512 | D7: DA | E7: art. 26 alin. (1) lit. b) CF — în limita cotei prevăzute în contracte
A8: RESTRUCTURARE | B8: Provizioane pentru restructurare | C8: 1514 | D8: NU | E8: nu figurează printre cele deductibile
A9: IMPOZITE | B9: Provizioane pentru impozite | C9: 1516 | D9: NU | E9: nu figurează printre cele deductibile
A10: TERMINARE | B10: Provizioane pentru terminarea contractului de muncă | C10: 1517 | D10: NU | E10: nu figurează printre cele deductibile
A11: ALTE | B11: Alte provizioane | C11: 1518 | D11: NU | E11: verifică art. 26 CF pentru cazul concret
A13: Tabel B — Condițiile de recunoaștere (toate trei, cumulativ)
A14: Condiție | B14: Ce înseamnă | E14: Dacă lipsește
A15: Obligație actuală | B15: din eveniment trecut, la data bilanțului | E15: Nu e provizion — e o intenție
A16: Ieșire probabilă de resurse | B16: mai degrabă da decât nu | E16: Rămâne datorie contingentă — se prezintă în note, nu se înregistrează
A17: Estimare credibilă | B17: suma se poate evalua rezonabil | E17: Se prezintă în note, fără sumă
A19: Tabel C — LIMITĂRI DECLARATE ale modulului
A20: Ce NU tratează | B20: De ce | C20: Ce faci | E20: Efect dacă îl ignori
A21: Actualizarea provizioanelor pe termen lung | B21: Provizioanele scadente peste un an se pot actualiza la valoarea prezentă. | C21: Dacă politica firmei o cere, actualizează și trece diferența pe 686/786. | E21: Provizionul e supraevaluat față de valoarea prezentă
A22: Revizuirea la fiecare bilanț | B22: Modulul tratează un ciclu constituire → reluare, nu ajustările intermediare. | C22: La fiecare bilanț, reevaluează și ajustează prin aceleași conturi. | E22: Provizionul rămâne la estimarea inițială, care poate fi depășită
A23: Provizioane pentru garanții cu cotă contractuală | B23: Deductibilitatea lor e limitată la cota din contracte, care variază. | C23: Verifică art. 26 alin. (1) lit. b) și cota din contractul concret. | E23: Partea peste cotă rămâne nedeductibilă și nesemnalată
A24: Utilizarea pentru altă cheltuială decât cea constituită | B24: Interzisă — provizionul e specific obligației. | C24: Reia provizionul vechi și constituie unul nou. | E24: Provizionul devine un cont-tampon, exact ce nu trebuie

Sheet Jurnale_PROVIZION
A1: MOD_PROVIZION — Jurnale (generate automat)
A2: Blocul 2 e INDEPENDENT de blocurile 1 și 3: factura se înregistrează pe contul real de cheltuială, nu pe contul de provizion.
A4: Bloc 1 — Constituirea provizionului (exercițiul N)
A5: Data jurnal: | B5: =Declarații_PROVIZION!B7 -> 2026-12-31
A7: Nr | B7: Cont Dr | C7: Sumă Dr | D7: Descriere Dr | E7: Cont Cr | F7: Sumă Cr | G7: Descriere Cr
A8: 1 | B8: =Declarații_PROVIZION!B25 -> 6812 | C8: =Declarații_PROVIZION!B12 -> 8000 | D8: ="Constituire provizion" & Declarații_PROVIZION!B39 -> Constituire provizion - Litigiu comercial cu clientul X | E8: =Declarații_PROVIZION!B19 -> 1511 | F8: =Declarații_PROVIZION!B12 -> 8000 | G8: ="Provizion constituit" & Declarații_PROVIZION!B39 -> Provizion constituit - Litigiu comercial cu clientul X
A10: Check Σ (structural) | B10: =C8-F8 -> 0 | C10: =IF(ABS(B10)<0.01,"OK — nota se închide","EROARE") -> OK — nota se închide
A11: Declarativ | B11: =Declarații_PROVIZION!B20 -> NU | C11: =IF(Declarații_PROVIZION!B20="DA","D101 — cheltuială deductibilă","D101 — cheltuială NEDEDUCTIBILĂ, se adaugă la rezultatul fiscal") -> D101 — cheltuială NEDEDUCTIBILĂ, se adaugă la rezultatul fiscal
A13: Bloc 2 — Factura efectivă (exercițiul N+1) — INDEPENDENT
A14: Data jurnal: | B14: =Declarații_PROVIZION!B8 -> 2027-04-30
A16: Nr | B16: Cont Dr | C16: Sumă Dr | D16: Descriere Dr | E16: Cont Cr | F16: Sumă Cr | G16: Descriere Cr
A17: 1 | B17: =Declarații_PROVIZION!B27 -> 628 | C17: =Declarații_PROVIZION!B15 -> 8000 | D17: ="Cheltuiala efectivă, pe contul ei real" & Declarații_PROVIZION!B39 -> Cheltuiala efectivă, pe contul ei real - Litigiu comercial cu clientul X | E17: =Declarații_PROVIZION!B29 -> 401 | F17: =Declarații_PROVIZION!B15+Declarații_PROVIZION!B16 -> 9680 | G17: ="Datorie față de furnizor" & Declarații_PROVIZION!B39 -> Datorie față de furnizor - Litigiu comercial cu clientul X
A18: 2 | B18: =Declarații_PROVIZION!B28 -> 4426 | C18: =Declarații_PROVIZION!B16 -> 1680 | D18: ="TVA deductibilă" & Declarații_PROVIZION!B39 -> TVA deductibilă - Litigiu comercial cu clientul X
A20: Check Σ (structural) | B20: =SUM(C17:C18)-SUM(F17:F18) -> 0 | C20: =IF(ABS(B20)<0.01,"OK — nota se închide","EROARE") -> OK — nota se închide
A21: Check: nu atinge contul de provizion | B21: =Declarații_PROVIZION!B19 -> 1511 | C21: ="Corect — factura se înregistrează pe contul real de cheltuială. Provizionul se reia separat, în blocul 3." -> Corect — factura se înregistrează pe contul real de cheltuială. Provizionul se reia separat, în blocul 3.
A23: Bloc 3 — Reluarea provizionului (exercițiul N+1)
A24: Data jurnal: | B24: =Declarații_PROVIZION!B8 -> 2027-04-30
A26: Nr | B26: Cont Dr | C26: Sumă Dr | D26: Descriere Dr | E26: Cont Cr | F26: Sumă Cr | G26: Descriere Cr
A27: 1 | B27: =Declarații_PROVIZION!B19 -> 1511 | C27: =Declarații_PROVIZION!B12 -> 8000 | D27: ="Reluarea provizionului, obligația s-a stins" & Declarații_PROVIZION!B39 -> Reluarea provizionului, obligația s-a stins - Litigiu comercial cu clientul X | E27: =Declarații_PROVIZION!B26 -> 7812 | F27: =Declarații_PROVIZION!B12 -> 8000 | G27: ="Venit din reluarea provizionului" & Declarații_PROVIZION!B39 -> Venit din reluarea provizionului - Litigiu comercial cu clientul X
A29: Check Σ (structural) | B29: =C27-F27 -> 0 | C29: =IF(ABS(B29)<0.01,"OK — nota se închide","EROARE") -> OK — nota se închide
A30: Check sold provizion după reluare | B30: =Declarații_PROVIZION!B12-Declarații_PROVIZION!B12 -> 0 | C30: =IF(ABS(B30)<0.01,"OK — soldul contului de provizion = 0","EROARE") -> OK — soldul contului de provizion = 0
A31: Efect fiscal pe cei doi ani | B31: =Declarații_PROVIZION!B22 -> 1280 | C31: =IF(Declarații_PROVIZION!B20="DA","Deductibil la constituire, impozabil la reluare — efect net zero.","Nedeductibil la constituire, neimpozabil la reluare — efect net zero. Provizionul mută cheltuiala în exercițiul corect, nu reduce impozitul.") -> Nedeductibil la constituire, neimpozabil la reluare — efect net zero. Provizionul mută cheltuiala în exercițiul corect, nu reduce impozitul.
A33: Stare terminală: contul de provizion = 0; efectul net pe rezultatul exercițiului N+1 ≈ 0, pentru că reluarea (venit) compensează cheltuiala reală.

Sheet NotaExport_PROVIZION
A1: MOD_PROVIZION — Notă pentru import (1 rând = 1 înregistrare)
A2: Blocurile 1 și 3 aparțin exercițiilor diferite. Filtrează pe Include = DA și pe dată înainte de import.
A4: Nr | B4: Bloc | C4: Data | D4: Cont Dr | E4: Cont Cr | F4: Sumă | G4: Descriere | H4: Document | I4: Include
A5: 1 | B5: Bloc 1 — Constituire | C5: =Declarații_PROVIZION!B7 -> 2026-12-31 | D5: =Jurnale_PROVIZION!B8 -> 6812 | E5: =Jurnale_PROVIZION!E8 -> 1511 | F5: =MAX(N(Jurnale_PROVIZION!C8),N(Jurnale_PROVIZION!F8)) -> 8000 | G5: =Jurnale_PROVIZION!D8 -> Constituire provizion - Litigiu comercial cu clientul X | H5: Hotărâre + estimare | I5: =IF(N(F5)>0.005,"DA","NU") -> DA
A6: 2 | B6: Bloc 2 — Factura efectivă | C6: =Declarații_PROVIZION!B8 -> 2027-04-30 | D6: =Jurnale_PROVIZION!B17 -> 628 | E6: =Jurnale_PROVIZION!E17 -> 401 | F6: =MAX(N(Jurnale_PROVIZION!C17),N(Jurnale_PROVIZION!F17)) -> 9680 | G6: =Jurnale_PROVIZION!D17 -> Cheltuiala efectivă, pe contul ei real - Litigiu comercial cu clientul X | H6: Factură furnizor | I6: =IF(N(F6)>0.005,"DA","NU") -> DA
A7: 3 | B7: Bloc 2 — Factura efectivă | C7: =Declarații_PROVIZION!B8 -> 2027-04-30 | D7: =Jurnale_PROVIZION!B18 -> 4426 | E7: =Jurnale_PROVIZION!E18 -> 0 | F7: =MAX(N(Jurnale_PROVIZION!C18),N(Jurnale_PROVIZION!F18)) -> 1680 | G7: =Jurnale_PROVIZION!D18 -> TVA deductibilă - Litigiu comercial cu clientul X | H7: Factură furnizor | I7: =IF(N(F7)>0.005,"DA","NU") -> DA
A8: 4 | B8: Bloc 3 — Reluare | C8: =Declarații_PROVIZION!B8 -> 2027-04-30 | D8: =Jurnale_PROVIZION!B27 -> 1511 | E8: =Jurnale_PROVIZION!E27 -> 7812 | F8: =MAX(N(Jurnale_PROVIZION!C27),N(Jurnale_PROVIZION!F27)) -> 8000 | G8: =Jurnale_PROVIZION!D27 -> Reluarea provizionului, obligația s-a stins - Litigiu comercial cu clientul X | H8: Notă contabilă | I8: =IF(N(F8)>0.005,"DA","NU") -> DA
A10: Rânduri de importat (Include=DA) | B10: =COUNTIF(I5:I8,"DA") -> 4

Sheet Declarații_CREDIT_VALUTA
A1: MOD_CREDIT_VALUTA — Declarații (input)
A2: Valorile implicite reproduc monografia din F-107. Rata și dobânda se iau din SCADENȚAR, nu din extras — extrasul le arată deseori cumulat.
A4: 1. Antet
A5: Societate | B5: =Parametri!B5 -> SC EXEMPLU SRL
A6: Număr contract de credit | B6: CR-2026-001 | C6: 1621 se ține analitic pe contract și pe valută
A7: Luna (AAAA-LL) | B7: 2026-07
A8: Data plății ratei | B8: 2026-07-15
A9: Data reevaluării (ultima zi bancară a lunii) | B9: 2026-07-31
A10: Valuta | B10: EUR
A12: 2. Soldul de la care pornim
A13: Sold inițial, în valută | B13: 20000
A14: Cursul la care e înregistrat soldul | B14: 4.97
A15: Sold inițial, în lei | B15: =ROUND(B13*B14,2) -> 99400
A17: 3. Mișcările lunii (din SCADENȚAR)
A18: Rata de capital, în valută | B18: 5000
A19: Dobânda, în valută | B19: 200
A20: Cursul de la data plății | B20: 4.99
A21: Comisioane bancare, în lei | B21: 50
A23: 4. Reevaluarea de la finalul lunii
A24: Curs BNR la data reevaluării | B24: 5.01
A26: 5. Calcul automat (nu edita)
A27: Rata, la cursul de înregistrare | B27: =ROUND(B18*B14,2) -> 24850
A28: Rata, la cursul de plată | B28: =ROUND(B18*B20,2) -> 24950
A29: MOMENTUL 1 — diferența la plată | B29: =B28-B27 -> 100 | C29: Pozitiv = nefavorabil (665); negativ = favorabil (765)
A30: Dobânda, în lei | B30: =ROUND(B19*B20,2) -> 998
A31: Sold rămas, în valută | B31: =B13-B18 -> 15000
A32: Sold rămas, la cursul de înregistrare | B32: =ROUND(B31*B14,2) -> 74550
A33: Sold rămas, la cursul BNR | B33: =ROUND(B31*B24,2) -> 75150
A34: MOMENTUL 2 — diferența din reevaluare | B34: =B33-B32 -> 600 | C34: Pozitiv = datoria crește = nefavorabil (665)
A36: 6. Conturi
A37: Cont credit (162x) | B37: 1621 | C37: 1621…1627 sunt sintetice DISTINCTE, nu analitice ale aceluiași cont
A38: Cont dobândă neajunsă la scadență | B38: 1682
A39: Cont trezorerie în valută | B39: 5124
A40: Cont trezorerie în lei | B40: 5121
A41: Cont cheltuială cu dobânda | B41: 666
A42: Cont cheltuială cu serviciile bancare | B42: 627
A43: Cont diferențe nefavorabile | B43: 665
A44: Cont diferențe favorabile | B44: 765
A46: 7. Controale
A47: Check FINAL: sold lei = sold valută × curs BNR | B47: =B32+B34-B33 -> 0 | C47: =IF(ABS(B47)<0.01,"OK — soldul în lei corespunde soldului în valută","EROARE — una dintre cele două diferențe de curs lipsește") -> OK — soldul în lei corespunde soldului în valută
A48: Check cele două momente sunt distincte | B48: =B29+B34 -> 700 | C48: ="Momentul 1 (la plată): " & TEXT(B29,"0.00") & " lei · Momentul 2 (reevaluare): " & TEXT(B34,"0.00") & " lei" -> Momentul 1 (la plată): 100.00 lei · Momentul 2 (reevaluare): 600.00 lei
A49: Reminder: rata și dobânda vin din scadențar | B49: =B18+B19 -> 5200 | C49: ="Extrasul arată deseori B18+B19 cumulat. Dacă le înregistrezi așa, ajungi cu 1621 pe debit sau cu sold rămas la finalul creditului." -> Extrasul arată deseori B18+B19 cumulat. Dacă le înregistrezi așa, ajungi cu 1621 pe debit sau cu sold rămas la finalul creditului.
A50: Reminder: reevaluarea e LUNARĂ | B50: =B9 -> 2026-07-31 | C50: ="Obligatorie lunar (OMFP 1802/2014), nu trimestrial. Verifică și soldul ÎN VALUTĂ, nu doar în lei." -> Obligatorie lunar (OMFP 1802/2014), nu trimestrial. Verifică și soldul ÎN VALUTĂ, nu doar în lei.
A51: Reminder bilanț | B51: =B31 -> 15000 | C51: ="Reclasifică porțiunea scadentă în ≤ 12 luni pentru bilanț, prin analitic sau cont dedicat. Dobânda calculată și neajunsă la scadență stă pe 1682." -> Reclasifică porțiunea scadentă în ≤ 12 luni pentru bilanț, prin analitic sau cont dedicat. Dobânda calculată și neajunsă la scadență stă pe 1682.
A53: 8. Sufix generat
A54: Sufix | B54: =" - " & B6 & " - " & B7 -> - CR-2026-001 - 2026-07

Sheet Reguli_CREDIT_VALUTA
A1: MOD_CREDIT_VALUTA — Reguli (tabele fixe)
A3: Tabel A — Cele două momente de diferență de curs
A4: Moment | B4: Când apare | C4: Bază | D4: Formula | E4: Cont | F4: Temei / observație
A5: 1. La plată | B5: la fiecare rambursare de rată | C5: rata în valută | D5: (curs plată − curs înregistrare) × rată | E5: 665 / 765 | F5: Diferența dintre cursul la care e înregistrată datoria și cel la care se stinge
A6: 2. La reevaluare | B6: ultima zi bancară a FIECĂREI luni | C6: soldul rămas în valută | D6: (curs BNR − curs înregistrare) × sold rămas | E6: 665 / 765 | F6: OMFP 1802/2014 — obligatoriu lunar; „la 3 luni” e insuficient
A8: Tabel B — Ce se ia din scadențar, nu din extras
A9: Element | B9: Cont | F9: De ce contează
A10: Rata de capital | B10: 1621 | F10: Stinge datoria. Dacă o umfli cu dobânda, 1621 ajunge pe debit
A11: Dobânda | B11: 666 | F11: Cheltuială financiară. Dacă o pui pe 1621, rămâi cu sold la finalul creditului
A12: Comisioane | B12: 627 | F12: Cheltuială cu serviciile bancare, separată de dobândă
A13: Dobânda neajunsă la scadență | B13: 1682 | F13: Se calculează, nu se plătește încă
A15: Tabel C — LIMITĂRI DECLARATE ale modulului
A16: Ce NU tratează | B16: De ce | C16: Ce faci | F16: Efect dacă îl ignori
A17: Linii de credit revolving | B17: Soldul fluctuează în ambele sensuri în cursul lunii, deci nu există o „rată” unică. | C17: Reevaluează soldul la finalul lunii; tratează tragerile separat. | F17: Diferențele de curs pe trageri intermediare rămân neînregistrate
A18: Instrumente de acoperire a riscului valutar (hedging) | B18: Contabilitatea de acoperire are reguli proprii (OMFP 1802, cap. dedicat). | C18: Tratează separat; nu compensa în 665/765. | F18: Rezultatul financiar apare volatil fără motiv
A19: Credite cu dobândă variabilă recalculată retroactiv | B19: Recalculul schimbă scadențarul pe perioade deja înregistrate. | C19: Reia scadențarul nou și corectează perioadele afectate. | F19: Dobânda înregistrată nu corespunde cu cea datorată
A20: Costuri de tranzacție amortizate (metoda dobânzii efective) | B20: Comisioanele inițiale se pot amortiza pe durata creditului. | C20: Dacă politica firmei o cere, tratează prin 471. | F20: Cheltuiala e recunoscută integral în prima lună

Sheet Jurnale_CREDIT_VALUTA
A1: MOD_CREDIT_VALUTA — Jurnale (generate automat)
A2: Blocurile de diferență se activează după semn: nefavorabilă pe 665, favorabilă pe 765. Doar unul dintre ele are sumă.
A4: Bloc 1 — Rata de capital și diferența la plată
A5: Data jurnal: | B5: =Declarații_CREDIT_VALUTA!B8 -> 2026-07-15
A7: Nr | B7: Cont Dr | C7: Sumă Dr | D7: Descriere Dr | E7: Cont Cr | F7: Sumă Cr | G7: Descriere Cr
A8: 1 | B8: =Declarații_CREDIT_VALUTA!B37 -> 1621 | C8: =Declarații_CREDIT_VALUTA!B27 -> 24850 | D8: ="Rambursare rată de capital" & Declarații_CREDIT_VALUTA!B54 -> Rambursare rată de capital - CR-2026-001 - 2026-07 | E8: =Declarații_CREDIT_VALUTA!B39 -> 5124 | F8: =Declarații_CREDIT_VALUTA!B28 -> 24950 | G8: ="Plata ratei din contul în valută" & Declarații_CREDIT_VALUTA!B54 -> Plata ratei din contul în valută - CR-2026-001 - 2026-07
A9: 2 | B9: =Declarații_CREDIT_VALUTA!B43 -> 665 | C9: =MAX(0,Declarații_CREDIT_VALUTA!B29) -> 100 | D9: ="Diferență de curs nefavorabilă la plată" & Declarații_CREDIT_VALUTA!B54 -> Diferență de curs nefavorabilă la plată - CR-2026-001 - 2026-07
A10: 3 | E10: =Declarații_CREDIT_VALUTA!B44 -> 765 | F10: =MAX(0,-Declarații_CREDIT_VALUTA!B29) -> 0 | G10: ="Diferență de curs favorabilă la plată" & Declarații_CREDIT_VALUTA!B54 -> Diferență de curs favorabilă la plată - CR-2026-001 - 2026-07
A12: Check Σ (structural) | B12: =SUM(C8:C10)-SUM(F8:F10) -> 0 | C12: =IF(ABS(B12)<0.01,"OK — nota se închide","EROARE") -> OK — nota se închide
A13: Check exclusivitate 665/665 | B13: =IF(AND(C9>0.005,F10>0.005),1,0) -> 0 | C13: =IF(B13=0,"OK — o singură diferență, într-un singur sens","EROARE — 665 și 765 nu pot avea ambele sumă") -> OK — o singură diferență, într-un singur sens
A15: Bloc 2 — Dobânda
A16: Data jurnal: | B16: =Declarații_CREDIT_VALUTA!B8 -> 2026-07-15
A18: Nr | B18: Cont Dr | C18: Sumă Dr | D18: Descriere Dr | E18: Cont Cr | F18: Sumă Cr | G18: Descriere Cr
A19: 1 | B19: =Declarații_CREDIT_VALUTA!B41 -> 666 | C19: =Declarații_CREDIT_VALUTA!B30 -> 998 | D19: ="Dobândă aferentă creditului" & Declarații_CREDIT_VALUTA!B54 -> Dobândă aferentă creditului - CR-2026-001 - 2026-07 | E19: =Declarații_CREDIT_VALUTA!B39 -> 5124 | F19: =Declarații_CREDIT_VALUTA!B30 -> 998 | G19: ="Plata dobânzii din contul în valută" & Declarații_CREDIT_VALUTA!B54 -> Plata dobânzii din contul în valută - CR-2026-001 - 2026-07
A21: Check Σ (structural) | B21: =C19-F19 -> 0 | C21: =IF(ABS(B21)<0.01,"OK — nota se închide","EROARE") -> OK — nota se închide
A23: Bloc 3 — Comisioane bancare
A24: Data jurnal: | B24: =Declarații_CREDIT_VALUTA!B8 -> 2026-07-15
A26: Nr | B26: Cont Dr | C26: Sumă Dr | D26: Descriere Dr | E26: Cont Cr | F26: Sumă Cr | G26: Descriere Cr
A27: 1 | B27: =Declarații_CREDIT_VALUTA!B42 -> 627 | C27: =Declarații_CREDIT_VALUTA!B21 -> 50 | D27: ="Comisioane bancare aferente creditului" & Declarații_CREDIT_VALUTA!B54 -> Comisioane bancare aferente creditului - CR-2026-001 - 2026-07 | E27: =Declarații_CREDIT_VALUTA!B40 -> 5121 | F27: =Declarații_CREDIT_VALUTA!B21 -> 50 | G27: ="Plata comisioanelor" & Declarații_CREDIT_VALUTA!B54 -> Plata comisioanelor - CR-2026-001 - 2026-07
A29: Check Σ (structural) | B29: =C27-F27 -> 0 | C29: =IF(ABS(B29)<0.01,"OK — nota se închide","EROARE") -> OK — nota se închide
A31: Bloc 4 — Reevaluarea soldului (PASUL CARE SE UITĂ)
A32: Data jurnal: | B32: =Declarații_CREDIT_VALUTA!B9 -> 2026-07-31
A34: Nr | B34: Cont Dr | C34: Sumă Dr | D34: Descriere Dr | E34: Cont Cr | F34: Sumă Cr | G34: Descriere Cr
A35: 1 | B35: =Declarații_CREDIT_VALUTA!B43 -> 665 | C35: =MAX(0,Declarații_CREDIT_VALUTA!B34) -> 600 | D35: ="Reevaluare sold credit — diferență nefavorabilă" & Declarații_CREDIT_VALUTA!B54 -> Reevaluare sold credit — diferență nefavorabilă - CR-2026-001 - 2026-07 | E35: =Declarații_CREDIT_VALUTA!B37 -> 1621 | F35: =MAX(0,Declarații_CREDIT_VALUTA!B34) -> 600 | G35: ="Creșterea datoriei din reevaluare" & Declarații_CREDIT_VALUTA!B54 -> Creșterea datoriei din reevaluare - CR-2026-001 - 2026-07
A36: 2 | B36: =Declarații_CREDIT_VALUTA!B37 -> 1621 | C36: =MAX(0,-Declarații_CREDIT_VALUTA!B34) -> 0 | D36: ="Diminuarea datoriei din reevaluare" & Declarații_CREDIT_VALUTA!B54 -> Diminuarea datoriei din reevaluare - CR-2026-001 - 2026-07 | E36: =Declarații_CREDIT_VALUTA!B44 -> 765 | F36: =MAX(0,-Declarații_CREDIT_VALUTA!B34) -> 0 | G36: ="Reevaluare sold credit — diferență favorabilă" & Declarații_CREDIT_VALUTA!B54 -> Reevaluare sold credit — diferență favorabilă - CR-2026-001 - 2026-07
A38: Check Σ (structural) | B38: =SUM(C35:C36)-SUM(F35:F36) -> 0 | C38: =IF(ABS(B38)<0.01,"OK — nota se închide","EROARE") -> OK — nota se închide
A39: Check sold final | B39: =Declarații_CREDIT_VALUTA!B33 -> 75150 | C39: ="Sold 1621 după reevaluare = " & TEXT(B39,"0.00") & " lei = " & TEXT(Declarații_CREDIT_VALUTA!B31,"0") & " " & Declarații_CREDIT_VALUTA!B10 & " × " & TEXT(Declarații_CREDIT_VALUTA!B24,"0.0000") -> Sold 1621 după reevaluare = 75150.00 lei = 15000 EUR × 5.0100
A41: Stare terminală: soldul lui 1621 în lei = soldul în valută × cursul BNR de la data reevaluării. Dacă nu ține, unul dintre cele două momente lipsește.

Sheet NotaExport_CREDIT_VALUTA
A1: MOD_CREDIT_VALUTA — Notă pentru import (1 rând = 1 înregistrare)
A2: Filtrează pe Include = DA. Rândurile de diferență cu sumă zero ies singure.
A4: Nr | B4: Bloc | C4: Data | D4: Cont Dr | E4: Cont Cr | F4: Sumă | G4: Descriere | H4: Document | I4: Include
A5: 1 | B5: Bloc 1 — Rata + diferență | C5: =Declarații_CREDIT_VALUTA!B8 -> 2026-07-15 | D5: =Jurnale_CREDIT_VALUTA!B8 -> 1621 | E5: =Jurnale_CREDIT_VALUTA!E8 -> 5124 | F5: =MAX(N(Jurnale_CREDIT_VALUTA!C8),N(Jurnale_CREDIT_VALUTA!F8)) -> 24950 | G5: =Jurnale_CREDIT_VALUTA!D8 -> Rambursare rată de capital - CR-2026-001 - 2026-07 | H5: Scadențar + extras | I5: =IF(N(F5)>0.005,"DA","NU") -> DA
A6: 2 | B6: Bloc 1 — Rata + diferență | C6: =Declarații_CREDIT_VALUTA!B8 -> 2026-07-15 | D6: =Jurnale_CREDIT_VALUTA!B9 -> 665 | E6: =Jurnale_CREDIT_VALUTA!E9 -> 0 | F6: =MAX(N(Jurnale_CREDIT_VALUTA!C9),N(Jurnale_CREDIT_VALUTA!F9)) -> 100 | G6: =Jurnale_CREDIT_VALUTA!D9 -> Diferență de curs nefavorabilă la plată - CR-2026-001 - 2026-07 | H6: Scadențar + extras | I6: =IF(N(F6)>0.005,"DA","NU") -> DA
A7: 3 | B7: Bloc 1 — Rata + diferență | C7: =Declarații_CREDIT_VALUTA!B8 -> 2026-07-15 | D7: =Jurnale_CREDIT_VALUTA!B10 -> 0 | E7: =Jurnale_CREDIT_VALUTA!E10 -> 765 | F7: =MAX(N(Jurnale_CREDIT_VALUTA!C10),N(Jurnale_CREDIT_VALUTA!F10)) -> 0 | G7: =Jurnale_CREDIT_VALUTA!D10 -> 0 | H7: Scadențar + extras | I7: =IF(N(F7)>0.005,"DA","NU") -> NU
A8: 4 | B8: Bloc 2 — Dobânda | C8: =Declarații_CREDIT_VALUTA!B8 -> 2026-07-15 | D8: =Jurnale_CREDIT_VALUTA!B19 -> 666 | E8: =Jurnale_CREDIT_VALUTA!E19 -> 5124 | F8: =MAX(N(Jurnale_CREDIT_VALUTA!C19),N(Jurnale_CREDIT_VALUTA!F19)) -> 998 | G8: =Jurnale_CREDIT_VALUTA!D19 -> Dobândă aferentă creditului - CR-2026-001 - 2026-07 | H8: Scadențar + extras | I8: =IF(N(F8)>0.005,"DA","NU") -> DA
A9: 5 | B9: Bloc 3 — Comisioane | C9: =Declarații_CREDIT_VALUTA!B8 -> 2026-07-15 | D9: =Jurnale_CREDIT_VALUTA!B27 -> 627 | E9: =Jurnale_CREDIT_VALUTA!E27 -> 5121 | F9: =MAX(N(Jurnale_CREDIT_VALUTA!C27),N(Jurnale_CREDIT_VALUTA!F27)) -> 50 | G9: =Jurnale_CREDIT_VALUTA!D27 -> Comisioane bancare aferente creditului - CR-2026-001 - 2026-07 | H9: Scadențar + extras | I9: =IF(N(F9)>0.005,"DA","NU") -> DA
A10: 6 | B10: Bloc 4 — Reevaluare | C10: =Declarații_CREDIT_VALUTA!B9 -> 2026-07-31 | D10: =Jurnale_CREDIT_VALUTA!B35 -> 665 | E10: =Jurnale_CREDIT_VALUTA!E35 -> 1621 | F10: =MAX(N(Jurnale_CREDIT_VALUTA!C35),N(Jurnale_CREDIT_VALUTA!F35)) -> 600 | G10: =Jurnale_CREDIT_VALUTA!D35 -> Reevaluare sold credit — diferență nefavorabilă - CR-2026-001 - 2026-07 | H10: Scadențar + extras | I10: =IF(N(F10)>0.005,"DA","NU") -> DA
A11: 7 | B11: Bloc 4 — Reevaluare | C11: =Declarații_CREDIT_VALUTA!B9 -> 2026-07-31 | D11: =Jurnale_CREDIT_VALUTA!B36 -> 1621 | E11: =Jurnale_CREDIT_VALUTA!E36 -> 765 | F11: =MAX(N(Jurnale_CREDIT_VALUTA!C36),N(Jurnale_CREDIT_VALUTA!F36)) -> 0 | G11: =Jurnale_CREDIT_VALUTA!D36 -> Diminuarea datoriei din reevaluare - CR-2026-001 - 2026-07 | H11: Scadențar + extras | I11: =IF(N(F11)>0.005,"DA","NU") -> NU
A13: Rânduri de importat (Include=DA) | B13: =COUNTIF(I5:I11,"DA") -> 5

Sheet Declarații_LEASING_FIN
A1: MOD_LEASING_FIN — Declarații (input)
A2: Valorile implicite reproduc monografia din trainingul 07.08.2026 (contract 150.000, avans 50.000, rată 2.000, dobândă 500, comision 100, CASCO 20).
A4: 1. Antet
A5: Societate | B5: =Parametri!B5 -> SC EXEMPLU SRL
A6: Număr contract de leasing | B6: LF-2026-001 | C6: 167 este 1-la-1 cu contractul (C-19)
A7: Luna | B7: 2026-07
A8: Data facturii de avans | B8: 2026-07-01
A9: Data recepției bunului | B9: 2026-07-10
A10: Data facturii lunare | B10: 2026-07-31
A12: 2. Contract
A13: Valoare de intrare din contract (fără TVA) | B13: 150000
A14: Avans (fără TVA) | B14: 50000
A15: Durata de amortizare (luni) | B15: 60
A16: Cotă TVA | B16: =Parametri!B10 -> 0.21
A18: 3. Regim fiscal al vehiculului
A19: Regim (MIXT / EXCLUSIV / EXCEPTAT) | B19: MIXT | C19: MIXT = 50%. EXCLUSIV/EXCEPTAT = 100%, dar cere documentație (foi de parcurs, decizie internă)
A20: Procent de deducere aplicat | B20: =IF(B19="MIXT",param_proc_vehicul,1) -> 0.5
A21: TVA nededusă pe rata de capital: CAPITALIZEAZA / CHELTUIALA | B21: CAPITALIZEAZA | C21: ❓ De clarificat cu formatorul — practica e împărțită. Capitalizarea e coerentă cu tratamentul avansului (pct. 75 OMFP 1802)
A23: 4. Factura lunară de leasing
A24: Rata de capital | B24: 2000
A25: Dobândă | B25: 500
A26: Comision de administrare | B26: 100
A27: CASCO (fără TVA) | B27: 20
A29: 5. Calcul — intrarea bunului (nu edita)
A30: TVA pe avans | B30: =B14*B16 -> 10500
A31: TVA nedeductibilă pe avans (capitalizată) | B31: =ROUND(B30*(1-B20),2) -> 5250
A32: Valoare de intrare a mijlocului fix | B32: =B13+B31 -> 155250 | C32: 150.000 + 5.250 = 155.250 în exemplul din training
A33: Amortizare contabilă lunară | B33: =ROUND(B32/B15,2) -> 2587.5
A34: Amortizare deductibilă fiscal | B34: =MIN(B33,param_plafon_amo_auto) -> 1500 | C34: Plafon 1.500 lei/lună, art. 28 alin. (14) CF
A35: Amortizare NEdeductibilă lunară | B35: =B33-B34 -> 1087.5
A37: 6. Calcul — factura lunară (nu edita)
A38: TVA pe rata de capital | B38: =B24*B16 -> 420
A39: TVA pe dobândă | B39: =B25*B16 -> 105
A40: TVA pe comision | B40: =B26*B16 -> 21
A41: TVA total pe factură | B41: =B38+B39+B40 -> 546 | C41: CASCO e fără TVA
A42: Total factură | B42: =B24+B25+B26+B27+B41 -> 3166
A44: 7. Calcul — corecția TVA nedeductibilă (limitarea 1)
A45: TVA nededusă — rată | B45: =ROUND(B38*(1-B20),2) -> 210
A46: TVA nededusă — dobândă | B46: =ROUND(B39*(1-B20),2) -> 52.5
A47: TVA nededusă — comision | B47: =ROUND(B40*(1-B20),2) -> 10.5
A48: TVA nededusă total | B48: =B45+B46+B47 -> 273
A50: 8. Calcul — limitarea de 50% a cheltuielilor (limitarea 2)
A51: Baza include TVA nedeductibilă deja trecută pe cheltuială. Amortizarea NU intră aici — are propria plafonare (limitarea 3).
A52: Bază dobândă (dobândă + TVA nededusă) | B52: =B25+B46 -> 552.5
A53: Bază comision (comision + TVA nededusă) | B53: =B26+B47 -> 110.5
A54: Bază CASCO | B54: =B27 -> 20
A55: Dobândă nedeductibilă | B55: =ROUND(B52*(1-B20),2) -> 276.25
A56: Comision nedeductibil | B56: =ROUND(B53*(1-B20),2) -> 55.25
A57: CASCO nedeductibil | B57: =ROUND(B54*(1-B20),2) -> 10
A59: 9. Controale
A60: Check valoare de intrare | B60: =B32 -> 155250 | C60: =IF(B19="MIXT",IF(ABS(B32-(B13+B30*0.5))<0.01,"OK — include TVA nedeductibilă pe avans","EROARE"),"OK — regim cu deducere integrală, fără TVA capitalizată") -> OK — include TVA nedeductibilă pe avans
A61: Check cele trei limitări | B61: =B35+B48+B55+B56+B57 -> 1702 | C61: ="Nedeductibil lunar total: " & TEXT(B35+B55+B56+B57,"0.00") & " lei (din care amortizare " & TEXT(B35,"0.00") & ")" -> Nedeductibil lunar total: 1429.00 lei (din care amortizare 1087.50)
A62: Check plafon amortizare | B62: =B33 -> 2587.5 | C62: =IF(B33>param_plafon_amo_auto,"ATENȚIE — amortizarea contabilă depășește plafonul de 1.500 lei/lună; diferența e nedeductibilă","OK — sub plafon") -> ATENȚIE — amortizarea contabilă depășește plafonul de 1.500 lei/lună; diferența e nedeductibilă
A63: Reminder: amortizarea NU se limitează cu 50% | B63: ="regulă" -> regulă | C63: ="Amortizarea are propria plafonare (1.500 lei/lună). Nu se aplică și 50% peste ea — ar fi dublă limitare." -> Amortizarea are propria plafonare (1.500 lei/lună). Nu se aplică și 50% peste ea — ar fi dublă limitare.
A64: Reminder impozit local | B64: =B6 -> LF-2026-001 | C64: ="Declarație la primărie în 30 de zile. La leasing financiar, impozitul pe mijlocul de transport e datorat de LOCATAR pe toată durata contractului." -> Declarație la primărie în 30 de zile. La leasing financiar, impozitul pe mijlocul de transport e datorat de LOCATAR pe toată durata contractului.
A66: 10. Conturi
A67: Cont avans imobilizări | B67: 4093
A68: Cont mijloc fix | B68: 2133
A69: Cont amortizare | B69: 2813
A70: Cont datorie leasing (analitic pe contract) | B70: 167.LF-2026-001
A71: Cont furnizor de imobilizări | B71: 404
A72: Cont TVA deductibilă | B72: 4426
A73: Cont dobândă | B73: 666
A74: Cont comision | B74: 628 | C74: Poate fi și 627 — fii consecvent cu politica firmei
A75: Cont primă de asigurare | B75: 613
A76: Cont dobândă nedeductibilă | B76: 666.NED
A77: Cont comision nedeductibil | B77: 628.NED
A78: Cont CASCO nedeductibil | B78: 613.NED | C78: ⚠ NU 615 — acela e cheltuieli cu pregătirea personalului
A79: Cont cheltuială pentru TVA nededusă pe rată | B79: 6588
A80: Cont cheltuială cu amortizarea | B80: 6811
A82: 11. Sufix generat
A83: Sufix | B83: ="— leasing " & B6 & " " & B7 -> — leasing LF-2026-001 2026-07
A85: Modul activ în CatalogModule? | B85: =IF(INDEX(CatalogModule!$A$1:$A$200,MATCH("MOD_LEASING_FIN",CatalogModule!$B$1:$B$200,0))="DA","ACTIV — jurnalele se generează","INACTIV — jurnalele rămân goale") -> INACTIV — jurnalele rămân goale

Sheet Reguli_LEASING_FIN
A1: MOD_LEASING_FIN — Reguli (tabele fixe)
A2: Se editează doar când se schimbă legea.
A4: Tabel A — Cele trei limitări fiscale (se aplică simultan, pe baze diferite)
A5: # | B5: Limitare | C5: Bază de aplicare | D5: Procent / plafon | E5: Temei | F5: Observație
A6: 1 | B6: TVA deductibilă | C6: TVA de pe TOATE facturile aferente vehiculului | D6: 50% | E6: art. 298 CF | F6: Inclusiv avansul și factura lunară
A7: 2 | B7: Cheltuieli deductibile | C7: combustibil, întreținere, piese, chirii, asigurări, dobânzi, comisioane, diferențe de curs, INCLUSIV TVA nedeductibilă trecută pe cheltuială | D7: 50% | E7: art. 25 alin. (3) lit. l) CF | F7: Deductibilitate limitată la UN SINGUR autoturism per persoană cu funcție de conducere (art. 25 alin. 3 lit. m)
A8: 3 | B8: Amortizare | C8: amortizarea contabilă a fiecărui autoturism | D8: max. 1.500 lei/lună | E8: art. 28 alin. (14) CF | F8: ⚠ NU intră sub limitarea de 50% — cele două nu se cumulează
A10: Tabel B — Operațional vs. financiar
A11: Criteriu | B11: Operațional | C11: Financiar | F11: Observație
A12: Bunul în bilanț | B12: NU — rămâne la locator | C12: DA — 2133
A13: Datoria | B13: nu se înregistrează | C13: 167 | F13: 167 e 1:1 cu contractul (C-19)
A14: Cheltuiala lunară | B14: 612 chirie | C14: 666 dobândă + amortizare
A15: Evidență extrabilanțieră | B15: 8036 | C15: —
A16: Impozit local | B16: plătit de locator | C16: plătit de LOCATAR, pe toată durata | F16: Declarație la primărie în 30 de zile
A17: Valoarea reziduală | B17: achiziție nouă la final | C17: deja capitalizată | F17: La operațional, mijlocul fix apare abia la final
A19: Tabel C — Excepții de la regimul de 50%
A20: Urgență / pază / curierat · agenți de vânzări și achiziții · taxi · închiriere · școli de șoferi · transport de persoane cu plată.
A21: Fără documentație (foi de parcurs, decizie internă), regimul prudent și conform este MIXT (50%).
A23: Tabel D — Porți de calitate
A24: • ΣDr = ΣCr pe fiecare bloc
A25: • Valoarea de intrare include TVA nedeductibilă pe avans (taxe nerecuperabile în cost)
A26: • Sold 167 pe contract = sold din scadențar, în valuta contractului (C-19)
A27: • Avansul 4093 se închide integral în 167 la recepție
A28: • Amortizarea contabilă se calculează pe valoarea de intrare COMPLETĂ, nu pe cea din contract
A29: • Nedeductibilul lunar = amortizare peste plafon + 50% din dobândă/comision/CASCO
A30: • Verifică rata de schimb de pe factură față de scadențar (altfel reevaluarea e greșită)

Sheet Jurnale_LEASING_FIN
A1: MOD_LEASING_FIN — Jurnale (generate automat)
A2: Blocurile 1–4 se rulează o singură dată, la deschiderea contractului. Blocurile 5–8 se rulează lunar.
A4: Bloc 1 — Factura de avans
A5: Data jurnal: | B5: =Declarații_LEASING_FIN!B8 -> 2026-07-01
A7: Nr | B7: Cont Dr | C7: Sumă Dr | D7: Descriere Dr | E7: Cont Cr | F7: Sumă Cr | G7: Descriere Cr
A8: 1 | B8: =Declarații_LEASING_FIN!B67 -> 4093 | C8: =Declarații_LEASING_FIN!B14 -> 50000 | D8: ="Avans leasing " & Declarații_LEASING_FIN!B83 -> Avans leasing — leasing LF-2026-001 2026-07 | E8: =Declarații_LEASING_FIN!B71 -> 404 | F8: =Declarații_LEASING_FIN!B14 -> 50000 | G8: ="Datorie societate de leasing — avans " & Declarații_LEASING_FIN!B83 -> Datorie societate de leasing — avans — leasing LF-2026-001 2026-07
A9: 2 | B9: =Declarații_LEASING_FIN!B72 -> 4426 | C9: =Declarații_LEASING_FIN!B30 -> 10500 | D9: ="TVA pe avans " & Declarații_LEASING_FIN!B83 -> TVA pe avans — leasing LF-2026-001 2026-07 | E9: =Declarații_LEASING_FIN!B71 -> 404 | F9: =Declarații_LEASING_FIN!B30 -> 10500 | G9: ="Datorie — TVA avans " & Declarații_LEASING_FIN!B83 -> Datorie — TVA avans — leasing LF-2026-001 2026-07
A11: Bloc 2 — TVA nedeductibilă pe avans, capitalizată
A12: Nr | B12: Cont Dr | C12: Sumă Dr | D12: Descriere Dr | E12: Cont Cr | F12: Sumă Cr | G12: Descriere Cr
A13: 1 | B13: =Declarații_LEASING_FIN!B68 -> 2133 | C13: =Declarații_LEASING_FIN!B31 -> 5250 | D13: ="TVA nedeductibilă capitalizată în cost " & Declarații_LEASING_FIN!B83 -> TVA nedeductibilă capitalizată în cost — leasing LF-2026-001 2026-07 | E13: =Declarații_LEASING_FIN!B72 -> 4426 | F13: =Declarații_LEASING_FIN!B31 -> 5250 | G13: ="Stingere TVA nedeductibilă " & Declarații_LEASING_FIN!B83 -> Stingere TVA nedeductibilă — leasing LF-2026-001 2026-07
A15: Bloc 3 — Recepția bunului și nașterea datoriei
A16: Data jurnal: | B16: =Declarații_LEASING_FIN!B9 -> 2026-07-10
A18: Nr | B18: Cont Dr | C18: Sumă Dr | D18: Descriere Dr | E18: Cont Cr | F18: Sumă Cr | G18: Descriere Cr
A19: 1 | B19: =Declarații_LEASING_FIN!B68 -> 2133 | C19: =Declarații_LEASING_FIN!B13 -> 150000 | D19: ="Intrare autoturism în patrimoniu " & Declarații_LEASING_FIN!B83 -> Intrare autoturism în patrimoniu — leasing LF-2026-001 2026-07 | E19: =Declarații_LEASING_FIN!B70 -> 167.LF-2026-001 | F19: =Declarații_LEASING_FIN!B13 -> 150000 | G19: ="Datorie leasing financiar " & Declarații_LEASING_FIN!B83 -> Datorie leasing financiar — leasing LF-2026-001 2026-07
A21: Bloc 4 — Închiderea avansului
A22: Nr | B22: Cont Dr | C22: Sumă Dr | D22: Descriere Dr | E22: Cont Cr | F22: Sumă Cr | G22: Descriere Cr
A23: 1 | B23: =Declarații_LEASING_FIN!B70 -> 167.LF-2026-001 | C23: =Declarații_LEASING_FIN!B14 -> 50000 | D23: ="Închidere avans în datoria de leasing " & Declarații_LEASING_FIN!B83 -> Închidere avans în datoria de leasing — leasing LF-2026-001 2026-07 | E23: =Declarații_LEASING_FIN!B67 -> 4093 | F23: =Declarații_LEASING_FIN!B14 -> 50000 | G23: ="Stingere avans 4093 " & Declarații_LEASING_FIN!B83 -> Stingere avans 4093 — leasing LF-2026-001 2026-07
A25: Bloc 5 — Factura lunară de leasing (la valoarea ei, fără split)
A26: Data jurnal: | B26: =Declarații_LEASING_FIN!B10 -> 2026-07-31
A28: Nr | B28: Cont Dr | C28: Sumă Dr | D28: Descriere Dr | E28: Cont Cr | F28: Sumă Cr | G28: Descriere Cr
A29: 1 | B29: =Declarații_LEASING_FIN!B70 -> 167.LF-2026-001 | C29: =Declarații_LEASING_FIN!B24 -> 2000 | D29: ="Rata de capital " & Declarații_LEASING_FIN!B83 -> Rata de capital — leasing LF-2026-001 2026-07 | E29: =Declarații_LEASING_FIN!B71 -> 404 | F29: =Declarații_LEASING_FIN!B24 -> 2000 | G29: ="Factura lunară — capital " & Declarații_LEASING_FIN!B83 -> Factura lunară — capital — leasing LF-2026-001 2026-07
A30: 2 | B30: =Declarații_LEASING_FIN!B73 -> 666 | C30: =Declarații_LEASING_FIN!B25 -> 500 | D30: ="Dobândă de leasing " & Declarații_LEASING_FIN!B83 -> Dobândă de leasing — leasing LF-2026-001 2026-07 | E30: =Declarații_LEASING_FIN!B71 -> 404 | F30: =Declarații_LEASING_FIN!B25 -> 500 | G30: ="Factura lunară — dobândă " & Declarații_LEASING_FIN!B83 -> Factura lunară — dobândă — leasing LF-2026-001 2026-07
A31: 3 | B31: =Declarații_LEASING_FIN!B74 -> 628 | C31: =Declarații_LEASING_FIN!B26 -> 100 | D31: ="Comision de administrare " & Declarații_LEASING_FIN!B83 -> Comision de administrare — leasing LF-2026-001 2026-07 | E31: =Declarații_LEASING_FIN!B71 -> 404 | F31: =Declarații_LEASING_FIN!B26 -> 100 | G31: ="Factura lunară — comision " & Declarații_LEASING_FIN!B83 -> Factura lunară — comision — leasing LF-2026-001 2026-07
A32: 4 | B32: =Declarații_LEASING_FIN!B75 -> 613 | C32: =Declarații_LEASING_FIN!B27 -> 20 | D32: ="Primă CASCO " & Declarații_LEASING_FIN!B83 -> Primă CASCO — leasing LF-2026-001 2026-07 | E32: =Declarații_LEASING_FIN!B71 -> 404 | F32: =Declarații_LEASING_FIN!B27 -> 20 | G32: ="Factura lunară — CASCO " & Declarații_LEASING_FIN!B83 -> Factura lunară — CASCO — leasing LF-2026-001 2026-07
A33: 5 | B33: =Declarații_LEASING_FIN!B72 -> 4426 | C33: =Declarații_LEASING_FIN!B41 -> 546 | D33: ="TVA pe factura de leasing " & Declarații_LEASING_FIN!B83 -> TVA pe factura de leasing — leasing LF-2026-001 2026-07 | E33: =Declarații_LEASING_FIN!B71 -> 404 | F33: =Declarații_LEASING_FIN!B41 -> 546 | G33: ="Factura lunară — TVA " & Declarații_LEASING_FIN!B83 -> Factura lunară — TVA — leasing LF-2026-001 2026-07
A35: Bloc 6 — Corecția TVA nedeductibilă (limitarea 1: 50%)
A36: Nr | B36: Cont Dr | C36: Sumă Dr | D36: Descriere Dr | E36: Cont Cr | F36: Sumă Cr | G36: Descriere Cr
A37: 1 | B37: =IF(Declarații_LEASING_FIN!B21="CAPITALIZEAZA",Declarații_LEASING_FIN!B68,Declarații_LEASING_FIN!B79) -> 2133 | C37: =Declarații_LEASING_FIN!B45 -> 210 | D37: ="TVA nededusă pe rata de capital — " & IF(Declarații_LEASING_FIN!B21="CAPITALIZEAZA","capitalizată","pe cheltuială") & " " & Declarații_LEASING_FIN!B83 -> TVA nededusă pe rata de capital — capitalizată — leasing LF-2026-001 2026-07 | E37: =Declarații_LEASING_FIN!B72 -> 4426 | F37: =Declarații_LEASING_FIN!B45 -> 210 | G37: ="Stingere TVA nededusă — rată " & Declarații_LEASING_FIN!B83 -> Stingere TVA nededusă — rată — leasing LF-2026-001 2026-07
A38: 2 | B38: =Declarații_LEASING_FIN!B73 -> 666 | C38: =Declarații_LEASING_FIN!B46 -> 52.5 | D38: ="TVA nededusă pe dobândă " & Declarații_LEASING_FIN!B83 -> TVA nededusă pe dobândă — leasing LF-2026-001 2026-07 | E38: =Declarații_LEASING_FIN!B72 -> 4426 | F38: =Declarații_LEASING_FIN!B46 -> 52.5 | G38: ="Stingere TVA nededusă — dobândă " & Declarații_LEASING_FIN!B83 -> Stingere TVA nededusă — dobândă — leasing LF-2026-001 2026-07
A39: 3 | B39: =Declarații_LEASING_FIN!B74 -> 628 | C39: =Declarații_LEASING_FIN!B47 -> 10.5 | D39: ="TVA nededusă pe comision " & Declarații_LEASING_FIN!B83 -> TVA nededusă pe comision — leasing LF-2026-001 2026-07 | E39: =Declarații_LEASING_FIN!B72 -> 4426 | F39: =Declarații_LEASING_FIN!B47 -> 10.5 | G39: ="Stingere TVA nededusă — comision " & Declarații_LEASING_FIN!B83 -> Stingere TVA nededusă — comision — leasing LF-2026-001 2026-07
A41: Bloc 7 — Limitarea de 50% a cheltuielilor (limitarea 2)
A42: Reclasificare pe analitice nedeductibile. Amortizarea NU apare aici.
A43: Nr | B43: Cont Dr | C43: Sumă Dr | D43: Descriere Dr | E43: Cont Cr | F43: Sumă Cr | G43: Descriere Cr
A44: 1 | B44: =Declarații_LEASING_FIN!B76 -> 666.NED | C44: =Declarații_LEASING_FIN!B55 -> 276.25 | D44: ="Dobândă nedeductibilă 50% " & Declarații_LEASING_FIN!B83 -> Dobândă nedeductibilă 50% — leasing LF-2026-001 2026-07 | E44: =Declarații_LEASING_FIN!B73 -> 666 | F44: =Declarații_LEASING_FIN!B55 -> 276.25 | G44: ="Reclasificare din 666 " & Declarații_LEASING_FIN!B83 -> Reclasificare din 666 — leasing LF-2026-001 2026-07
A45: 2 | B45: =Declarații_LEASING_FIN!B77 -> 628.NED | C45: =Declarații_LEASING_FIN!B56 -> 55.25 | D45: ="Comision nedeductibil 50% " & Declarații_LEASING_FIN!B83 -> Comision nedeductibil 50% — leasing LF-2026-001 2026-07 | E45: =Declarații_LEASING_FIN!B74 -> 628 | F45: =Declarații_LEASING_FIN!B56 -> 55.25 | G45: ="Reclasificare din 628 " & Declarații_LEASING_FIN!B83 -> Reclasificare din 628 — leasing LF-2026-001 2026-07
A46: 3 | B46: =Declarații_LEASING_FIN!B78 -> 613.NED | C46: =Declarații_LEASING_FIN!B57 -> 10 | D46: ="CASCO nedeductibil 50% " & Declarații_LEASING_FIN!B83 -> CASCO nedeductibil 50% — leasing LF-2026-001 2026-07 | E46: =Declarații_LEASING_FIN!B75 -> 613 | F46: =Declarații_LEASING_FIN!B57 -> 10 | G46: ="Reclasificare din 613 (NU 615) " & Declarații_LEASING_FIN!B83 -> Reclasificare din 613 (NU 615) — leasing LF-2026-001 2026-07
A48: Bloc 8 — Amortizarea lunară (limitarea 3: plafon 1.500 lei/lună)
A49: Nr | B49: Cont Dr | C49: Sumă Dr | D49: Descriere Dr | E49: Cont Cr | F49: Sumă Cr | G49: Descriere Cr
A50: 1 | B50: =Declarații_LEASING_FIN!B80 -> 6811 | C50: =Declarații_LEASING_FIN!B33 -> 2587.5 | D50: ="Amortizare contabilă (din care nedeductibil " & TEXT(Declarații_LEASING_FIN!B35,"0.00") & " lei) " & Declarații_LEASING_FIN!B83 -> Amortizare contabilă (din care nedeductibil 1087.50 lei) — leasing LF-2026-001 2026-07 | E50: =Declarații_LEASING_FIN!B69 -> 2813 | F50: =Declarații_LEASING_FIN!B33 -> 2587.5 | G50: ="Amortizare cumulată " & Declarații_LEASING_FIN!B83 -> Amortizare cumulată — leasing LF-2026-001 2026-07
A52: Sumar și controale
A53: Total Dr | B53: =C8+C9+C13+C19+C23+C29+C30+C31+C32+C33+C37+C38+C39+C44+C45+C46+C50 -> 272118
A54: Total Cr | B54: =F8+F9+F13+F19+F23+F29+F30+F31+F32+F33+F37+F38+F39+F44+F45+F46+F50 -> 272118
A55: Check Σ (structural) | B55: =B53-B54 -> 0 | C55: =IF(ABS(B53-B54)<0.01,"OK — notele se închid","EROARE") -> OK — notele se închid
A56: Check valoare de intrare a mijlocului fix | B56: =C13+C19-Declarații_LEASING_FIN!B32 -> 0 | C56: =IF(ABS(C13+C19-Declarații_LEASING_FIN!B32)<0.01,"OK — 2133 = valoare contract + TVA nedeductibilă pe avans","EROARE") -> OK — 2133 = valoare contract + TVA nedeductibilă pe avans
A57: Check stingere avans (C-19) | B57: =C8-C23 -> 0 | C57: =IF(ABS(C8-C23)<0.01,"OK — 4093 se închide integral în 167","EROARE — avansul rămâne cu sold") -> OK — 4093 se închide integral în 167
A58: Check TVA de pe factura lunară | B58: =C37+C38+C39-Declarații_LEASING_FIN!B48 -> 0 | C58: =IF(ABS(C37+C38+C39-Declarații_LEASING_FIN!B48)<0.01,"OK — corecția acoperă exact TVA nedeductibilă","EROARE") -> OK — corecția acoperă exact TVA nedeductibilă
A59: Check limitarea 2 nu atinge amortizarea | B59: =C50 -> 2587.5 | C59: =IF(ABS(C44+C45+C46)<C50,"OK — amortizarea are propria plafonare, nu se limitează cu 50%","VERIFICĂ — sume neobișnuite") -> OK — amortizarea are propria plafonare, nu se limitează cu 50%
A60: Nedeductibil lunar total (informativ) | B60: =Declarații_LEASING_FIN!B35+C44+C45+C46 -> 1429 | C60: ="Din care amortizare peste plafon: " & TEXT(Declarații_LEASING_FIN!B35,"0.00") & " lei" -> Din care amortizare peste plafon: 1087.50 lei
A61: Stare terminală așteptată: sold 4093 = 0; sold 167 pe contract = soldul din scadențar; 2133 = valoarea de intrare completă; nedeductibilul lunar urmărit pentru D101.

Sheet NotaExport_LEASING_FIN
A1: MOD_LEASING_FIN — Notă pentru import (1 rând = 1 înregistrare)
A2: Blocurile 1–4 se importă o singură dată, la deschiderea contractului. Blocurile 5–8, lunar. Filtrează pe Include = DA.
A4: Nr | B4: Bloc | C4: Data | D4: Cont Dr | E4: Cont Cr | F4: Sumă | G4: Descriere | H4: Document | I4: Include
A5: 1 | B5: Bloc 1 — Avans | C5: =Declarații_LEASING_FIN!B8 -> 2026-07-01 | D5: =Jurnale_LEASING_FIN!B8 -> 4093 | E5: =Jurnale_LEASING_FIN!E8 -> 404 | F5: =Jurnale_LEASING_FIN!C8 -> 50000 | G5: =Jurnale_LEASING_FIN!D8 -> Avans leasing — leasing LF-2026-001 2026-07 | H5: Factură de avans | I5: =IF(F5>0.001,"DA","NU") -> DA
A6: 2 | B6: Bloc 1 — TVA avans | C6: =Declarații_LEASING_FIN!B8 -> 2026-07-01 | D6: =Jurnale_LEASING_FIN!B9 -> 4426 | E6: =Jurnale_LEASING_FIN!E9 -> 404 | F6: =Jurnale_LEASING_FIN!C9 -> 10500 | G6: =Jurnale_LEASING_FIN!D9 -> TVA pe avans — leasing LF-2026-001 2026-07 | H6: Factură de avans | I6: =IF(F6>0.001,"DA","NU") -> DA
A7: 3 | B7: Bloc 2 — TVA nededusă capitalizată | C7: =Declarații_LEASING_FIN!B8 -> 2026-07-01 | D7: =Jurnale_LEASING_FIN!B13 -> 2133 | E7: =Jurnale_LEASING_FIN!E13 -> 4426 | F7: =Jurnale_LEASING_FIN!C13 -> 5250 | G7: =Jurnale_LEASING_FIN!D13 -> TVA nedeductibilă capitalizată în cost — leasing LF-2026-001 2026-07 | H7: Notă contabilă | I7: =IF(F7>0.001,"DA","NU") -> DA
A8: 4 | B8: Bloc 3 — Intrare + 167 | C8: =Declarații_LEASING_FIN!B9 -> 2026-07-10 | D8: =Jurnale_LEASING_FIN!B19 -> 2133 | E8: =Jurnale_LEASING_FIN!E19 -> 167.LF-2026-001 | F8: =Jurnale_LEASING_FIN!C19 -> 150000 | G8: =Jurnale_LEASING_FIN!D19 -> Intrare autoturism în patrimoniu — leasing LF-2026-001 2026-07 | H8: Proces-verbal de recepție | I8: =IF(F8>0.001,"DA","NU") -> DA
A9: 5 | B9: Bloc 4 — Stingere avans | C9: =Declarații_LEASING_FIN!B9 -> 2026-07-10 | D9: =Jurnale_LEASING_FIN!B23 -> 167.LF-2026-001 | E9: =Jurnale_LEASING_FIN!E23 -> 4093 | F9: =Jurnale_LEASING_FIN!C23 -> 50000 | G9: =Jurnale_LEASING_FIN!D23 -> Închidere avans în datoria de leasing — leasing LF-2026-001 2026-07 | H9: Notă contabilă | I9: =IF(F9>0.001,"DA","NU") -> DA
A10: 6 | B10: Bloc 5 — Rata de capital | C10: =Declarații_LEASING_FIN!B10 -> 2026-07-31 | D10: =Jurnale_LEASING_FIN!B29 -> 167.LF-2026-001 | E10: =Jurnale_LEASING_FIN!E29 -> 404 | F10: =Jurnale_LEASING_FIN!C29 -> 2000 | G10: =Jurnale_LEASING_FIN!D29 -> Rata de capital — leasing LF-2026-001 2026-07 | H10: Factură lunară | I10: =IF(F10>0.001,"DA","NU") -> DA
A11: 7 | B11: Bloc 5 — Dobândă | C11: =Declarații_LEASING_FIN!B10 -> 2026-07-31 | D11: =Jurnale_LEASING_FIN!B30 -> 666 | E11: =Jurnale_LEASING_FIN!E30 -> 404 | F11: =Jurnale_LEASING_FIN!C30 -> 500 | G11: =Jurnale_LEASING_FIN!D30 -> Dobândă de leasing — leasing LF-2026-001 2026-07 | H11: Factură lunară | I11: =IF(F11>0.001,"DA","NU") -> DA
A12: 8 | B12: Bloc 5 — Comision | C12: =Declarații_LEASING_FIN!B10 -> 2026-07-31 | D12: =Jurnale_LEASING_FIN!B31 -> 628 | E12: =Jurnale_LEASING_FIN!E31 -> 404 | F12: =Jurnale_LEASING_FIN!C31 -> 100 | G12: =Jurnale_LEASING_FIN!D31 -> Comision de administrare — leasing LF-2026-001 2026-07 | H12: Factură lunară | I12: =IF(F12>0.001,"DA","NU") -> DA
A13: 9 | B13: Bloc 5 — CASCO | C13: =Declarații_LEASING_FIN!B10 -> 2026-07-31 | D13: =Jurnale_LEASING_FIN!B32 -> 613 | E13: =Jurnale_LEASING_FIN!E32 -> 404 | F13: =Jurnale_LEASING_FIN!C32 -> 20 | G13: =Jurnale_LEASING_FIN!D32 -> Primă CASCO — leasing LF-2026-001 2026-07 | H13: Factură lunară | I13: =IF(F13>0.001,"DA","NU") -> DA
A14: 10 | B14: Bloc 5 — TVA | C14: =Declarații_LEASING_FIN!B10 -> 2026-07-31 | D14: =Jurnale_LEASING_FIN!B33 -> 4426 | E14: =Jurnale_LEASING_FIN!E33 -> 404 | F14: =Jurnale_LEASING_FIN!C33 -> 546 | G14: =Jurnale_LEASING_FIN!D33 -> TVA pe factura de leasing — leasing LF-2026-001 2026-07 | H14: Factură lunară | I14: =IF(F14>0.001,"DA","NU") -> DA
A15: 11 | B15: Bloc 6 — TVA nededusă rată | C15: =Declarații_LEASING_FIN!B10 -> 2026-07-31 | D15: =Jurnale_LEASING_FIN!B37 -> 2133 | E15: =Jurnale_LEASING_FIN!E37 -> 4426 | F15: =Jurnale_LEASING_FIN!C37 -> 210 | G15: =Jurnale_LEASING_FIN!D37 -> TVA nededusă pe rata de capital — capitalizată — leasing LF-2026-001 2026-07 | H15: Notă contabilă | I15: =IF(F15>0.001,"DA","NU") -> DA
A16: 12 | B16: Bloc 6 — TVA nededusă dobândă | C16: =Declarații_LEASING_FIN!B10 -> 2026-07-31 | D16: =Jurnale_LEASING_FIN!B38 -> 666 | E16: =Jurnale_LEASING_FIN!E38 -> 4426 | F16: =Jurnale_LEASING_FIN!C38 -> 52.5 | G16: =Jurnale_LEASING_FIN!D38 -> TVA nededusă pe dobândă — leasing LF-2026-001 2026-07 | H16: Notă contabilă | I16: =IF(F16>0.001,"DA","NU") -> DA
A17: 13 | B17: Bloc 6 — TVA nededusă comision | C17: =Declarații_LEASING_FIN!B10 -> 2026-07-31 | D17: =Jurnale_LEASING_FIN!B39 -> 628 | E17: =Jurnale_LEASING_FIN!E39 -> 4426 | F17: =Jurnale_LEASING_FIN!C39 -> 10.5 | G17: =Jurnale_LEASING_FIN!D39 -> TVA nededusă pe comision — leasing LF-2026-001 2026-07 | H17: Notă contabilă | I17: =IF(F17>0.001,"DA","NU") -> DA
A18: 14 | B18: Bloc 7 — Dobândă nedeductibilă | C18: =Declarații_LEASING_FIN!B10 -> 2026-07-31 | D18: =Jurnale_LEASING_FIN!B44 -> 666.NED | E18: =Jurnale_LEASING_FIN!E44 -> 666 | F18: =Jurnale_LEASING_FIN!C44 -> 276.25 | G18: =Jurnale_LEASING_FIN!D44 -> Dobândă nedeductibilă 50% — leasing LF-2026-001 2026-07 | H18: Notă contabilă | I18: =IF(F18>0.001,"DA","NU") -> DA
A19: 15 | B19: Bloc 7 — Comision nedeductibil | C19: =Declarații_LEASING_FIN!B10 -> 2026-07-31 | D19: =Jurnale_LEASING_FIN!B45 -> 628.NED | E19: =Jurnale_LEASING_FIN!E45 -> 628 | F19: =Jurnale_LEASING_FIN!C45 -> 55.25 | G19: =Jurnale_LEASING_FIN!D45 -> Comision nedeductibil 50% — leasing LF-2026-001 2026-07 | H19: Notă contabilă | I19: =IF(F19>0.001,"DA","NU") -> DA
A20: 16 | B20: Bloc 7 — CASCO nedeductibil | C20: =Declarații_LEASING_FIN!B10 -> 2026-07-31 | D20: =Jurnale_LEASING_FIN!B46 -> 613.NED | E20: =Jurnale_LEASING_FIN!E46 -> 613 | F20: =Jurnale_LEASING_FIN!C46 -> 10 | G20: =Jurnale_LEASING_FIN!D46 -> CASCO nedeductibil 50% — leasing LF-2026-001 2026-07 | H20: Notă contabilă | I20: =IF(F20>0.001,"DA","NU") -> DA
A21: 17 | B21: Bloc 8 — Amortizare | C21: =Declarații_LEASING_FIN!B10 -> 2026-07-31 | D21: =Jurnale_LEASING_FIN!B50 -> 6811 | E21: =Jurnale_LEASING_FIN!E50 -> 2813 | F21: =Jurnale_LEASING_FIN!C50 -> 2587.5 | G21: =Jurnale_LEASING_FIN!D50 -> Amortizare contabilă (din care nedeductibil 1087.50 lei) — leasing LF-2026-001 2026-07 | H21: Notă de amortizare | I21: =IF(F21>0.001,"DA","NU") -> DA
A23: Rânduri de importat (Include=DA) | B23: =COUNTIF(I5:I21,"DA") -> 17
A24: Check global (trebuie 0) | B24: =Jurnale_LEASING_FIN!B53-Jurnale_LEASING_FIN!B54 -> 0 | C24: =IF(ABS(Jurnale_LEASING_FIN!B53-Jurnale_LEASING_FIN!B54)<0.01,"OK","EROARE") -> OK

Sheet Declarații_DIVIDENDE
A1: MOD_DIVIDENDE — Declarații (input)
A2: Valorile implicite reproduc monografiile din F-109 (30.000 lei, trei asociați în cote egale) și F-110 (interimare de 80.000 pe un 121 de 80.000, regularizate la un profit final de 70.000).
A4: 1. Antet
A5: Societate | B5: =Parametri!B5 -> SC EXEMPLU SRL
A6: CUI | B6: =Parametri!B6 -> RO00000000
A7: Exercițiul repartizat (AAAA) | B7: 2025
A8: Hotărârea AGA (număr și dată) | B8: 12 / 2026-04-20
A9: Data notei contabile | B9: 2026-04-30
A11: 2. Blocul A — Repartizarea dividendelor certe
A12: Se aplică? (DA/NU) | B12: DA
A13: Sold 1171 pe exercițiul repartizat (creditor) | B13: 30000 | C13: Sold DEBITOR = pierdere neacoperită: nu se distribuie nimic
A14: Total repartizat prin hotărârea AGA | B14: 30000
A16: Cotele se citesc din DENUMIRILE analiticelor lui 1012, nu din hotărâre. Sumele se introduc așa cum apar în hotărâre; modulul le recalculează alături și compară — de-aia sunt intrare, nu formulă.
A17: 2.1 Asociatul 1
A18: Nume (din 1012) | B18: Ionescu
A19: Cota de participare (din denumirea analiticului) | B19: 0.3333
A20: Sumă din hotărârea AGA | B20: 10000
A21: Recalculat: cotă × total | B21: =ROUND(B19*B14,2) -> 9999
A22: 2.2 Asociatul 2
A23: Nume (din 1012) | B23: Popescu
A24: Cota de participare | B24: 0.3333
A25: Sumă din hotărârea AGA | B25: 10000
A26: Recalculat: cotă × total | B26: =ROUND(B24*B14,2) -> 9999
A27: 2.3 Asociatul 3
A28: Nume (din 1012) | B28: Xulescu
A29: Cota de participare | B29: 0.3334
A30: Sumă din hotărârea AGA | B30: 10000
A31: Recalculat: cotă × total | B31: =ROUND(B29*B14,2) -> 10002
A32: Toleranța de rotunjire a cotelor (auto) | B32: =ROUND(B14*0.0001,2) -> 3 | C32: O sutime de procent din total — precizia cu care se scrie cota în denumirea analiticului
A34: 3. Blocul B — Impozitul pe dividende
A35: Cota de impozit | B35: =param_cota_impozit_dividend -> 0.16
A36: Impozit reținut, din nota contabilă | B36: 4800
A37: Recalculat, calea 1: Σ (16% × brutul fiecărui asociat) | B37: =ROUND(B20*B35,2)+ROUND(B25*B35,2)+ROUND(B30*B35,2) -> 4800
A38: Recalculat, calea 2: 16% × totalul din hotărâre | B38: =ROUND(B14*B35,2) -> 4800
A39: S-au ridicat dividendele? (DA/NU) | B39: DA | C39: NU → 457 rămâne cu sold, dar impozitul se plătește oricum
A41: 4. Blocul C — Dividende interimare
A42: Se aplică? (DA/NU) | B42: DA
A43: S-a făcut inventarierea? (DA/NU) | B43: DA
A44: S-a întocmit bilanțul interimar? (DA/NU) | B44: DA
A45: Sold creditor 121 la data bilanțului interimar | B45: 80000 | C45: Din BALANȚĂ, după înregistrarea impozitului — nu din extras
A46: Suma cerută de administrator | B46: 100000
A47: Suma efectiv repartizată | B47: 80000
A48: Impozit pe interimare, din nota contabilă | B48: 12800
A49: Recalculat: 16% × repartizat | B49: =ROUND(B47*B35,2) -> 12800
A51: 5. Blocul D — Regularizarea la 31.12
A52: Se aplică? (DA/NU) | B52: DA
A53: Profit realizat la 31.12 (sold 121) | B53: 70000
A54: Diferența de stornat (auto) | B54: =MAX(0,B47-B53) -> 10000
A55: Storno de impozit (auto) | B55: =ROUND(B54*B35,2) -> 1600
A57: 6. Conturi
A58: Cont rezultat reportat | B58: 1171
A59: Cont dividende asociat 1 | B59: 457.1
A60: Cont dividende asociat 2 | B60: 457.2
A61: Cont dividende asociat 3 | B61: 457.3
A62: Cont impozit pe dividende | B62: 446.dividende
A63: Cont dividende interimare | B63: 463
A64: Cont decontări cu asociații | B64: 456
A65: Cont trezorerie | B65: 5121
A67: 7. Sufix
A68: Sufix | B68: ="— AGA " & B8 & ", exercițiul " & B7 -> — AGA 12 / 2026-04-20, exercițiul 2025
A70: 8. Control
A71: Modul activ? | B71: =IF(INDEX(CatalogModule!$A$1:$A$200,MATCH("MOD_DIVIDENDE",CatalogModule!$B$1:$B$200,0))="DA","ACTIV","INACTIV") -> INACTIV
A72: Verificare: Σ cotelor de participare = 100% | B72: =IF(OR(B12<>"DA",ABS(B19+B24+B29-1)<0.0001),"OK — cotele acoperă exact capitalul","EROARE — Σ cote = " & TEXT(B19+B24+B29,"0.00%") & "; un asociat lipsește din 1012 sau un procent e greșit") -> OK — cotele acoperă exact capitalul
A73: Verificare: sumele din AGA = cotă × total | B73: =IF(OR(B12<>"DA",AND(ABS(B20-B21)<=B32,ABS(B25-B26)<=B32,ABS(B30-B31)<=B32)),"OK — repartizarea din hotărâre urmează cotele din 1012, în limita rotunjirii procentelor","EROARE — hotărârea repartizează altfel decât spun cotele din balanță: abateri de " & TEXT(B20-B21,"#,##0.00") & " / " & TEXT(B25-B26,"#,##0.00") & " / " & TEXT(B30-B31,"#,##0.00") & " lei, peste toleranța de " & TEXT(B32,"#,##0.00")) -> OK — repartizarea din hotărâre urmează cotele din 1012, în limita rotunjirii procentelor
A74: Verificare: Σ sumelor repartizate = totalul din hotărâre | B74: =IF(OR(B12<>"DA",ABS(B20+B25+B30-B14)<0.01),"OK","EROARE — Σ pe asociați diferă de total cu " & TEXT(B20+B25+B30-B14,"#,##0.00") & " lei") -> OK
A75: Verificare: există sursă în 1171 pentru ce se repartizează | B75: =IF(OR(B12<>"DA",B13>=B14),"OK",IF(B13<0,"BLOCAT — 1171 are sold debitor: cu pierdere neacoperită nu se distribuie nimic (art. 69 L. 31/1990)","EROARE — se repartizează mai mult decât are 1171, lipsă " & TEXT(B14-B13,"#,##0.00") & " lei")) -> OK
A76: Verificare: impozitul reținut, pe două căi | B76: =IF(B12<>"DA","—",IF(AND(ABS(B36-B37)<0.01,ABS(B36-B38)<0.02),"OK — 16% verificat și pe asociat, și pe total","EROARE — impozit " & TEXT(B36,"#,##0.00") & " vs. " & TEXT(B37,"#,##0.00") & " pe asociat și " & TEXT(B38,"#,##0.00") & " pe total")) -> OK — 16% verificat și pe asociat, și pe total
A77: Verificare: interimarele nu depășesc soldul lui 121 | B77: =IF(B42<>"DA","—",IF(B47<=B45,"OK — sub plafon, rezervă de " & TEXT(B45-B47,"#,##0.00") & " lei","EROARE — depășire de " & TEXT(B47-B45,"#,##0.00") & " lei, care se va storna la 31.12 și se va restitui")) -> OK — sub plafon, rezervă de 0,.00 lei
A78: Verificare: condițiile legale ale interimarelor | B78: =IF(B42<>"DA","—",IF(AND(B43="DA",B44="DA"),"OK — inventariere și bilanț interimar făcute","BLOCAT — interimarele cer INVENTARIERE și bilanț interimar; sunt condiții legale, nu formalități")) -> OK — inventariere și bilanț interimar făcute
A79: Informativ: cât a cerut administratorul vs. cât poate ridica net | B79: =IF(B42<>"DA","—","Cerut " & TEXT(B46,"#,##0") & " lei; repartizabil " & TEXT(MIN(B46,B45),"#,##0") & "; ridicat net " & TEXT(B47-B48,"#,##0") & " lei") -> Cerut 100,000 lei; repartizabil 80,000; ridicat net 67,200 lei
A80: Verificare: după storno, 463 rămâne la nivelul profitului realizat | B80: =IF(B52<>"DA","—",IF(ABS((B47-B54)-MIN(B47,B53))<0.01,"OK — 463 = " & TEXT(B47-B54,"#,##0.00") & " lei, adică profitul realizat","EROARE — stornarea nu aduce 463 la profitul realizat")) -> OK — 463 = 70,000.00 lei, adică profitul realizat
A81: Termenul care surprinde | B81: Impozitul pe dividende se plătește până la 25.01 a anului următor repartizării, CHIAR DACĂ dividendele nu au fost ridicate. Obligația e față de buget, nu față de asociat.

Sheet Reguli_DIVIDENDE
A1: MOD_DIVIDENDE — Reguli (tabele fixe)
A2: Ce e regulă dată, nu formulă: tipurile de dividend, declarațiile și calendarul interimarelor.
A4: Tabel A — Cele două feluri de dividende
A5: Tip | B5: Cont | C5: Din ce se repartizează | D5: Ce document cere
A6: Certe | B6: 457 | C6: Din rezultatul unui exercițiu ÎNCHEIAT (1171) | D6: Hotărâre AGA. Condiție: 1171 fără sold debitor pe niciun an
A7: Interimare | B7: 463 → 456 | C7: Din profitul anului CURENT, doar trimestrial | D7: Hotărâre AGA + INVENTARIERE + bilanț interimar
A9: Tabel B — Declarațiile
A10: Declarație | B10: Cadență | C10: Ce conține
A11: D100 | B11: Ori de câte ori e impozit de plată | C11: Impozitul pe dividende. Atenție la rubrica separată pentru persoane fizice — nu se confundă cu impozitul datorat de persoane juridice
A12: D205 | B12: Anual, cumulativ | C12: Declarație informativă. Două rubrici distincte: dividende DISTRIBUITE și dividende RIDICATE. Se confruntă cu D100 și cu fișa contului 446
A13: Declarația Unică | B13: Anual, de către asociat | C13: CASS. ❓ Notițele spun că se datorează la dividendele RIDICATE, nu la cele distribuite — de confirmat cu formatorul
A14: D710 | B14: La regularizarea de la 31.12 | C14: Rectificativa lui D100. Apare suma plătită inițial și cea corectată; diferența plătită în plus se compensează sau se restituie la cerere
A16: Tabel C — Calendarul interimarelor
A17: Nu e intuitiv: hotărârea se ia într-o lună, înregistrarea se face în alta.
A18: Momentul | B18: Ce se întâmplă
A19: 30.06 | B19: Închiderea a șase luni. Soldul lui 121 la data asta E plafonul
A20: iunie | B20: LUNA în care se face înregistrarea contabilă — bilanțul interimar are rubrică separată pentru 463, deci acolo vede ANAF ce s-a repartizat
A21: iulie | B21: LUNA în care se ia hotărârea AGA: are nevoie de balanța închisă
A22: 31.07 | B22: Termenul de depunere a bilanțului interimar
A23: 31.12 | B23: Comparația cu profitul realizat. Dacă e mai mic, se stornează diferența
A24: 25.01 | B24: Termenul de plată a impozitului, indiferent dacă s-a ridicat sau nu
A26: Tabel D — Porți de calitate
A27: • Cotele se citesc din DENUMIRILE analiticelor lui 1012; hotărârea AGA se contraverifică cu ele, nu invers
A28: • Fără hotărâre AGA nu se înregistrează dividende — nici certe, nici interimare
A29: • Cu sold debitor pe 1171 (pierdere neacoperită) nu se distribuie nimic
A30: • Interimarele cer inventariere ȘI bilanț interimar, și se acordă doar trimestrial
A31: • Plafonul interimarelor e soldul lui 121, nu disponibilul din bancă
A32: • Impozitul se datorează la DISTRIBUIRE; termenul de 25.01 nu depinde de ridicare
A33: • 457 se stinge doar prin 446 sau prin trezorerie — nu prin 4551 sau 461 (vezi C-34)
A34: • D205 se confruntă cu D100 și cu fișa contului 446: se caută o plată făcută fără declarație
A36: Temei legal
A37: Ce se sprijină pe el | B37: Temei
A38: Dividendele se repartizează proporțional cu cota de participare la capitalul social | B38: art. 67 alin. (2) Legea 31/1990
A39: Cota de impozit pe dividende, 16% pentru distribuirile de la 01.01.2026 | B39: art. 43 Cod fiscal, astfel cum a fost modificat prin Legea 141/2025
A40: Termenul de plată: 25 ianuarie a anului următor celui în care s-a aprobat repartizarea, dacă dividendele nu au fost ridicate | B40: art. 43 alin. (3) Cod fiscal
A41: Dividendele interimare, trimestrial, pe baza situațiilor financiare interimare | B41: art. 67 alin. (2) și (4) Legea 31/1990 — cu inventariere prealabilă
A42: Regularizarea la 31.12 și restituirea diferenței distribuite în plus | B42: art. 67 alin. (4) Legea 31/1990
A43: Nu se distribuie dividende cât timp există pierdere contabilă reportată neacoperită | B43: art. 69 Legea 31/1990

Sheet Jurnale_DIVIDENDE
A1: MOD_DIVIDENDE — Jurnale (generate automat)
A2: Blocurile neactivate ies cu zero. Blocul D produce sume NEGATIVE: e stornare, nu o înregistrare inversă.
A4: Bloc A — Repartizarea pe asociați
A5: Data: | B5: =Declarații_DIVIDENDE!B9 -> 2026-04-30
A6: Nr | B6: Cont Dr | C6: Sumă Dr | D6: Descriere Dr | E6: Cont Cr | F6: Sumă Cr | G6: Descriere Cr
A7: 1 | B7: =Declarații_DIVIDENDE!B58 -> 1171 | C7: =IF(Declarații_DIVIDENDE!B12="DA",Declarații_DIVIDENDE!B20,0) -> 10000 | D7: ="Repartizare dividende " & Declarații_DIVIDENDE!B18 & " " & Declarații_DIVIDENDE!B68 -> Repartizare dividende Ionescu — AGA 12 / 2026-04-20, exercițiul 2025 | E7: =Declarații_DIVIDENDE!B59 -> 457.1 | F7: =IF(Declarații_DIVIDENDE!B12="DA",Declarații_DIVIDENDE!B20,0) -> 10000 | G7: ="Dividende de plată " & Declarații_DIVIDENDE!B18 & " " & Declarații_DIVIDENDE!B68 -> Dividende de plată Ionescu — AGA 12 / 2026-04-20, exercițiul 2025
A8: 2 | B8: =Declarații_DIVIDENDE!B58 -> 1171 | C8: =IF(Declarații_DIVIDENDE!B12="DA",Declarații_DIVIDENDE!B25,0) -> 10000 | D8: ="Repartizare dividende " & Declarații_DIVIDENDE!B23 & " " & Declarații_DIVIDENDE!B68 -> Repartizare dividende Popescu — AGA 12 / 2026-04-20, exercițiul 2025 | E8: =Declarații_DIVIDENDE!B60 -> 457.2 | F8: =IF(Declarații_DIVIDENDE!B12="DA",Declarații_DIVIDENDE!B25,0) -> 10000 | G8: ="Dividende de plată " & Declarații_DIVIDENDE!B23 & " " & Declarații_DIVIDENDE!B68 -> Dividende de plată Popescu — AGA 12 / 2026-04-20, exercițiul 2025
A9: 3 | B9: =Declarații_DIVIDENDE!B58 -> 1171 | C9: =IF(Declarații_DIVIDENDE!B12="DA",Declarații_DIVIDENDE!B30,0) -> 10000 | D9: ="Repartizare dividende " & Declarații_DIVIDENDE!B28 & " " & Declarații_DIVIDENDE!B68 -> Repartizare dividende Xulescu — AGA 12 / 2026-04-20, exercițiul 2025 | E9: =Declarații_DIVIDENDE!B61 -> 457.3 | F9: =IF(Declarații_DIVIDENDE!B12="DA",Declarații_DIVIDENDE!B30,0) -> 10000 | G9: ="Dividende de plată " & Declarații_DIVIDENDE!B28 & " " & Declarații_DIVIDENDE!B68 -> Dividende de plată Xulescu — AGA 12 / 2026-04-20, exercițiul 2025
A10: Check A (Σ pe asociați = totalul din hotărâre) | B10: =C7+C8+C9-IF(Declarații_DIVIDENDE!B12="DA",Declarații_DIVIDENDE!B14,0) -> 0 | C10: =IF(ABS(B10)<0.01,"OK — repartizarea acoperă exact totalul din AGA","EROARE — Σ pe asociați ≠ total") -> OK — repartizarea acoperă exact totalul din AGA
A12: Bloc B — Impozitul de 16%
A13: Nr | B13: Cont Dr | C13: Sumă Dr | D13: Descriere Dr | E13: Cont Cr | F13: Sumă Cr | G13: Descriere Cr
A14: 1 | B14: =Declarații_DIVIDENDE!B59 -> 457.1 | C14: =IF(Declarații_DIVIDENDE!B12="DA",ROUND(Declarații_DIVIDENDE!B20*Declarații_DIVIDENDE!B35,2),0) -> 1600 | D14: ="Impozit 16% dividende " & Declarații_DIVIDENDE!B18 & " " & Declarații_DIVIDENDE!B68 -> Impozit 16% dividende Ionescu — AGA 12 / 2026-04-20, exercițiul 2025 | E14: =Declarații_DIVIDENDE!B62 -> 446.dividende | F14: =IF(Declarații_DIVIDENDE!B12="DA",ROUND(Declarații_DIVIDENDE!B20*Declarații_DIVIDENDE!B35,2),0) -> 1600 | G14: ="Impozit pe dividende de plată " & Declarații_DIVIDENDE!B68 -> Impozit pe dividende de plată — AGA 12 / 2026-04-20, exercițiul 2025
A15: 2 | B15: =Declarații_DIVIDENDE!B60 -> 457.2 | C15: =IF(Declarații_DIVIDENDE!B12="DA",ROUND(Declarații_DIVIDENDE!B25*Declarații_DIVIDENDE!B35,2),0) -> 1600 | D15: ="Impozit 16% dividende " & Declarații_DIVIDENDE!B23 & " " & Declarații_DIVIDENDE!B68 -> Impozit 16% dividende Popescu — AGA 12 / 2026-04-20, exercițiul 2025 | E15: =Declarații_DIVIDENDE!B62 -> 446.dividende | F15: =IF(Declarații_DIVIDENDE!B12="DA",ROUND(Declarații_DIVIDENDE!B25*Declarații_DIVIDENDE!B35,2),0) -> 1600 | G15: ="Impozit pe dividende de plată " & Declarații_DIVIDENDE!B68 -> Impozit pe dividende de plată — AGA 12 / 2026-04-20, exercițiul 2025
A16: 3 | B16: =Declarații_DIVIDENDE!B61 -> 457.3 | C16: =IF(Declarații_DIVIDENDE!B12="DA",ROUND(Declarații_DIVIDENDE!B30*Declarații_DIVIDENDE!B35,2),0) -> 1600 | D16: ="Impozit 16% dividende " & Declarații_DIVIDENDE!B28 & " " & Declarații_DIVIDENDE!B68 -> Impozit 16% dividende Xulescu — AGA 12 / 2026-04-20, exercițiul 2025 | E16: =Declarații_DIVIDENDE!B62 -> 446.dividende | F16: =IF(Declarații_DIVIDENDE!B12="DA",ROUND(Declarații_DIVIDENDE!B30*Declarații_DIVIDENDE!B35,2),0) -> 1600 | G16: ="Impozit pe dividende de plată " & Declarații_DIVIDENDE!B68 -> Impozit pe dividende de plată — AGA 12 / 2026-04-20, exercițiul 2025
A17: 4 | B17: =Declarații_DIVIDENDE!B62 -> 446.dividende | C17: =IF(Declarații_DIVIDENDE!B12="DA",Declarații_DIVIDENDE!B36,0) -> 4800 | D17: ="Plata impozitului pe dividende (termen 25.01) " & Declarații_DIVIDENDE!B68 -> Plata impozitului pe dividende (termen 25.01) — AGA 12 / 2026-04-20, exercițiul 2025 | E17: =Declarații_DIVIDENDE!B65 -> 5121 | F17: =IF(Declarații_DIVIDENDE!B12="DA",Declarații_DIVIDENDE!B36,0) -> 4800 | G17: ="Ieșire trezorerie " & Declarații_DIVIDENDE!B68 -> Ieșire trezorerie — AGA 12 / 2026-04-20, exercițiul 2025
A18: Check B (impozitul din notă = Σ reținerilor pe asociat) | B18: =Declarații_DIVIDENDE!B36*IF(Declarații_DIVIDENDE!B12="DA",1,0)-C14-C15-C16 -> 0 | C18: =IF(ABS(B18)<0.01,"OK — 16% pe fiecare analitic de 457","EROARE — impozitul plătit nu e suma reținerilor") -> OK — 16% pe fiecare analitic de 457
A20: Bloc B2 — Plata dividendelor nete
A21: Nr | B21: Cont Dr | C21: Sumă Dr | D21: Descriere Dr | E21: Cont Cr | F21: Sumă Cr | G21: Descriere Cr
A22: 1 | B22: =Declarații_DIVIDENDE!B59 -> 457.1 | C22: =IF(AND(Declarații_DIVIDENDE!B12="DA",Declarații_DIVIDENDE!B39="DA"),Declarații_DIVIDENDE!B20-ROUND(Declarații_DIVIDENDE!B20*Declarații_DIVIDENDE!B35,2),0) -> 8400 | D22: ="Plată dividend net " & Declarații_DIVIDENDE!B18 & " " & Declarații_DIVIDENDE!B68 -> Plată dividend net Ionescu — AGA 12 / 2026-04-20, exercițiul 2025 | E22: =Declarații_DIVIDENDE!B65 -> 5121 | F22: =IF(AND(Declarații_DIVIDENDE!B12="DA",Declarații_DIVIDENDE!B39="DA"),Declarații_DIVIDENDE!B20-ROUND(Declarații_DIVIDENDE!B20*Declarații_DIVIDENDE!B35,2),0) -> 8400 | G22: ="Ieșire trezorerie " & Declarații_DIVIDENDE!B68 -> Ieșire trezorerie — AGA 12 / 2026-04-20, exercițiul 2025
A23: 2 | B23: =Declarații_DIVIDENDE!B60 -> 457.2 | C23: =IF(AND(Declarații_DIVIDENDE!B12="DA",Declarații_DIVIDENDE!B39="DA"),Declarații_DIVIDENDE!B25-ROUND(Declarații_DIVIDENDE!B25*Declarații_DIVIDENDE!B35,2),0) -> 8400 | D23: ="Plată dividend net " & Declarații_DIVIDENDE!B23 & " " & Declarații_DIVIDENDE!B68 -> Plată dividend net Popescu — AGA 12 / 2026-04-20, exercițiul 2025 | E23: =Declarații_DIVIDENDE!B65 -> 5121 | F23: =IF(AND(Declarații_DIVIDENDE!B12="DA",Declarații_DIVIDENDE!B39="DA"),Declarații_DIVIDENDE!B25-ROUND(Declarații_DIVIDENDE!B25*Declarații_DIVIDENDE!B35,2),0) -> 8400 | G23: ="Ieșire trezorerie " & Declarații_DIVIDENDE!B68 -> Ieșire trezorerie — AGA 12 / 2026-04-20, exercițiul 2025
A24: 3 | B24: =Declarații_DIVIDENDE!B61 -> 457.3 | C24: =IF(AND(Declarații_DIVIDENDE!B12="DA",Declarații_DIVIDENDE!B39="DA"),Declarații_DIVIDENDE!B30-ROUND(Declarații_DIVIDENDE!B30*Declarații_DIVIDENDE!B35,2),0) -> 8400 | D24: ="Plată dividend net " & Declarații_DIVIDENDE!B28 & " " & Declarații_DIVIDENDE!B68 -> Plată dividend net Xulescu — AGA 12 / 2026-04-20, exercițiul 2025 | E24: =Declarații_DIVIDENDE!B65 -> 5121 | F24: =IF(AND(Declarații_DIVIDENDE!B12="DA",Declarații_DIVIDENDE!B39="DA"),Declarații_DIVIDENDE!B30-ROUND(Declarații_DIVIDENDE!B30*Declarații_DIVIDENDE!B35,2),0) -> 8400 | G24: ="Ieșire trezorerie " & Declarații_DIVIDENDE!B68 -> Ieșire trezorerie — AGA 12 / 2026-04-20, exercițiul 2025
A25: Check B2 (457 se stinge integral după plată) | B25: =C7+C8+C9-C14-C15-C16-C22-C23-C24 -> 0 | C25: =IF(ABS(B25)<0.01,"OK — 457 = 0 pe fiecare analitic",IF(Declarații_DIVIDENDE!B39<>"DA","AȘTEPTARE — dividende neridicate: 457 rămâne cu sold, impozitul e plătit","EROARE — 457 nu se stinge")) -> OK — 457 = 0 pe fiecare analitic
A27: Bloc C — Dividende interimare
A28: Nr | B28: Cont Dr | C28: Sumă Dr | D28: Descriere Dr | E28: Cont Cr | F28: Sumă Cr | G28: Descriere Cr
A29: 1 | B29: =Declarații_DIVIDENDE!B63 -> 463 | C29: =IF(Declarații_DIVIDENDE!B42="DA",Declarații_DIVIDENDE!B47,0) -> 80000 | D29: ="Dividende interimare repartizate " & Declarații_DIVIDENDE!B68 -> Dividende interimare repartizate — AGA 12 / 2026-04-20, exercițiul 2025 | E29: =Declarații_DIVIDENDE!B64 -> 456 | F29: =IF(Declarații_DIVIDENDE!B42="DA",Declarații_DIVIDENDE!B47,0) -> 80000 | G29: ="Datorie față de asociat, interimar " & Declarații_DIVIDENDE!B68 -> Datorie față de asociat, interimar — AGA 12 / 2026-04-20, exercițiul 2025
A30: 2 | B30: =Declarații_DIVIDENDE!B64 -> 456 | C30: =IF(Declarații_DIVIDENDE!B42="DA",Declarații_DIVIDENDE!B48,0) -> 12800 | D30: ="Impozit 16% pe dividende interimare " & Declarații_DIVIDENDE!B68 -> Impozit 16% pe dividende interimare — AGA 12 / 2026-04-20, exercițiul 2025 | E30: =Declarații_DIVIDENDE!B62 -> 446.dividende | F30: =IF(Declarații_DIVIDENDE!B42="DA",Declarații_DIVIDENDE!B48,0) -> 12800 | G30: ="Impozit de plată " & Declarații_DIVIDENDE!B68 -> Impozit de plată — AGA 12 / 2026-04-20, exercițiul 2025
A31: 3 | B31: =Declarații_DIVIDENDE!B64 -> 456 | C31: =IF(Declarații_DIVIDENDE!B42="DA",Declarații_DIVIDENDE!B47-Declarații_DIVIDENDE!B48,0) -> 67200 | D31: ="Plata dividendelor interimare " & Declarații_DIVIDENDE!B68 -> Plata dividendelor interimare — AGA 12 / 2026-04-20, exercițiul 2025 | E31: =Declarații_DIVIDENDE!B65 -> 5121 | F31: =IF(Declarații_DIVIDENDE!B42="DA",Declarații_DIVIDENDE!B47-Declarații_DIVIDENDE!B48,0) -> 67200 | G31: ="Ieșire trezorerie " & Declarații_DIVIDENDE!B68 -> Ieșire trezorerie — AGA 12 / 2026-04-20, exercițiul 2025
A32: Check C (456 se stinge integral) | B32: =F29-C30-C31 -> 0 | C32: =IF(ABS(B32)<0.01,"OK — 456 = 0; 463 rămâne creanță până la 31.12","EROARE — 456 nu se stinge") -> OK — 456 = 0; 463 rămâne creanță până la 31.12
A33: Check C2 (repartizat ≤ sold 121) | B33: =IF(Declarații_DIVIDENDE!B42="DA",MAX(0,Declarații_DIVIDENDE!B47-Declarații_DIVIDENDE!B45),0) -> 0 | C33: =IF(B33<0.01,"OK — sub plafonul profitului realizat","EROARE — depășire de " & TEXT(B33,"#,##0.00") & " lei") -> OK — sub plafonul profitului realizat
A35: Bloc D — Regularizarea la 31.12 (storno)
A36: Sumele sunt NEGATIVE: stornarea se face în roșu, nu prin înregistrare inversă. Cele două rânduri se echilibrează fiecare în parte.
A37: Nr | B37: Cont Dr | C37: Sumă Dr | D37: Descriere Dr | E37: Cont Cr | F37: Sumă Cr | G37: Descriere Cr
A38: 1 | B38: =Declarații_DIVIDENDE!B63 -> 463 | C38: =IF(Declarații_DIVIDENDE!B52="DA",-Declarații_DIVIDENDE!B54,0) -> -10000 | D38: ="Storno dividende interimare nerealizate " & Declarații_DIVIDENDE!B68 -> Storno dividende interimare nerealizate — AGA 12 / 2026-04-20, exercițiul 2025 | E38: =Declarații_DIVIDENDE!B64 -> 456 | F38: =IF(Declarații_DIVIDENDE!B52="DA",-Declarații_DIVIDENDE!B54,0) -> -10000 | G38: ="Storno datorie față de asociat " & Declarații_DIVIDENDE!B68 -> Storno datorie față de asociat — AGA 12 / 2026-04-20, exercițiul 2025
A39: 2 | B39: =Declarații_DIVIDENDE!B64 -> 456 | C39: =IF(Declarații_DIVIDENDE!B52="DA",-Declarații_DIVIDENDE!B55,0) -> -1600 | D39: ="Storno impozit pe partea nerealizată " & Declarații_DIVIDENDE!B68 -> Storno impozit pe partea nerealizată — AGA 12 / 2026-04-20, exercițiul 2025 | E39: =Declarații_DIVIDENDE!B62 -> 446.dividende | F39: =IF(Declarații_DIVIDENDE!B52="DA",-Declarații_DIVIDENDE!B55,0) -> -1600 | G39: ="Storno impozit de plată (rectificativă D710) " & Declarații_DIVIDENDE!B68 -> Storno impozit de plată (rectificativă D710) — AGA 12 / 2026-04-20, exercițiul 2025
A40: 3 | B40: =Declarații_DIVIDENDE!B63 -> 463 | C40: 0 | D40: "Anul următor, la AGA: 121 = 1171, apoi 1171 = 463 pe partea rămasă" | E40: =Declarații_DIVIDENDE!B63 -> 463 | F40: 0 | G40: "Vezi F-110 pașii de închidere"
A41: Check D (storno = repartizat − profit realizat) | B41: =IF(Declarații_DIVIDENDE!B52="DA",ABS(C38)-MAX(0,Declarații_DIVIDENDE!B47-Declarații_DIVIDENDE!B53),0) -> 0 | C41: =IF(ABS(B41)<0.01,"OK — se stornează exact partea nerealizată","EROARE — stornarea nu corespunde diferenței") -> OK — se stornează exact partea nerealizată
A43: Check global | B43: =ABS(B10)+ABS(B18)+ABS(B25)+ABS(B32)+ABS(B33)+ABS(B41) -> 0 | C43: =IF(B43<0.01,"OK — toate blocurile se închid","EROARE — cel puțin un bloc nu se închide") -> OK — toate blocurile se închid
A45: Stare terminală
A46: După blocul B2: 1171 repartizat integral, 446 = 0, 457 = 0 pe fiecare analitic (dacă s-a ridicat). După blocul D: 463 rămâne la nivelul profitului realizat și se soldează anul următor, prin 1171. Rămâne de depus D710 și de recuperat de la asociat diferența stornată.

Sheet NotaExport_DIVIDENDE
A1: MOD_DIVIDENDE — Notă pentru import
A2: Filtrează Include=DA. Rândurile de storno au sumă negativă și se importă ca atare — includerea lor se decide după sumă ≠ 0, nu după semn.
A4: Nr | B4: Bloc | C4: Data | D4: Cont Dr | E4: Cont Cr | F4: Sumă | G4: Descriere | H4: Document | I4: Include
A5: 1 | B5: A Repartizare asociat 1 | C5: =Declarații_DIVIDENDE!B9 -> 2026-04-30 | D5: =Jurnale_DIVIDENDE!B7 -> 1171 | E5: =Jurnale_DIVIDENDE!E7 -> 457.1 | F5: =Jurnale_DIVIDENDE!C7 -> 10000 | G5: =Jurnale_DIVIDENDE!D7 -> Repartizare dividende Ionescu — AGA 12 / 2026-04-20, exercițiul 2025 | H5: Hotărâre AGA | I5: =IF(AND(ISNUMBER(F5),ABS(F5)>0),"DA","NU") -> DA
A6: 2 | B6: A Repartizare asociat 2 | C6: =Declarații_DIVIDENDE!B9 -> 2026-04-30 | D6: =Jurnale_DIVIDENDE!B8 -> 1171 | E6: =Jurnale_DIVIDENDE!E8 -> 457.2 | F6: =Jurnale_DIVIDENDE!C8 -> 10000 | G6: =Jurnale_DIVIDENDE!D8 -> Repartizare dividende Popescu — AGA 12 / 2026-04-20, exercițiul 2025 | H6: Hotărâre AGA | I6: =IF(AND(ISNUMBER(F6),ABS(F6)>0),"DA","NU") -> DA
A7: 3 | B7: A Repartizare asociat 3 | C7: =Declarații_DIVIDENDE!B9 -> 2026-04-30 | D7: =Jurnale_DIVIDENDE!B9 -> 1171 | E7: =Jurnale_DIVIDENDE!E9 -> 457.3 | F7: =Jurnale_DIVIDENDE!C9 -> 10000 | G7: =Jurnale_DIVIDENDE!D9 -> Repartizare dividende Xulescu — AGA 12 / 2026-04-20, exercițiul 2025 | H7: Hotărâre AGA | I7: =IF(AND(ISNUMBER(F7),ABS(F7)>0),"DA","NU") -> DA
A8: 4 | B8: B Impozit asociat 1 | C8: =Declarații_DIVIDENDE!B9 -> 2026-04-30 | D8: =Jurnale_DIVIDENDE!B14 -> 457.1 | E8: =Jurnale_DIVIDENDE!E14 -> 446.dividende | F8: =Jurnale_DIVIDENDE!C14 -> 1600 | G8: =Jurnale_DIVIDENDE!D14 -> Impozit 16% dividende Ionescu — AGA 12 / 2026-04-20, exercițiul 2025 | H8: Notă contabilă | I8: =IF(AND(ISNUMBER(F8),ABS(F8)>0),"DA","NU") -> DA
A9: 5 | B9: B Impozit asociat 2 | C9: =Declarații_DIVIDENDE!B9 -> 2026-04-30 | D9: =Jurnale_DIVIDENDE!B15 -> 457.2 | E9: =Jurnale_DIVIDENDE!E15 -> 446.dividende | F9: =Jurnale_DIVIDENDE!C15 -> 1600 | G9: =Jurnale_DIVIDENDE!D15 -> Impozit 16% dividende Popescu — AGA 12 / 2026-04-20, exercițiul 2025 | H9: Notă contabilă | I9: =IF(AND(ISNUMBER(F9),ABS(F9)>0),"DA","NU") -> DA
A10: 6 | B10: B Impozit asociat 3 | C10: =Declarații_DIVIDENDE!B9 -> 2026-04-30 | D10: =Jurnale_DIVIDENDE!B16 -> 457.3 | E10: =Jurnale_DIVIDENDE!E16 -> 446.dividende | F10: =Jurnale_DIVIDENDE!C16 -> 1600 | G10: =Jurnale_DIVIDENDE!D16 -> Impozit 16% dividende Xulescu — AGA 12 / 2026-04-20, exercițiul 2025 | H10: Notă contabilă | I10: =IF(AND(ISNUMBER(F10),ABS(F10)>0),"DA","NU") -> DA
A11: 7 | B11: B Plata impozitului | C11: =Declarații_DIVIDENDE!B9 -> 2026-04-30 | D11: =Jurnale_DIVIDENDE!B17 -> 446.dividende | E11: =Jurnale_DIVIDENDE!E17 -> 5121 | F11: =Jurnale_DIVIDENDE!C17 -> 4800 | G11: =Jurnale_DIVIDENDE!D17 -> Plata impozitului pe dividende (termen 25.01) — AGA 12 / 2026-04-20, exercițiul 2025 | H11: Ordin de plată | I11: =IF(AND(ISNUMBER(F11),ABS(F11)>0),"DA","NU") -> DA
A12: 8 | B12: B2 Plată net asociat 1 | C12: =Declarații_DIVIDENDE!B9 -> 2026-04-30 | D12: =Jurnale_DIVIDENDE!B22 -> 457.1 | E12: =Jurnale_DIVIDENDE!E22 -> 5121 | F12: =Jurnale_DIVIDENDE!C22 -> 8400 | G12: =Jurnale_DIVIDENDE!D22 -> Plată dividend net Ionescu — AGA 12 / 2026-04-20, exercițiul 2025 | H12: Ordin de plată | I12: =IF(AND(ISNUMBER(F12),ABS(F12)>0),"DA","NU") -> DA
A13: 9 | B13: B2 Plată net asociat 2 | C13: =Declarații_DIVIDENDE!B9 -> 2026-04-30 | D13: =Jurnale_DIVIDENDE!B23 -> 457.2 | E13: =Jurnale_DIVIDENDE!E23 -> 5121 | F13: =Jurnale_DIVIDENDE!C23 -> 8400 | G13: =Jurnale_DIVIDENDE!D23 -> Plată dividend net Popescu — AGA 12 / 2026-04-20, exercițiul 2025 | H13: Ordin de plată | I13: =IF(AND(ISNUMBER(F13),ABS(F13)>0),"DA","NU") -> DA
A14: 10 | B14: B2 Plată net asociat 3 | C14: =Declarații_DIVIDENDE!B9 -> 2026-04-30 | D14: =Jurnale_DIVIDENDE!B24 -> 457.3 | E14: =Jurnale_DIVIDENDE!E24 -> 5121 | F14: =Jurnale_DIVIDENDE!C24 -> 8400 | G14: =Jurnale_DIVIDENDE!D24 -> Plată dividend net Xulescu — AGA 12 / 2026-04-20, exercițiul 2025 | H14: Ordin de plată | I14: =IF(AND(ISNUMBER(F14),ABS(F14)>0),"DA","NU") -> DA
A15: 11 | B15: C Interimare — repartizare | C15: =Declarații_DIVIDENDE!B9 -> 2026-04-30 | D15: =Jurnale_DIVIDENDE!B29 -> 463 | E15: =Jurnale_DIVIDENDE!E29 -> 456 | F15: =Jurnale_DIVIDENDE!C29 -> 80000 | G15: =Jurnale_DIVIDENDE!D29 -> Dividende interimare repartizate — AGA 12 / 2026-04-20, exercițiul 2025 | H15: Hotărâre AGA + bilanț interimar | I15: =IF(AND(ISNUMBER(F15),ABS(F15)>0),"DA","NU") -> DA
A16: 12 | B16: C Interimare — impozit | C16: =Declarații_DIVIDENDE!B9 -> 2026-04-30 | D16: =Jurnale_DIVIDENDE!B30 -> 456 | E16: =Jurnale_DIVIDENDE!E30 -> 446.dividende | F16: =Jurnale_DIVIDENDE!C30 -> 12800 | G16: =Jurnale_DIVIDENDE!D30 -> Impozit 16% pe dividende interimare — AGA 12 / 2026-04-20, exercițiul 2025 | H16: Notă contabilă | I16: =IF(AND(ISNUMBER(F16),ABS(F16)>0),"DA","NU") -> DA
A17: 13 | B17: C Interimare — plată | C17: =Declarații_DIVIDENDE!B9 -> 2026-04-30 | D17: =Jurnale_DIVIDENDE!B31 -> 456 | E17: =Jurnale_DIVIDENDE!E31 -> 5121 | F17: =Jurnale_DIVIDENDE!C31 -> 67200 | G17: =Jurnale_DIVIDENDE!D31 -> Plata dividendelor interimare — AGA 12 / 2026-04-20, exercițiul 2025 | H17: Ordin de plată | I17: =IF(AND(ISNUMBER(F17),ABS(F17)>0),"DA","NU") -> DA
A18: 14 | B18: D Storno interimare | C18: =Declarații_DIVIDENDE!B9 -> 2026-04-30 | D18: =Jurnale_DIVIDENDE!B38 -> 463 | E18: =Jurnale_DIVIDENDE!E38 -> 456 | F18: =Jurnale_DIVIDENDE!C38 -> -10000 | G18: =Jurnale_DIVIDENDE!D38 -> Storno dividende interimare nerealizate — AGA 12 / 2026-04-20, exercițiul 2025 | H18: Notă contabilă 31.12 | I18: =IF(AND(ISNUMBER(F18),ABS(F18)>0),"DA","NU") -> DA
A19: 15 | B19: D Storno impozit | C19: =Declarații_DIVIDENDE!B9 -> 2026-04-30 | D19: =Jurnale_DIVIDENDE!B39 -> 456 | E19: =Jurnale_DIVIDENDE!E39 -> 446.dividende | F19: =Jurnale_DIVIDENDE!C39 -> -1600 | G19: =Jurnale_DIVIDENDE!D39 -> Storno impozit pe partea nerealizată — AGA 12 / 2026-04-20, exercițiul 2025 | H19: Notă contabilă + D710 | I19: =IF(AND(ISNUMBER(F19),ABS(F19)>0),"DA","NU") -> DA
A20: 16 | B20: D Închidere anul următor | C20: =Declarații_DIVIDENDE!B9 -> 2026-04-30 | D20: =Jurnale_DIVIDENDE!B40 -> 463 | E20: =Jurnale_DIVIDENDE!E40 -> 463 | F20: =Jurnale_DIVIDENDE!C40 -> 0 | G20: =Jurnale_DIVIDENDE!D40 -> "Anul următor, la AGA: 121 = 1171, apoi 1171 = 463 pe partea rămasă" | H20: Hotărâre AGA anul următor | I20: =IF(AND(ISNUMBER(F20),ABS(F20)>0),"DA","NU") -> NU
A22: Rânduri de importat | B22: =COUNTIF(I5:I20,"DA") -> 15
A23: Check global | B23: =Jurnale_DIVIDENDE!B43 -> 0 | C23: =IF(ABS(B23)<0.01,"OK","EROARE") -> OK

Sheet Declarații_IMOBILIZARI
A1: MOD_IMOBILIZARI — Declarații (input)
A2: Completează doar celulele galbene. Regimul de TVA activează singur blocul potrivit.
A4: 1. Antet
A5: Societate | B5: =Parametri!B5 -> SC EXEMPLU SRL
A6: Denumire mijloc fix | B6: Echipament tehnologic
A7: Luna | B7: 2026-07
A8: Data facturii | B8: 2026-07-05
A9: Data punerii în funcțiune | B9: 2026-07-20
A11: 2. Valori
A12: Valoare din factură / DVI (fără TVA) | B12: 100000
A13: Taxe vamale (0 dacă nu e import) | B13: 0 | C13: Se CAPITALIZEAZĂ, nu se trec pe 635
A14: Transport și manipulare până la recepție | B14: 0 | C14: Intră tot în costul de achiziție
A15: Cotă TVA | B15: =Parametri!B10 -> 0.21
A17: 3. Regim și clasificare
A18: Regim TVA (INTERN / TAXARE_INVERSA / IMPORT) | B18: INTERN
A19: Bunul a fost recepționat? (DA / NU) | B19: DA | C19: NU → intrarea se face pe 223/224 (tranzit), vezi F-207
A20: Cod de clasificare din catalog | B20: 2.1.16.4.1
A21: Durată de amortizare (luni) | B21: 120 | C21: Din catalogul de clasificare; merge în D406/SAF-T
A23: 4. Calcul automat (nu edita)
A24: Valoare de intrare (cost complet) | B24: =B12+B13+B14 -> 100000
A25: TVA aferentă | B25: =B12*B15 -> 21000
A26: Amortizare lunară | B26: =ROUND(B24/B21,2) -> 833.33
A27: Test prag mijloc fix | B27: =B24 -> 100000 | C27: =IF(B24>=param_prag_mf,"OK — mijloc fix, se amortizează","ATENȚIE — sub prag: obiect de inventar (303), nu mijloc fix") -> OK — mijloc fix, se amortizează
A28: Test recepție | B28: =B19 -> DA | C28: =IF(B19="DA","OK — intrare directă în contul de imobilizare","TRANZIT — se înregistrează pe 223/224 până la recepție (F-207)") -> OK — intrare directă în contul de imobilizare
A29: Test regim TVA | B29: =B18 -> INTERN | C29: =IF(OR(B18="INTERN",B18="TAXARE_INVERSA",B18="IMPORT"),"OK — regim recunoscut","EROARE — regim necunoscut") -> OK — regim recunoscut
A31: 5. Conturi
A32: Cont imobilizare (21x) | B32: 2131
A33: Cont amortizare (28x) — oglinda | B33: 2813 | C33: C-14: 212↔2812, 213x↔2813, 214↔2814, 215↔2815
A34: Cont tranzit dacă nerecepționat | B34: 223
A35: Cont furnizor de imobilizări | B35: 404
A36: Cont TVA deductibilă | B36: 4426
A37: Cont TVA colectată (taxare inversă) | B37: 4427
A38: Cont taxe vamale | B38: 446.VAMA
A39: Cont bancă | B39: 5121
A40: Cont cheltuială cu amortizarea | B40: 6811
A42: 6. Sufix generat
A43: Sufix | B43: ="— " & B6 & " " & B7 -> — Echipament tehnologic 2026-07
A45: Modul activ în CatalogModule? | B45: =IF(INDEX(CatalogModule!$A$1:$A$200,MATCH("MOD_IMOBILIZARI",CatalogModule!$B$1:$B$200,0))="DA","ACTIV — jurnalele se generează","INACTIV — jurnalele rămân goale") -> INACTIV — jurnalele rămân goale

Sheet Reguli_IMOBILIZARI
A1: MOD_IMOBILIZARI — Reguli (tabele fixe)
A2: Se editează doar când se schimbă legea sau catalogul de clasificare.
A4: Tabel A — Regimuri de TVA la intrare
A5: Regim | B5: Cont Dr | C5: Cont Cr | D5: Sumă | E5: Condiție | F5: Temei / observație
A6: INTERN | B6: 4426 | C6: 404 | D6: valoare × cotă | E6: Furnizor român plătitor | F6: TVA deductibilă normală
A7: TAXARE_INVERSA | B7: 4426 | C7: 4427 | D7: valoare × cota din România | E7: Achiziție intracomunitară SAU art. 331 intern | F7: IC: cere VIES valid + dovada transportului. Clădiri: cod 27 în D394, altfel decontul nu recunoaște operațiunea
A8: IMPORT | B8: 4426 | C8: 5121 | D8: TVA plătit efectiv în vamă | E8: Import din afara UE | F8: Document de bază: DVI, nu factura furnizorului. Cu certificat de amânare: 4426 = 4427
A10: Tabel B — Ce intră în costul de achiziție
A11: Element | B11: Tratament | F11: Temei
A12: Preț din factură / DVI | B12: capitalizat | F12: OMFP 1802/2014
A13: Taxe vamale nerecuperabile | B13: CAPITALIZAT — nu pe 635 | F13: OMFP 1802/2014
A14: Transport și manipulare până la recepție | B14: capitalizat | F14: OMFP 1802/2014
A15: TVA nedeductibilă (ex. 50% vehicule) | B15: capitalizată sau pe cheltuială | F15: vezi MOD_LEASING_FIN
A16: Dobânzi de finanțare | B16: de regulă pe cheltuială | F16: OMFP 1802/2014
A18: Tabel C — Oglinda cont activ ↔ cont amortizare (C-14)
A19: Activ | B19: Amortizare | D19: Activ | E19: Amortizare | F19: Observație
A20: 205 | B20: 2805 | D20: 212 | E20: 2812
A21: 208 | B21: 2808 | D21: 2131/2132/2133 | E21: 2813 | F21: 2813 deservește mai multe conturi
A22: 2111 | B22: — nu se amortizează | D22: 214 | E22: 2814 | F22: „2114” din notițe este 214
A23: 2112 | B23: 2811 | D23: 215 | E23: 2815
A25: Tabel D — Porți de calitate
A26: • ΣDr = ΣCr pe fiecare bloc
A27: • Amortizarea începe cu luna următoare punerii în funcțiune
A28: • Sold 28x ≤ sold 21x, pe fiecare mijloc (C-13)
A29: • Analitic 21x din balanță = registrul mijloacelor fixe, LUNAR (C-15)
A30: • Verifică în PRIMA lună că nota de amortizare postează perechea corectă (C-14)
A31: • Sub pragul de 5.000 lei: obiect de inventar (303 + 8035), nu mijloc fix
A32: • Declarație la primărie în 30 de zile de la achiziție

Sheet Jurnale_IMOBILIZARI
A1: MOD_IMOBILIZARI — Jurnale (generate automat)
A2: Blocurile inactive rămân pe zero — sumele sunt condiționate de regimul declarat.
A4: Bloc 1 — Intrarea în patrimoniu
A5: Data jurnal: | B5: =Declarații_IMOBILIZARI!B8 -> 2026-07-05
A7: Nr | B7: Cont Dr | C7: Sumă Dr | D7: Descriere Dr | E7: Cont Cr | F7: Sumă Cr | G7: Descriere Cr
A8: 1 | B8: =IF(Declarații_IMOBILIZARI!B19="DA",Declarații_IMOBILIZARI!B32,Declarații_IMOBILIZARI!B34) -> 2131 | C8: =Declarații_IMOBILIZARI!B12 -> 100000 | D8: ="Intrare imobilizare " & Declarații_IMOBILIZARI!B43 -> Intrare imobilizare — Echipament tehnologic 2026-07 | E8: =Declarații_IMOBILIZARI!B35 -> 404 | F8: =Declarații_IMOBILIZARI!B12 -> 100000 | G8: ="Datorie furnizor de imobilizări " & Declarații_IMOBILIZARI!B43 -> Datorie furnizor de imobilizări — Echipament tehnologic 2026-07
A9: 2 | B9: =IF(Declarații_IMOBILIZARI!B19="DA",Declarații_IMOBILIZARI!B32,Declarații_IMOBILIZARI!B34) -> 2131 | C9: =Declarații_IMOBILIZARI!B13+Declarații_IMOBILIZARI!B14 -> 0 | D9: ="Taxe vamale și transport capitalizate " & Declarații_IMOBILIZARI!B43 -> Taxe vamale și transport capitalizate — Echipament tehnologic 2026-07 | E9: =Declarații_IMOBILIZARI!B38 -> 446.VAMA | F9: =Declarații_IMOBILIZARI!B13+Declarații_IMOBILIZARI!B14 -> 0 | G9: ="Taxe vamale / transport de plată " & Declarații_IMOBILIZARI!B43 -> Taxe vamale / transport de plată — Echipament tehnologic 2026-07
A11: Bloc 2 — TVA, pe regimul declarat
A12: Nr | B12: Cont Dr | C12: Sumă Dr | D12: Descriere Dr | E12: Cont Cr | F12: Sumă Cr | G12: Descriere Cr
A13: 1 | B13: =Declarații_IMOBILIZARI!B36 -> 4426 | C13: =IF(Declarații_IMOBILIZARI!B18="INTERN",Declarații_IMOBILIZARI!B25,0) -> 21000 | D13: ="TVA deductibilă — achiziție internă " & Declarații_IMOBILIZARI!B43 -> TVA deductibilă — achiziție internă — Echipament tehnologic 2026-07 | E13: =Declarații_IMOBILIZARI!B35 -> 404 | F13: =IF(Declarații_IMOBILIZARI!B18="INTERN",Declarații_IMOBILIZARI!B25,0) -> 21000 | G13: ="TVA pe factura furnizorului " & Declarații_IMOBILIZARI!B43 -> TVA pe factura furnizorului — Echipament tehnologic 2026-07
A14: 2 | B14: =Declarații_IMOBILIZARI!B36 -> 4426 | C14: =IF(Declarații_IMOBILIZARI!B18="TAXARE_INVERSA",Declarații_IMOBILIZARI!B25,0) -> 0 | D14: ="TVA deductibilă — taxare inversă " & Declarații_IMOBILIZARI!B43 -> TVA deductibilă — taxare inversă — Echipament tehnologic 2026-07 | E14: =Declarații_IMOBILIZARI!B37 -> 4427 | F14: =IF(Declarații_IMOBILIZARI!B18="TAXARE_INVERSA",Declarații_IMOBILIZARI!B25,0) -> 0 | G14: ="TVA colectată — autolichidare " & Declarații_IMOBILIZARI!B43 -> TVA colectată — autolichidare — Echipament tehnologic 2026-07
A15: 3 | B15: =Declarații_IMOBILIZARI!B36 -> 4426 | C15: =IF(Declarații_IMOBILIZARI!B18="IMPORT",Declarații_IMOBILIZARI!B25,0) -> 0 | D15: ="TVA deductibilă plătită în vamă " & Declarații_IMOBILIZARI!B43 -> TVA deductibilă plătită în vamă — Echipament tehnologic 2026-07 | E15: =Declarații_IMOBILIZARI!B39 -> 5121 | F15: =IF(Declarații_IMOBILIZARI!B18="IMPORT",Declarații_IMOBILIZARI!B25,0) -> 0 | G15: ="Plată TVA în vamă " & Declarații_IMOBILIZARI!B43 -> Plată TVA în vamă — Echipament tehnologic 2026-07
A17: Bloc 3 — Recepția, dacă intrarea a fost pe tranzit (F-207)
A18: Nr | B18: Cont Dr | C18: Sumă Dr | D18: Descriere Dr | E18: Cont Cr | F18: Sumă Cr | G18: Descriere Cr
A19: 1 | B19: =Declarații_IMOBILIZARI!B32 -> 2131 | C19: =IF(Declarații_IMOBILIZARI!B19="NU",Declarații_IMOBILIZARI!B24,0) -> 0 | D19: ="Recepție — stingere tranzit " & Declarații_IMOBILIZARI!B43 -> Recepție — stingere tranzit — Echipament tehnologic 2026-07 | E19: =Declarații_IMOBILIZARI!B34 -> 223 | F19: =IF(Declarații_IMOBILIZARI!B19="NU",Declarații_IMOBILIZARI!B24,0) -> 0 | G19: ="Stingere 223/224 la recepție " & Declarații_IMOBILIZARI!B43 -> Stingere 223/224 la recepție — Echipament tehnologic 2026-07
A21: Bloc 4 — Amortizarea lunară (din luna următoare punerii în funcțiune)
A22: Nr | B22: Cont Dr | C22: Sumă Dr | D22: Descriere Dr | E22: Cont Cr | F22: Sumă Cr | G22: Descriere Cr
A23: 1 | B23: =Declarații_IMOBILIZARI!B40 -> 6811 | C23: =Declarații_IMOBILIZARI!B26 -> 833.33 | D23: ="Amortizare lunară " & Declarații_IMOBILIZARI!B43 -> Amortizare lunară — Echipament tehnologic 2026-07 | E23: =Declarații_IMOBILIZARI!B33 -> 2813 | F23: =Declarații_IMOBILIZARI!B26 -> 833.33 | G23: ="Amortizare cumulată " & Declarații_IMOBILIZARI!B43 -> Amortizare cumulată — Echipament tehnologic 2026-07
A25: Sumar și controale
A26: Total Dr | B26: =C8+C9+C13+C14+C15+C19+C23 -> 121833.33
A27: Total Cr | B27: =F8+F9+F13+F14+F15+F19+F23 -> 121833.33
A28: Check Σ (structural) | B28: =B26-B27 -> 0 | C28: =IF(ABS(B26-B27)<0.01,"OK — notele se închid","EROARE") -> OK — notele se închid
A29: Check exclusivitate regim TVA | B29: =COUNTIF(C13:C15,">0.001") -> 1 | C29: =IF(COUNTIF(C13:C15,">0.001")<=1,"OK — un singur regim activ","EROARE — mai multe regimuri simultan") -> OK — un singur regim activ
A30: Check valoare de intrare | B30: =C8+C9-Declarații_IMOBILIZARI!B24 -> 0 | C30: =IF(ABS(C8+C9-Declarații_IMOBILIZARI!B24)<0.01,"OK — cost complet capitalizat","EROARE — taxe sau transport pierdute") -> OK — cost complet capitalizat
A31: Check amortizare vs. durată | B31: =Declarații_IMOBILIZARI!B26*Declarații_IMOBILIZARI!B21-Declarații_IMOBILIZARI!B24 -> -0.4 | C31: =IF(ABS(Declarații_IMOBILIZARI!B26*Declarații_IMOBILIZARI!B21-Declarații_IMOBILIZARI!B24)<1,"OK — planul acoperă valoarea de intrare","ATENȚIE — diferență din rotunjire, se regularizează la ultima rată") -> OK — planul acoperă valoarea de intrare
A32: Stare terminală așteptată: 21x = valoarea de intrare completă, sold 223/224 = 0, 28x crește lunar și nu depășește niciodată 21x.

Sheet NotaExport_IMOBILIZARI
A1: MOD_IMOBILIZARI — Notă pentru import (1 rând = 1 înregistrare)
A2: Filtrează pe Include = DA. Rândurile cu sumă zero sunt blocuri inactive pe regimul ales.
A4: Nr | B4: Bloc | C4: Data | D4: Cont Dr | E4: Cont Cr | F4: Sumă | G4: Descriere | H4: Document | I4: Include
A5: 1 | B5: Bloc 1 — Intrare | C5: =Declarații_IMOBILIZARI!B8 -> 2026-07-05 | D5: =Jurnale_IMOBILIZARI!B8 -> 2131 | E5: =Jurnale_IMOBILIZARI!E8 -> 404 | F5: =Jurnale_IMOBILIZARI!C8 -> 100000 | G5: =Jurnale_IMOBILIZARI!D8 -> Intrare imobilizare — Echipament tehnologic 2026-07 | H5: Factură / DVI | I5: =IF(F5>0.001,"DA","NU") -> DA
A6: 2 | B6: Bloc 1 — Costuri capitalizate | C6: =Declarații_IMOBILIZARI!B8 -> 2026-07-05 | D6: =Jurnale_IMOBILIZARI!B9 -> 2131 | E6: =Jurnale_IMOBILIZARI!E9 -> 446.VAMA | F6: =Jurnale_IMOBILIZARI!C9 -> 0 | G6: =Jurnale_IMOBILIZARI!D9 -> Taxe vamale și transport capitalizate — Echipament tehnologic 2026-07 | H6: DVI + factură transport | I6: =IF(F6>0.001,"DA","NU") -> NU
A7: 3 | B7: Bloc 2 — TVA intern | C7: =Declarații_IMOBILIZARI!B8 -> 2026-07-05 | D7: =Jurnale_IMOBILIZARI!B13 -> 4426 | E7: =Jurnale_IMOBILIZARI!E13 -> 404 | F7: =Jurnale_IMOBILIZARI!C13 -> 21000 | G7: =Jurnale_IMOBILIZARI!D13 -> TVA deductibilă — achiziție internă — Echipament tehnologic 2026-07 | H7: Factură furnizor | I7: =IF(F7>0.001,"DA","NU") -> DA
A8: 4 | B8: Bloc 2 — TVA taxare inversă | C8: =Declarații_IMOBILIZARI!B8 -> 2026-07-05 | D8: =Jurnale_IMOBILIZARI!B14 -> 4426 | E8: =Jurnale_IMOBILIZARI!E14 -> 4427 | F8: =Jurnale_IMOBILIZARI!C14 -> 0 | G8: =Jurnale_IMOBILIZARI!D14 -> TVA deductibilă — taxare inversă — Echipament tehnologic 2026-07 | H8: Autofactură / factură IC | I8: =IF(F8>0.001,"DA","NU") -> NU
A9: 5 | B9: Bloc 2 — TVA în vamă | C9: =Declarații_IMOBILIZARI!B8 -> 2026-07-05 | D9: =Jurnale_IMOBILIZARI!B15 -> 4426 | E9: =Jurnale_IMOBILIZARI!E15 -> 5121 | F9: =Jurnale_IMOBILIZARI!C15 -> 0 | G9: =Jurnale_IMOBILIZARI!D15 -> TVA deductibilă plătită în vamă — Echipament tehnologic 2026-07 | H9: DVI + extras | I9: =IF(F9>0.001,"DA","NU") -> NU
A10: 6 | B10: Bloc 3 — Recepție | C10: =Declarații_IMOBILIZARI!B8 -> 2026-07-05 | D10: =Jurnale_IMOBILIZARI!B19 -> 2131 | E10: =Jurnale_IMOBILIZARI!E19 -> 223 | F10: =Jurnale_IMOBILIZARI!C19 -> 0 | G10: =Jurnale_IMOBILIZARI!D19 -> Recepție — stingere tranzit — Echipament tehnologic 2026-07 | H10: Proces-verbal de recepție | I10: =IF(F10>0.001,"DA","NU") -> NU
A11: 7 | B11: Bloc 4 — Amortizare | C11: =Declarații_IMOBILIZARI!B9 -> 2026-07-20 | D11: =Jurnale_IMOBILIZARI!B23 -> 6811 | E11: =Jurnale_IMOBILIZARI!E23 -> 2813 | F11: =Jurnale_IMOBILIZARI!C23 -> 833.33 | G11: =Jurnale_IMOBILIZARI!D23 -> Amortizare lunară — Echipament tehnologic 2026-07 | H11: Notă de amortizare | I11: =IF(F11>0.001,"DA","NU") -> DA
A13: Rânduri de importat (Include=DA) | B13: =COUNTIF(I5:I11,"DA") -> 3
A14: Check global (trebuie 0) | B14: =Jurnale_IMOBILIZARI!B26-Jurnale_IMOBILIZARI!B27 -> 0 | C14: =IF(ABS(Jurnale_IMOBILIZARI!B26-Jurnale_IMOBILIZARI!B27)<0.01,"OK","EROARE") -> OK

Sheet Declarații_NEUTRALIZARE
A1: MOD_NEUTRALIZARE — Declarații (input)
A2: Acoperă F-311 (bunuri/711), F-312 (servicii/712), F-209 (imobilizări/722). Alege tipul — conturile și lanțul se adaptează. Principiu: costurile lovesc cls.6, apoi contul de venit de producție capitalizează și neutralizează.
A4: 1. Antet
A5: Societate | B5: =Parametri!B5 -> SC EXEMPLU SRL
A6: CUI | B6: =Parametri!B6 -> RO00000000
A7: Luna / proiect | B7: 2026-07
A8: Data costuri (B1) | B8: 2026-07-05
A9: Data finalizare stoc (B2-B3) | B9: 2026-07-20
A10: Data vânzare / recepție MF (B4) | B10: 2026-07-25
A12: 2. Tip producție (poartă principală)
A13: Tip (BUNURI / SERVICII / MF) | B13: BUNURI
A14: Cont venit neutralizare (auto) | B14: =IF(B13="BUNURI",711,IF(B13="SERVICII",712,IF(B13="MF",722,"?"))) -> 711
A15: Cont stoc intermediar (auto) | B15: =IF(B13="BUNURI",331,IF(B13="SERVICII",332,IF(B13="MF",231,"?"))) -> 331
A16: Cont stoc final (auto) | B16: =IF(B13="BUNURI",345,IF(B13="SERVICII","(nu e cazul — se stinge la livrare)",IF(B13="MF",213,"?"))) -> 345
A17: Cont venit vânzare (auto) | B17: =IF(B13="BUNURI",701,IF(B13="SERVICII",704,IF(B13="MF","(nu e vânzare — e activ)","?"))) -> 701
A19: 3. Costuri (cls.6)
A20: Cost materiale (→ 601) | B20: 4500
A21: Cost manoperă (→ 641) | B21: 0
A22: Alte costuri (→ 6xx) | B22: 0
A23: Cost total | B23: =B20+B21+B22 -> 4500
A25: 4. Vânzare (doar BUNURI / SERVICII)
A26: Preț vânzare (fără TVA) | B26: 7000
A27: Cota TVA | B27: 0.21
A28: TVA | B28: =IF(OR(B13="BUNURI",B13="SERVICII"),B26*B27,0) -> 1470
A29: Total factură | B29: =B26+B28 -> 8470
A31: 5. Conturi suplimentare
A32: Cont materii prime | B32: 301
A33: Cont client | B33: 411.RO
A34: Cont TVA colectată | B34: 4427
A36: 6. Sufix
A37: Sufix | B37: ="— " & B7 & " — " & B13 & " — " & B14 -> — 2026-07 — BUNURI — 711
A39: 7. Control
A40: Marjă (vânzare − cost) | B40: =IF(OR(B13="BUNURI",B13="SERVICII"),B26-B23,"n/a (MF)") -> 2500
A41: Notă principiu | B41: Costurile lovesc cls.6; contul de venit de producție (711/712/722) capitalizează și neutralizează. Descărcarea la vânzare (bunuri) e prin 711=345, nu prin 607.

Sheet Reguli_NEUTRALIZARE
A1: MOD_NEUTRALIZARE — Reguli (tabele fixe)
A2: Principiul comun F-311 / F-312 / F-209: cost → cls.6 → stoc intermediar = venit neutralizare → stoc final / livrare. 711/712/722 nu se stinge greșit în stocul final fără pasul de obținere.
A4: Tabel A — Lanț pe tip
A5: Tip | B5: Cost → | C5: Stoc intermediar | D5: Venit neut. | E5: Stoc final / livrare | F5: Descărcare la vânzare
A6: BUNURI | B6: 601=301 | C6: 331=711 | D6: 711=331 apoi 345=711 | E6: 345 | F6: 711=345 (NU 607)
A7: SERVICII | B7: 641/601=… | C7: 332=712 | D7: 712=332 | E7: (nu e stoc final) | F7: 712 stins la livrare
A8: MF | B8: 601=301, 641=421 | C8: 231=722 | D8: — | E8: 213=231 | F8: (nu e vânzare — e activ)
A10: Tabel B — Porți de calitate
A11: • ΣD=ΣC pe fiecare bloc
A12: • Cont venit neutralizare: rulaj D = rulaj C la final (sold 0)
A13: • Stoc intermediar sold 0 după finalizare
A14: • Pentru BUNURI: 345 un singur D și un singur C; descărcare prin 711, nu 607
A15: • Pentru MF: impact net pe 121 din capitalizare = 0 (cheltuieli = 722)
A17: Tabel C — Ce NU se face
A18: • 345 creditat de două ori fără un debit de obținere (eroarea F-311 veche)
A19: • 722 = 231 (ar stinge activul — eroare F-209 veche); corect e 231 = 722
A20: • 607 la descărcarea produselor finite (607 e doar mărfuri)
A21: • „711 sau 712” la servicii — pentru servicii e strict 712
A23: Temei legal
A24: Ce se sprijină pe el | B24: Temei
A25: Producția de imobilizări în regie proprie se evidențiază prin 722 | B25: OMFP 1802/2014 — funcțiunea contului 722
A26: Variația stocurilor de produse și producție în curs, prin 711 | B26: OMFP 1802/2014 — funcțiunea contului 711
A27: Costul de producție cuprinde materiile, manopera și cota de cheltuieli indirecte | B27: OMFP 1802/2014, pct. 9

Sheet Jurnale_NEUTRALIZARE
A1: MOD_NEUTRALIZARE — Jurnale (generate automat)
A2: Lanțul se adaptează după Tip. Pentru MF, blocul de vânzare rămâne 0. Pentru SERVICII, stocul final e gol.
A4: Bloc 1 — Costuri pe cls.6
A5: Data: | B5: =Declarații_NEUTRALIZARE!B8 -> 2026-07-05
A6: Nr | B6: Cont Dr | C6: Sumă Dr | D6: Descriere Dr | E6: Cont Cr | F6: Sumă Cr | G6: Descriere Cr
A7: 1 | B7: 601 | C7: =Declarații_NEUTRALIZARE!B20 -> 4500 | D7: ="Consum materiale " & Declarații_NEUTRALIZARE!B37 -> Consum materiale — 2026-07 — BUNURI — 711 | E7: =Declarații_NEUTRALIZARE!B32 -> 301 | F7: =Declarații_NEUTRALIZARE!B20 -> 4500 | G7: ="Stingere stoc materii " & Declarații_NEUTRALIZARE!B37 -> Stingere stoc materii — 2026-07 — BUNURI — 711
A8: 2 | B8: 641 | C8: =Declarații_NEUTRALIZARE!B21 -> 0 | D8: ="Manoperă pe proiect " & Declarații_NEUTRALIZARE!B37 -> Manoperă pe proiect — 2026-07 — BUNURI — 711 | E8: 421 | F8: =Declarații_NEUTRALIZARE!B21 -> 0 | G8: ="Datorie salarii " & Declarații_NEUTRALIZARE!B37 -> Datorie salarii — 2026-07 — BUNURI — 711
A9: Check B1 | B9: =(C7+C8)-(F7+F8) -> 0 | C9: =IF(ABS(B9)<0.01,"OK","EROARE") -> OK
A11: Bloc 2 — Stoc intermediar = venit neutralizare (pas revelator)
A12: Data: | B12: =Declarații_NEUTRALIZARE!B9 -> 2026-07-20
A13: Nr | B13: Cont Dr | C13: Sumă Dr | D13: Descriere Dr | E13: Cont Cr | F13: Sumă Cr | G13: Descriere Cr
A14: 1 | B14: =Declarații_NEUTRALIZARE!B15 -> 331 | C14: =Declarații_NEUTRALIZARE!B23 -> 4500 | D14: ="Stoc intermediar (PN/servicii/MF în curs) " & Declarații_NEUTRALIZARE!B37 -> Stoc intermediar (PN/servicii/MF în curs) — 2026-07 — BUNURI — 711 | E14: =Declarații_NEUTRALIZARE!B14 -> 711 | F14: =Declarații_NEUTRALIZARE!B23 -> 4500 | G14: ="Venit producție / neutralizare " & Declarații_NEUTRALIZARE!B37 -> Venit producție / neutralizare — 2026-07 — BUNURI — 711
A15: Check B2 | B15: =C14-F14 -> 0 | C15: =IF(ABS(B15)<0.01,"OK","EROARE") -> OK
A17: Bloc 3 — Finalizare (obținere stoc final / stingere intermediar)
A18: Data: | B18: =Declarații_NEUTRALIZARE!B9 -> 2026-07-20
A19: Nr | B19: Cont Dr | C19: Sumă Dr | D19: Descriere Dr | E19: Cont Cr | F19: Sumă Cr | G19: Descriere Cr
A20: 1 | B20: =IF(Declarații_NEUTRALIZARE!B13="BUNURI",Declarații_NEUTRALIZARE!B14,IF(Declarații_NEUTRALIZARE!B13="SERVICII",Declarații_NEUTRALIZARE!B14,Declarații_NEUTRALIZARE!B16)) -> 711 | C20: =Declarații_NEUTRALIZARE!B23 -> 4500 | D20: =IF(Declarații_NEUTRALIZARE!B13="BUNURI","Reluare PN (711 debitat #1) ",IF(Declarații_NEUTRALIZARE!B13="SERVICII","Stingere servicii în curs ","Transfer MF final ")) & Declarații_NEUTRALIZARE!B37 -> Reluare PN (711 debitat #1) — 2026-07 — BUNURI — 711 | E20: =IF(Declarații_NEUTRALIZARE!B13="MF",Declarații_NEUTRALIZARE!B15,Declarații_NEUTRALIZARE!B15) -> 331 | F20: =Declarații_NEUTRALIZARE!B23 -> 4500 | G20: ="Stingere stoc intermediar " & Declarații_NEUTRALIZARE!B37 -> Stingere stoc intermediar — 2026-07 — BUNURI — 711
A21: 2 | B21: =IF(Declarații_NEUTRALIZARE!B13="BUNURI",Declarații_NEUTRALIZARE!B16,0) -> 345 | C21: =IF(Declarații_NEUTRALIZARE!B13="BUNURI",Declarații_NEUTRALIZARE!B23,0) -> 4500 | D21: =IF(Declarații_NEUTRALIZARE!B13="BUNURI","Obținere produs finit (345=711) " & Declarații_NEUTRALIZARE!B37,"") -> Obținere produs finit (345=711) — 2026-07 — BUNURI — 711 | E21: =IF(Declarații_NEUTRALIZARE!B13="BUNURI",Declarații_NEUTRALIZARE!B14,0) -> 711 | F21: =IF(Declarații_NEUTRALIZARE!B13="BUNURI",Declarații_NEUTRALIZARE!B23,0) -> 4500 | G21: =IF(Declarații_NEUTRALIZARE!B13="BUNURI","Neutralizare (711 creditat #2) " & Declarații_NEUTRALIZARE!B37,"") -> Neutralizare (711 creditat #2) — 2026-07 — BUNURI — 711
A22: Check B3 | B22: =(C20+C21)-(F20+F21) -> 0 | C22: =IF(ABS(B22)<0.01,"OK","EROARE") -> OK
A24: Bloc 4 — Vânzare + descărcare (BUNURI/SERVICII; 0 pentru MF)
A25: Data: | B25: =Declarații_NEUTRALIZARE!B10 -> 2026-07-25
A26: Nr | B26: Cont Dr | C26: Sumă Dr | D26: Descriere Dr | E26: Cont Cr | F26: Sumă Cr | G26: Descriere Cr
A27: 1 | B27: =IF(OR(Declarații_NEUTRALIZARE!B13="BUNURI",Declarații_NEUTRALIZARE!B13="SERVICII"),Declarații_NEUTRALIZARE!B33,0) -> 411.RO | C27: =IF(OR(Declarații_NEUTRALIZARE!B13="BUNURI",Declarații_NEUTRALIZARE!B13="SERVICII"),Declarații_NEUTRALIZARE!B29,0) -> 8470 | D27: ="Creanță client " & Declarații_NEUTRALIZARE!B37 -> Creanță client — 2026-07 — BUNURI — 711 | E27: =IF(OR(Declarații_NEUTRALIZARE!B13="BUNURI",Declarații_NEUTRALIZARE!B13="SERVICII"),Declarații_NEUTRALIZARE!B17,0) -> 701 | F27: =IF(OR(Declarații_NEUTRALIZARE!B13="BUNURI",Declarații_NEUTRALIZARE!B13="SERVICII"),Declarații_NEUTRALIZARE!B26,0) -> 7000 | G27: ="Venit din vânzare " & Declarații_NEUTRALIZARE!B37 -> Venit din vânzare — 2026-07 — BUNURI — 711
A28: 2 | B28: 0 | C28: 0 | E28: =IF(OR(Declarații_NEUTRALIZARE!B13="BUNURI",Declarații_NEUTRALIZARE!B13="SERVICII"),Declarații_NEUTRALIZARE!B34,0) -> 4427 | F28: =IF(OR(Declarații_NEUTRALIZARE!B13="BUNURI",Declarații_NEUTRALIZARE!B13="SERVICII"),Declarații_NEUTRALIZARE!B28,0) -> 1470 | G28: ="TVA colectată " & Declarații_NEUTRALIZARE!B37 -> TVA colectată — 2026-07 — BUNURI — 711
A29: 3 | B29: =IF(Declarații_NEUTRALIZARE!B13="BUNURI",Declarații_NEUTRALIZARE!B14,IF(Declarații_NEUTRALIZARE!B13="SERVICII",Declarații_NEUTRALIZARE!B14,0)) -> 711 | C29: =IF(OR(Declarații_NEUTRALIZARE!B13="BUNURI",Declarații_NEUTRALIZARE!B13="SERVICII"),Declarații_NEUTRALIZARE!B23,0) -> 4500 | D29: =IF(Declarații_NEUTRALIZARE!B13="BUNURI","Descărcare PF prin 711 (NU 607) ",IF(Declarații_NEUTRALIZARE!B13="SERVICII","Stingere 712 la livrare ","")) & Declarații_NEUTRALIZARE!B37 -> Descărcare PF prin 711 (NU 607) — 2026-07 — BUNURI — 711 | E29: =IF(Declarații_NEUTRALIZARE!B13="BUNURI",Declarații_NEUTRALIZARE!B16,0) -> 345 | F29: =IF(Declarații_NEUTRALIZARE!B13="BUNURI",Declarații_NEUTRALIZARE!B23,0) -> 4500 | G29: =IF(Declarații_NEUTRALIZARE!B13="BUNURI","Stingere stoc PF " & Declarații_NEUTRALIZARE!B37,"") -> Stingere stoc PF — 2026-07 — BUNURI — 711
A30: Check B4 | B30: =(C27+C28+C29)-(F27+F28+F29) -> 0 | C30: =IF(ABS(B30)<0.01,"OK","EROARE") -> OK
A32: Check global | B32: =ABS(B9)+ABS(B15)+ABS(B22)+ABS(B30) -> 0 | C32: =IF(B32<0.01,"OK — toate blocurile se închid","EROARE — cel puțin un bloc dezechilibrat") -> OK — toate blocurile se închid
A34: Stare terminală
A35: Cont venit neut. sold 0 | Stoc intermediar 0 | Pentru BUNURI: 345 sold 0, descărcare prin 711 | Pentru MF: 213=cost, impact 121 din capitalizare = 0

Sheet NotaExport_NEUTRALIZARE
A1: MOD_NEUTRALIZARE — Notă pentru import
A2: Filtrează Include=DA. Rândurile cu sumă 0 (ex. manoperă 0, sau blocuri MF fără vânzare) apar ca NU.
A4: Nr | B4: Bloc | C4: Data | D4: Cont Dr | E4: Cont Cr | F4: Sumă | G4: Descriere | H4: Document | I4: Include
A5: 1 | B5: B1 Costuri | C5: =Declarații_NEUTRALIZARE!B8 -> 2026-07-05 | D5: =Jurnale_NEUTRALIZARE!B7 -> 601 | E5: =Jurnale_NEUTRALIZARE!E7 -> 301 | F5: =Jurnale_NEUTRALIZARE!C7 -> 4500 | G5: =Jurnale_NEUTRALIZARE!D7 -> Consum materiale — 2026-07 — BUNURI — 711 | H5: Producție / neutralizare | I5: =IF(AND(ISNUMBER(F5),F5>0),"DA","NU") -> DA
A6: 2 | B6: B1 Costuri | C6: =Declarații_NEUTRALIZARE!B8 -> 2026-07-05 | D6: =Jurnale_NEUTRALIZARE!B8 -> 641 | E6: =Jurnale_NEUTRALIZARE!E8 -> 421 | F6: =Jurnale_NEUTRALIZARE!C8 -> 0 | G6: =Jurnale_NEUTRALIZARE!D8 -> Manoperă pe proiect — 2026-07 — BUNURI — 711 | H6: Producție / neutralizare | I6: =IF(AND(ISNUMBER(F6),F6>0),"DA","NU") -> NU
A7: 3 | B7: B2 Neutralizare | C7: =Declarații_NEUTRALIZARE!B9 -> 2026-07-20 | D7: =Jurnale_NEUTRALIZARE!B14 -> 331 | E7: =Jurnale_NEUTRALIZARE!E14 -> 711 | F7: =Jurnale_NEUTRALIZARE!C14 -> 4500 | G7: =Jurnale_NEUTRALIZARE!D14 -> Stoc intermediar (PN/servicii/MF în curs) — 2026-07 — BUNURI — 711 | H7: Producție / neutralizare | I7: =IF(AND(ISNUMBER(F7),F7>0),"DA","NU") -> DA
A8: 4 | B8: B3 Finalizare | C8: =Declarații_NEUTRALIZARE!B9 -> 2026-07-20 | D8: =Jurnale_NEUTRALIZARE!B20 -> 711 | E8: =Jurnale_NEUTRALIZARE!E20 -> 331 | F8: =Jurnale_NEUTRALIZARE!C20 -> 4500 | G8: =Jurnale_NEUTRALIZARE!D20 -> Reluare PN (711 debitat #1) — 2026-07 — BUNURI — 711 | H8: Producție / neutralizare | I8: =IF(AND(ISNUMBER(F8),F8>0),"DA","NU") -> DA
A9: 5 | B9: B3 Finalizare | C9: =Declarații_NEUTRALIZARE!B9 -> 2026-07-20 | D9: =Jurnale_NEUTRALIZARE!B21 -> 345 | E9: =Jurnale_NEUTRALIZARE!E21 -> 711 | F9: =Jurnale_NEUTRALIZARE!C21 -> 4500 | G9: =Jurnale_NEUTRALIZARE!D21 -> Obținere produs finit (345=711) — 2026-07 — BUNURI — 711 | H9: Producție / neutralizare | I9: =IF(AND(ISNUMBER(F9),F9>0),"DA","NU") -> DA
A10: 6 | B10: B4 Vânzare | C10: =Declarații_NEUTRALIZARE!B10 -> 2026-07-25 | D10: =Jurnale_NEUTRALIZARE!B27 -> 411.RO | E10: =Jurnale_NEUTRALIZARE!E27 -> 701 | F10: =Jurnale_NEUTRALIZARE!F27 -> 7000 | G10: =Jurnale_NEUTRALIZARE!D27 -> Creanță client — 2026-07 — BUNURI — 711 | H10: Producție / neutralizare | I10: =IF(AND(ISNUMBER(F10),F10>0),"DA","NU") -> DA
A11: 7 | B11: B4 TVA | C11: =Declarații_NEUTRALIZARE!B10 -> 2026-07-25 | D11: =Jurnale_NEUTRALIZARE!B27 -> 411.RO | E11: =Jurnale_NEUTRALIZARE!E28 -> 4427 | F11: =Jurnale_NEUTRALIZARE!F28 -> 1470 | G11: =Jurnale_NEUTRALIZARE!G28 -> TVA colectată — 2026-07 — BUNURI — 711 | H11: Producție / neutralizare | I11: =IF(AND(ISNUMBER(F11),F11>0),"DA","NU") -> DA
A12: 8 | B12: B4 Descărcare | C12: =Declarații_NEUTRALIZARE!B10 -> 2026-07-25 | D12: =Jurnale_NEUTRALIZARE!B29 -> 711 | E12: =Jurnale_NEUTRALIZARE!E29 -> 345 | F12: =Jurnale_NEUTRALIZARE!C29 -> 4500 | G12: =Jurnale_NEUTRALIZARE!D29 -> Descărcare PF prin 711 (NU 607) — 2026-07 — BUNURI — 711 | H12: Producție / neutralizare | I12: =IF(AND(ISNUMBER(F12),F12>0),"DA","NU") -> DA
A14: Rânduri de importat | B14: =COUNTIF(I5:I12,"DA") -> 7
A15: Check global | B15: =Jurnale_NEUTRALIZARE!B32 -> 0 | C15: =IF(ABS(B15)<0.01,"OK","EROARE") -> OK

Sheet Declarații_SUBVENTIE
A1: MOD_SUBVENTIE — Declarații (input)
A2: Valorile implicite reproduc monografia din F-210 (utilaj 50.000, subvenție integrală, 60 de luni). Schimbă valoarea subvenției ca să vezi cazul parțial.
A4: 1. Antet
A5: Societate | B5: =Parametri!B5 -> SC EXEMPLU SRL
A6: Activul finanțat | B6: Utilaj tehnologic
A7: Contract / program de finanțare | B7: AFIR 2026-114
A8: Data încasării subvenției | B8: 2026-03-10
A9: Data punerii în funcțiune | B9: 2026-04-01
A10: Luna curentă (AAAA-LL) | B10: 2026-07
A11: Data notei lunare (ultima zi a lunii) | B11: 2026-07-31
A13: 2. Sumele
A14: Valoarea subvenției încasate | B14: 50000
A15: Valoarea de intrare a activului | B15: 50000
A16: Durata de amortizare (luni) | B16: 60
A17: Luni de amortizare deja înregistrate | B17: 3 | C17: Fără luna curentă; se folosește la calculul soldului rămas
A19: 3. Calcul automat (nu edita)
A20: Cota de finanțare din subvenție | B20: =IF(B15=0,0,MIN(1,B14/B15)) -> 1 | C20: 1 = subvenția acoperă integral activul; sub 1 = finanțare parțială
A21: Amortizare lunară | B21: =ROUND(B15/B16,2) -> 833.33
A22: Subvenție eliberată lunar la venit | B22: =ROUND(B21*B20,2) -> 833.33 | C22: Amortizarea × cota de finanțare — nu amortizarea întreagă
A23: Amortizare rămasă pe cheltuiala firmei | B23: =B21-B22 -> 0
A24: Sold 475 după luna curentă | B24: =ROUND(B14-B22*(B17+1),2) -> 46666.68
A25: Efect net pe rezultatul lunii | B25: =B22-B21 -> 0 | C25: Zero doar la finanțare integrală; altfel = partea proprie, cu minus
A27: 4. Conturi
A28: Cont subvenții pentru investiții | B28: 475
A29: Cont creanță din subvenție | B29: 445 | C29: Dacă subvenția e aprobată dar neîncasată încă
A30: Cont trezorerie | B30: 5121
A31: Cont imobilizare | B31: 2131
A32: Cont furnizor de imobilizări | B32: 404
A33: Cont amortizare | B33: 2813
A34: Cont cheltuială cu amortizarea | B34: 6811
A35: Cont venit din subvenții pentru investiții | B35: 7584
A37: 5. Controale
A38: Check cota de finanțare | B38: =B20 -> 1 | C38: =IF(B20>=1,"Finanțare INTEGRALĂ — efectul net pe rezultat e zero în fiecare lună","Finanțare PARȚIALĂ (" & TEXT(B20*100,"0.0") & "%) — restul de " & TEXT(B23,"0.00") & " lei/lună rămâne cheltuiala firmei") -> Finanțare INTEGRALĂ — efectul net pe rezultat e zero în fiecare lună
A39: Check efect net pe rezultat | B39: =B25 -> 0 | C39: =IF(ABS(B25)<0.01,"OK — amortizarea și venitul se anulează reciproc","Rezultatul lunii scade cu " & TEXT(-B25,"0.00") & " lei — corect la finanțare parțială") -> OK — amortizarea și venitul se anulează reciproc
A40: Check sold 475 nu devine negativ | B40: =B24 -> 46666.68 | C40: =IF(B24>=-0.01,"OK — mai sunt " & TEXT(B24,"0.00") & " lei de eliberat","EROARE — s-a eliberat mai mult decât s-a încasat; verifică numărul de luni") -> OK — mai sunt 46666.68 lei de eliberat
A41: Check durata eliberării = durata amortizării | B41: =IF(B22=0,0,ROUND(B14/B22,0)) -> 60 | C41: =IF(ABS(B41-B16)<1.5,"OK — subvenția se epuizează odată cu amortizarea","ATENȚIE — eliberarea nu se sincronizează cu amortizarea") -> OK — subvenția se epuizează odată cu amortizarea
A42: Reminder: NU e venit la încasare | B42: =B14 -> 50000 | C42: ="La încasare, subvenția intră în 475 (regularizare temporală), nu în clasa 7. Trecerea la venit se face lunar, pe măsura amortizării." -> La încasare, subvenția intră în 475 (regularizare temporală), nu în clasa 7. Trecerea la venit se face lunar, pe măsura amortizării.
A44: 6. Sufix generat
A45: Sufix | B45: =" - " & B6 & " - " & B10 -> - Utilaj tehnologic - 2026-07

Sheet Reguli_SUBVENTIE
A1: MOD_SUBVENTIE — Reguli (tabele fixe)
A3: Tabel A — Secvența
A4: Moment | B4: Înregistrare | C4: Cont | D4: Sumă | E4: Condiție | F4: Observație
A5: Aprobarea | B5: 445 = 475 | C5: 445 | D5: valoarea aprobată | E5: dacă e aprobată neîncasată | F5: Creanța față de finanțator; pasul se sare dacă încasarea e simultană
A6: Încasarea | B6: 5121 = 475 (sau 445) | C6: 475 | D6: valoarea încasată | E6: întotdeauna | F6: 475 e cont de REGULARIZARE TEMPORALĂ, nu de venit
A7: Achiziția activului | B7: 21x = 404 | C7: 21x | D7: valoarea de intrare | E7: întotdeauna | F7: Independentă de subvenție; activul se înregistrează la valoarea lui completă
A8: Amortizarea lunară | B8: 6811 = 28x | C8: 6811 | D8: valoare / durată | E8: lunar | F8: Pe valoarea INTEGRALĂ a activului, nu pe partea nesubvenționată
A9: Eliberarea subvenției | B9: 475 = 7584 | C9: 475 | D9: amortizare × cota | E9: lunar, CONCOMITENT | F9: Pas revelator: eliberarea urmează amortizarea, nu calendarul
A11: Tabel B — Cota de finanțare
A12: Situație | B12: Cota | C12: Eliberare lunară | D12: Efect net pe rezultat | F12: Observație
A13: Subvenția acoperă integral activul | B13: 1 | C13: cât amortizarea lunară | D13: zero | F13: Cazul din monografia F-210
A14: Subvenția acoperă parțial | B14: subvenție / activ | C14: amortizare × cota | D14: negativ, egal cu partea proprie | F14: Cazul frecvent în practică — cofinanțare
A15: Subvenția depășește valoarea activului | B15: plafonat la 1 | C15: cât amortizarea lunară | D15: zero | F15: Verifică încadrarea: excedentul nu e subvenție pentru investiții
A17: Tabel C — LIMITĂRI DECLARATE ale modulului
A18: Ce NU tratează | B18: De ce | C18: Ce faci | F18: Efect dacă îl ignori
A19: Subvenții pentru exploatare (741) | B19: Acelea sunt venit în perioada în care se produce cheltuiala acoperită, nu se eșalonează pe amortizare. | C19: Folosește 741, nu 475/7584. | F19: Venitul e amânat pe ani, când ar trebui recunoscut imediat
A20: Restituirea subvenției | B20: Neîndeplinirea condițiilor din contract obligă la restituire, cu tratament propriu. | C20: Stornează partea neeliberată din 475 și tratează restul pe cheltuială. | F20: 475 rămâne cu sold pentru o subvenție care nu mai există
A21: Cedarea activului înainte de finalul amortizării | B21: Soldul rămas din 475 se reia integral la venit la data ieșirii. | C21: Reia soldul 475 în 7584 odată cu descărcarea activului (vezi MOD_IESIRE_MF). | F21: 475 rămâne cu sold pentru un activ care nu mai e în patrimoniu
A22: Ajustarea planului de amortizare | B22: O modificare de durată schimbă și ritmul eliberării subvenției. | C22: Recalculează ambele; cota rămâne aceeași, amortizarea lunară se schimbă. | F22: Subvenția se epuizează înainte sau după activ
A24: Temei legal
A25: Ce se sprijină pe el | B25: Temei
A26: Subvenția pentru investiții se înregistrează ca venit amânat, nu ca venit al lunii | B26: OMFP 1802/2014, pct. 397–404 — conturile 475x
A27: Se eliberează la venit pe măsura amortizării activului finanțat | B27: OMFP 1802/2014, pct. 400 — simetrie cu cheltuiala pe care o compensează
A28: Cota de finanțare: dacă subvenția acoperă doar o parte, eliberarea e proporțională | B28: OMFP 1802/2014, pct. 401

Sheet Jurnale_SUBVENTIE
A1: MOD_SUBVENTIE — Jurnale (generate automat)
A2: Blocul 3 se repetă lunar, pe toată durata de amortizare. Cele două înregistrări din el se fac CONCOMITENT — asta e tot mecanismul.
A4: Bloc 1 — Încasarea subvenției
A5: Data jurnal: | B5: =Declarații_SUBVENTIE!B8 -> 2026-03-10
A7: Nr | B7: Cont Dr | C7: Sumă Dr | D7: Descriere Dr | E7: Cont Cr | F7: Sumă Cr | G7: Descriere Cr
A8: 1 | B8: =Declarații_SUBVENTIE!B30 -> 5121 | C8: =Declarații_SUBVENTIE!B14 -> 50000 | D8: ="Încasarea subvenției pentru investiții" & Declarații_SUBVENTIE!B45 -> Încasarea subvenției pentru investiții - Utilaj tehnologic - 2026-07 | E8: =Declarații_SUBVENTIE!B28 -> 475 | F8: =Declarații_SUBVENTIE!B14 -> 50000 | G8: ="Subvenție pentru investiții, de eliberat pe măsura amortizării" & Declarații_SUBVENTIE!B45 -> Subvenție pentru investiții, de eliberat pe măsura amortizării - Utilaj tehnologic - 2026-07
A10: Check Σ (structural) | B10: =C8-F8 -> 0 | C10: =IF(ABS(B10)<0.01,"OK — nota se închide","EROARE") -> OK — nota se închide
A11: Check: nu atinge clasa 7 | B11: =Declarații_SUBVENTIE!B28 -> 475 | C11: ="Corect — 475 e regularizare temporală. Venitul apare abia în blocul 3, lunar." -> Corect — 475 e regularizare temporală. Venitul apare abia în blocul 3, lunar.
A13: Bloc 2 — Achiziția activului
A14: Data jurnal: | B14: =Declarații_SUBVENTIE!B9 -> 2026-04-01
A16: Nr | B16: Cont Dr | C16: Sumă Dr | D16: Descriere Dr | E16: Cont Cr | F16: Sumă Cr | G16: Descriere Cr
A17: 1 | B17: =Declarații_SUBVENTIE!B31 -> 2131 | C17: =Declarații_SUBVENTIE!B15 -> 50000 | D17: ="Achiziția activului finanțat, la valoarea integrală" & Declarații_SUBVENTIE!B45 -> Achiziția activului finanțat, la valoarea integrală - Utilaj tehnologic - 2026-07 | E17: =Declarații_SUBVENTIE!B32 -> 404 | F17: =Declarații_SUBVENTIE!B15 -> 50000 | G17: ="Datorie față de furnizorul de imobilizări" & Declarații_SUBVENTIE!B45 -> Datorie față de furnizorul de imobilizări - Utilaj tehnologic - 2026-07
A19: Check Σ (structural) | B19: =C17-F17 -> 0 | C19: =IF(ABS(B19)<0.01,"OK — nota se închide","EROARE") -> OK — nota se închide
A21: Bloc 3 — Amortizare + eliberare (LUNAR, concomitent)
A22: Data jurnal: | B22: =Declarații_SUBVENTIE!B11 -> 2026-07-31
A24: Nr | B24: Cont Dr | C24: Sumă Dr | D24: Descriere Dr | E24: Cont Cr | F24: Sumă Cr | G24: Descriere Cr
A25: 1 | B25: =Declarații_SUBVENTIE!B34 -> 6811 | C25: =Declarații_SUBVENTIE!B21 -> 833.33 | D25: ="Amortizarea lunară a activului" & Declarații_SUBVENTIE!B45 -> Amortizarea lunară a activului - Utilaj tehnologic - 2026-07 | E25: =Declarații_SUBVENTIE!B33 -> 2813 | F25: =Declarații_SUBVENTIE!B21 -> 833.33 | G25: ="Amortizare cumulată" & Declarații_SUBVENTIE!B45 -> Amortizare cumulată - Utilaj tehnologic - 2026-07
A26: 2 | B26: =Declarații_SUBVENTIE!B28 -> 475 | C26: =Declarații_SUBVENTIE!B22 -> 833.33 | D26: ="Eliberarea subvenției pe măsura amortizării" & Declarații_SUBVENTIE!B45 -> Eliberarea subvenției pe măsura amortizării - Utilaj tehnologic - 2026-07 | E26: =Declarații_SUBVENTIE!B35 -> 7584 | F26: =Declarații_SUBVENTIE!B22 -> 833.33 | G26: ="Venit din subvenții pentru investiții" & Declarații_SUBVENTIE!B45 -> Venit din subvenții pentru investiții - Utilaj tehnologic - 2026-07
A28: Total Dr | B28: =SUM(C25:C26) -> 1666.66
A29: Total Cr | B29: =SUM(F25:F26) -> 1666.66
A30: Check Σ (structural) | B30: =SUM(C25:C26)-SUM(F25:F26) -> 0 | C30: =IF(ABS(B30)<0.01,"OK — notele se închid","EROARE") -> OK — notele se închid
A31: Check efect pe rezultat | B31: =Declarații_SUBVENTIE!B25 -> 0 | C31: =IF(ABS(Declarații_SUBVENTIE!B25)<0.01,"OK — amortizarea și venitul se anulează: rezultatul lunii nu e afectat de activul subvenționat","Rezultatul scade cu " & TEXT(-Declarații_SUBVENTIE!B25,"0.00") & " lei — partea nesubvenționată a amortizării") -> OK — amortizarea și venitul se anulează: rezultatul lunii nu e afectat de activul subvenționat
A33: Stare terminală, la finalul duratei: sold 475 = 0, activ complet amortizat, iar suma veniturilor din 7584 = valoarea subvenției încasate.

Sheet NotaExport_SUBVENTIE
A1: MOD_SUBVENTIE — Notă pentru import (1 rând = 1 înregistrare)
A2: Blocurile 1 și 2 se importă o singură dată; blocul 3 se repetă lunar.
A4: Nr | B4: Bloc | C4: Data | D4: Cont Dr | E4: Cont Cr | F4: Sumă | G4: Descriere | H4: Document | I4: Include
A5: 1 | B5: Bloc 1 — Încasare (o dată) | C5: =Declarații_SUBVENTIE!B8 -> 2026-03-10 | D5: =Jurnale_SUBVENTIE!B8 -> 5121 | E5: =Jurnale_SUBVENTIE!E8 -> 475 | F5: =MAX(N(Jurnale_SUBVENTIE!C8),N(Jurnale_SUBVENTIE!F8)) -> 50000 | G5: =Jurnale_SUBVENTIE!D8 -> Încasarea subvenției pentru investiții - Utilaj tehnologic - 2026-07 | H5: Contract + extras | I5: =IF(N(F5)>0.005,"DA","NU") -> DA
A6: 2 | B6: Bloc 2 — Achiziție (o dată) | C6: =Declarații_SUBVENTIE!B9 -> 2026-04-01 | D6: =Jurnale_SUBVENTIE!B17 -> 2131 | E6: =Jurnale_SUBVENTIE!E17 -> 404 | F6: =MAX(N(Jurnale_SUBVENTIE!C17),N(Jurnale_SUBVENTIE!F17)) -> 50000 | G6: =Jurnale_SUBVENTIE!D17 -> Achiziția activului finanțat, la valoarea integrală - Utilaj tehnologic - 2026-07 | H6: Factură + PV recepție | I6: =IF(N(F6)>0.005,"DA","NU") -> DA
A7: 3 | B7: Bloc 3 — Lunar | C7: =Declarații_SUBVENTIE!B11 -> 2026-07-31 | D7: =Jurnale_SUBVENTIE!B25 -> 6811 | E7: =Jurnale_SUBVENTIE!E25 -> 2813 | F7: =MAX(N(Jurnale_SUBVENTIE!C25),N(Jurnale_SUBVENTIE!F25)) -> 833.33 | G7: =Jurnale_SUBVENTIE!D25 -> Amortizarea lunară a activului - Utilaj tehnologic - 2026-07 | H7: Notă contabilă lunară | I7: =IF(N(F7)>0.005,"DA","NU") -> DA
A8: 4 | B8: Bloc 3 — Lunar | C8: =Declarații_SUBVENTIE!B11 -> 2026-07-31 | D8: =Jurnale_SUBVENTIE!B26 -> 475 | E8: =Jurnale_SUBVENTIE!E26 -> 7584 | F8: =MAX(N(Jurnale_SUBVENTIE!C26),N(Jurnale_SUBVENTIE!F26)) -> 833.33 | G8: =Jurnale_SUBVENTIE!D26 -> Eliberarea subvenției pe măsura amortizării - Utilaj tehnologic - 2026-07 | H8: Notă contabilă lunară | I8: =IF(N(F8)>0.005,"DA","NU") -> DA
A10: Rânduri de importat (Include=DA) | B10: =COUNTIF(I5:I8,"DA") -> 4

Sheet Declarații_IESIRE_MF
A1: MOD_IESIRE_MF — Declarații (input)
A2: Completează doar celulele galbene. Tipul ieșirii (VANZARE / CASARE) comandă blocurile.
A4: 1. Antet
A5: Societate | B5: =Parametri!B5 -> SC EXEMPLU SRL
A6: Denumire mijloc fix | B6: Clădire administrativă
A7: Data ieșirii | B7: 2026-07-31
A8: Tip ieșire (VANZARE / CASARE) | B8: VANZARE
A10: 2. Date din evidență
A11: Valoare de intrare (sold 21x) | B11: 100000
A12: Amortizare cumulată (sold 28x) | B12: 30000
A13: Preț de vânzare, fără TVA (0 la casare) | B13: 50000
A14: Cotă TVA | B14: =Parametri!B10 -> 0.21
A15: Valoare piese recuperate din casare | B15: 0 | C15: Evaluate de comisia tehnică, pe listă
A16: Prețul este documentat? (DA / NU) | B16: NU | C16: Raport de evaluare / referință de piață / deviz de service
A18: 3. Calcul automat (nu edita)
A19: Valoare rămasă neamortizată | B19: =B11-B12 -> 70000
A20: TVA colectată | B20: =B13*B14 -> 10500
A21: Total de încasat | B21: =B13+B20 -> 60500
A22: Cheltuială deductibilă (în limita venitului) | B22: =MIN(B19,B13) -> 50000
A23: Cheltuială NEdeductibilă | B23: =MAX(0,B19-B13) -> 20000
A24: Rezultat din cedare (venit − valoare rămasă) | B24: =B13-B19 -> -20000
A26: 4. Controale
A27: Check C-13: amortizarea nu poate depăși valoarea de intrare | B27: =B11-B12 -> 70000 | C27: =IF(B12<=B11+0.001,"OK — 28x ≤ 21x","EROARE — amortizare mai mare decât valoarea de intrare") -> OK — 28x ≤ 21x
A28: Test deductibilitate | B28: =B23 -> 20000 | C28: =IF(B23<0.001,"OK — valoarea rămasă e integral acoperită de venit",IF(B16="DA","ATENȚIE — diferență nedeductibilă, dar prețul e documentat: susține poziția în scris","RISC — vânzare sub valoarea rămasă, fără document. Comunică riscul clientului ÎN SCRIS")) -> RISC — vânzare sub valoarea rămasă, fără document. Comunică riscul clientului ÎN SCRIS
A29: Test preț minim | B29: =B13 -> 50000 | C29: =IF(B16="DA","OK — preț documentat","ATENȚIE — reperul minim e valoarea de piață (Autovit/OLX) sau valoarea de fier vechi; nu se vinde cu 100 EUR doar pentru că e amortizat") -> ATENȚIE — reperul minim e valoarea de piață (Autovit/OLX) sau valoarea de fier vechi; nu se vinde cu 100 EUR doar pentru că e amortizat
A30: Reminder modul de imobilizări | B30: =B8 -> VANZARE | C30: ="Schimbă STAREA mijlocului fix în modul: " & IF(B8="VANZARE","vândut","casat") & " — altfel softul continuă să calculeze amortizare" -> Schimbă STAREA mijlocului fix în modul: vândut — altfel softul continuă să calculeze amortizare
A32: 5. Conturi
A33: Cont imobilizare (21x) | B33: 212
A34: Cont amortizare (28x) | B34: 2812
A35: Cont cheltuială din cedare | B35: 6583
A36: Cont venit din cedare | B36: 7583
A37: Cont creanță | B37: 461
A38: Cont TVA colectată | B38: 4427
A39: Cont stoc piese recuperate | B39: 3024
A40: Cont venit din piese recuperate | B40: 7588
A42: 6. Sufix generat
A43: Sufix | B43: ="— " & B6 & " " & B7 -> — Clădire administrativă 2026-07-31
A45: Modul activ în CatalogModule? | B45: =IF(INDEX(CatalogModule!$A$1:$A$200,MATCH("MOD_IESIRE_MF",CatalogModule!$B$1:$B$200,0))="DA","ACTIV — jurnalele se generează","INACTIV — jurnalele rămân goale") -> INACTIV — jurnalele rămân goale

Sheet Reguli_IESIRE_MF
A1: MOD_IESIRE_MF — Reguli (tabele fixe)
A2: Se editează doar când se schimbă legea sau practica documentată a cabinetului.
A4: Tabel A — Secvența de ieșire
A5: Pas | B5: Cont Dr | C5: Cont Cr | D5: Sumă (sursă) | E5: Condiție | F5: Temei / observație
A6: 1 | B6: 28x | C6: 21x | D6: amortizarea cumulată | E6: Întotdeauna | F6: 28x e pur rectificativ — nu ține nimic real
A7: 2 | B7: 6583 | C7: 21x | D7: valoarea rămasă neamortizată | E7: Dacă valoarea rămasă > 0 | F7: La bun integral amortizat, pasul lipsește
A8: 3 | B8: 461/411 | C8: 7583 + 4427 | D8: preț + TVA | E8: Doar la VANZARE | F8: La casare nu există venit din cedare
A9: 4 | B9: 3024 | C9: 7588 | D9: valoarea pieselor recuperate | E9: Doar la CASARE cu recuperări | F9: Lista vine de la comisia tehnică; dacă se revând, transfer în 371 (F-308)
A11: Tabel B — Testul de deductibilitate
A12: Situație | B12: Tratament | F12: Observație
A13: Preț ≥ valoarea rămasă | B13: 6583 integral deductibil | F13: Rezultatul din cedare e câștig
A14: Preț < valoarea rămasă, preț DOCUMENTAT | B14: deductibil în limita venitului; diferența e discutabilă | F14: ❓ De cerut formatorului baza legală exactă. Art. 28 alin. (17) CF, citit strict, include pierderea în rezultatul fiscal
A15: Preț < valoarea rămasă, preț NEdocumentat | B15: diferența — nedeductibilă; risc de reîncadrare | F15: art. 11 CF (reîncadrare) + art. 25 alin. (1) CF (scopul activității economice)
A16: Bun integral amortizat, vândut sub piață | B16: risc de reîncadrare | F16: Reper minim: valoare de piață sau valoare de fier vechi, documentat
A18: Tabel C — Porți de calitate
A19: • ΣDr = ΣCr pe fiecare bloc
A20: • Sold 21x = 0 și sold 28x = 0 pentru bunul ieșit
A21: • Amortizarea descărcată = soldul 28x din evidență, nu o estimare (C-13)
A22: • Starea mijlocului fix schimbată în modul: vândut / casat
A23: • Ieșirea din nota contabilă corelată cu modulul de imobilizări (C-15)
A24: • Diferența nedeductibilă comunicată clientului în scris

Sheet Jurnale_IESIRE_MF
A1: MOD_IESIRE_MF — Jurnale (generate automat)
A2: Blocul de vânzare rămâne pe zero la casare, și invers pentru piesele recuperate.
A4: Bloc 1 — Descărcarea amortizării cumulate
A5: Data jurnal: | B5: =Declarații_IESIRE_MF!B7 -> 2026-07-31
A7: Nr | B7: Cont Dr | C7: Sumă Dr | D7: Descriere Dr | E7: Cont Cr | F7: Sumă Cr | G7: Descriere Cr
A8: 1 | B8: =Declarații_IESIRE_MF!B34 -> 2812 | C8: =Declarații_IESIRE_MF!B12 -> 30000 | D8: ="Descărcare amortizare cumulată " & Declarații_IESIRE_MF!B43 -> Descărcare amortizare cumulată — Clădire administrativă 2026-07-31 | E8: =Declarații_IESIRE_MF!B33 -> 212 | F8: =Declarații_IESIRE_MF!B12 -> 30000 | G8: ="Scoatere din evidență — partea amortizată " & Declarații_IESIRE_MF!B43 -> Scoatere din evidență — partea amortizată — Clădire administrativă 2026-07-31
A10: Bloc 2 — Valoarea rămasă pe cheltuială
A11: Nr | B11: Cont Dr | C11: Sumă Dr | D11: Descriere Dr | E11: Cont Cr | F11: Sumă Cr | G11: Descriere Cr
A12: 1 | B12: =Declarații_IESIRE_MF!B35 -> 6583 | C12: =Declarații_IESIRE_MF!B19 -> 70000 | D12: ="Valoare rămasă neamortizată " & Declarații_IESIRE_MF!B43 -> Valoare rămasă neamortizată — Clădire administrativă 2026-07-31 | E12: =Declarații_IESIRE_MF!B33 -> 212 | F12: =Declarații_IESIRE_MF!B19 -> 70000 | G12: ="Scoatere din evidență — partea neamortizată " & Declarații_IESIRE_MF!B43 -> Scoatere din evidență — partea neamortizată — Clădire administrativă 2026-07-31
A14: Bloc 3 — Vânzarea (doar la tip = VANZARE)
A15: Nr | B15: Cont Dr | C15: Sumă Dr | D15: Descriere Dr | E15: Cont Cr | F15: Sumă Cr | G15: Descriere Cr
A16: 1 | B16: =Declarații_IESIRE_MF!B37 -> 461 | C16: =IF(Declarații_IESIRE_MF!B8="VANZARE",Declarații_IESIRE_MF!B13,0) -> 50000 | D16: ="Creanță din vânzare mijloc fix " & Declarații_IESIRE_MF!B43 -> Creanță din vânzare mijloc fix — Clădire administrativă 2026-07-31 | E16: =Declarații_IESIRE_MF!B36 -> 7583 | F16: =IF(Declarații_IESIRE_MF!B8="VANZARE",Declarații_IESIRE_MF!B13,0) -> 50000 | G16: ="Venit din cedarea activelor " & Declarații_IESIRE_MF!B43 -> Venit din cedarea activelor — Clădire administrativă 2026-07-31
A17: 2 | B17: =Declarații_IESIRE_MF!B37 -> 461 | C17: =IF(Declarații_IESIRE_MF!B8="VANZARE",Declarații_IESIRE_MF!B20,0) -> 10500 | D17: ="Creanță — TVA " & Declarații_IESIRE_MF!B43 -> Creanță — TVA — Clădire administrativă 2026-07-31 | E17: =Declarații_IESIRE_MF!B38 -> 4427 | F17: =IF(Declarații_IESIRE_MF!B8="VANZARE",Declarații_IESIRE_MF!B20,0) -> 10500 | G17: ="TVA colectată " & Declarații_IESIRE_MF!B43 -> TVA colectată — Clădire administrativă 2026-07-31
A19: Bloc 4 — Piese recuperate din casare
A20: Nr | B20: Cont Dr | C20: Sumă Dr | D20: Descriere Dr | E20: Cont Cr | F20: Sumă Cr | G20: Descriere Cr
A21: 1 | B21: =Declarații_IESIRE_MF!B39 -> 3024 | C21: =Declarații_IESIRE_MF!B15 -> 0 | D21: ="Piese recuperate, evaluate de comisia tehnică " & Declarații_IESIRE_MF!B43 -> Piese recuperate, evaluate de comisia tehnică — Clădire administrativă 2026-07-31 | E21: =Declarații_IESIRE_MF!B40 -> 7588 | F21: =Declarații_IESIRE_MF!B15 -> 0 | G21: ="Venit din piese recuperate " & Declarații_IESIRE_MF!B43 -> Venit din piese recuperate — Clădire administrativă 2026-07-31
A23: Sumar și controale
A24: Total Dr | B24: =C8+C12+C16+C17+C21 -> 160500
A25: Total Cr | B25: =F8+F12+F16+F17+F21 -> 160500
A26: Check Σ (structural) | B26: =B24-B25 -> 0 | C26: =IF(ABS(B24-B25)<0.01,"OK — notele se închid","EROARE") -> OK — notele se închid
A27: Check stingere integrală 21x | B27: =F8+F12-Declarații_IESIRE_MF!B11 -> 0 | C27: =IF(ABS(F8+F12-Declarații_IESIRE_MF!B11)<0.01,"OK — 21x se stinge integral","EROARE — rămâne sold pe mijlocul ieșit") -> OK — 21x se stinge integral
A28: Check deductibilitate (informativ, nu blochează) | B28: =Declarații_IESIRE_MF!B23 -> 20000 | C28: =IF(Declarații_IESIRE_MF!B23<0.001,"OK — integral deductibil","ATENȚIE — " & TEXT(Declarații_IESIRE_MF!B23,"0.00") & " lei nedeductibili fără document") -> ATENȚIE — 20000.00 lei nedeductibili fără document
A29: Stare terminală așteptată: sold 21x = 0, sold 28x = 0 pentru bunul ieșit; starea în modulul de imobilizări schimbată în vândut / casat.

Sheet NotaExport_IESIRE_MF
A1: MOD_IESIRE_MF — Notă pentru import (1 rând = 1 înregistrare)
A2: Filtrează pe Include = DA. Rândurile pe zero corespund blocului inactiv pentru tipul de ieșire ales.
A4: Nr | B4: Bloc | C4: Data | D4: Cont Dr | E4: Cont Cr | F4: Sumă | G4: Descriere | H4: Document | I4: Include
A5: 1 | B5: Bloc 1 — Descărcare amortizare | C5: =Declarații_IESIRE_MF!B7 -> 2026-07-31 | D5: =Jurnale_IESIRE_MF!B8 -> 2812 | E5: =Jurnale_IESIRE_MF!E8 -> 212 | F5: =Jurnale_IESIRE_MF!C8 -> 30000 | G5: =Jurnale_IESIRE_MF!D8 -> Descărcare amortizare cumulată — Clădire administrativă 2026-07-31 | H5: Notă de scoatere din evidență | I5: =IF(F5>0.001,"DA","NU") -> DA
A6: 2 | B6: Bloc 2 — Valoare rămasă | C6: =Declarații_IESIRE_MF!B7 -> 2026-07-31 | D6: =Jurnale_IESIRE_MF!B12 -> 6583 | E6: =Jurnale_IESIRE_MF!E12 -> 212 | F6: =Jurnale_IESIRE_MF!C12 -> 70000 | G6: =Jurnale_IESIRE_MF!D12 -> Valoare rămasă neamortizată — Clădire administrativă 2026-07-31 | H6: Notă de scoatere din evidență | I6: =IF(F6>0.001,"DA","NU") -> DA
A7: 3 | B7: Bloc 3 — Vânzare | C7: =Declarații_IESIRE_MF!B7 -> 2026-07-31 | D7: =Jurnale_IESIRE_MF!B16 -> 461 | E7: =Jurnale_IESIRE_MF!E16 -> 7583 | F7: =Jurnale_IESIRE_MF!C16 -> 50000 | G7: =Jurnale_IESIRE_MF!D16 -> Creanță din vânzare mijloc fix — Clădire administrativă 2026-07-31 | H7: Factură de vânzare | I7: =IF(F7>0.001,"DA","NU") -> DA
A8: 4 | B8: Bloc 3 — TVA | C8: =Declarații_IESIRE_MF!B7 -> 2026-07-31 | D8: =Jurnale_IESIRE_MF!B17 -> 461 | E8: =Jurnale_IESIRE_MF!E17 -> 4427 | F8: =Jurnale_IESIRE_MF!C17 -> 10500 | G8: =Jurnale_IESIRE_MF!D17 -> Creanță — TVA — Clădire administrativă 2026-07-31 | H8: Factură de vânzare | I8: =IF(F8>0.001,"DA","NU") -> DA
A9: 5 | B9: Bloc 4 — Piese recuperate | C9: =Declarații_IESIRE_MF!B7 -> 2026-07-31 | D9: =Jurnale_IESIRE_MF!B21 -> 3024 | E9: =Jurnale_IESIRE_MF!E21 -> 7588 | F9: =Jurnale_IESIRE_MF!C21 -> 0 | G9: =Jurnale_IESIRE_MF!D21 -> Piese recuperate, evaluate de comisia tehnică — Clădire administrativă 2026-07-31 | H9: PV scoatere din funcțiune + listă comisie | I9: =IF(F9>0.001,"DA","NU") -> NU
A11: Rânduri de importat (Include=DA) | B11: =COUNTIF(I5:I9,"DA") -> 4
A12: Check global (trebuie 0) | B12: =Jurnale_IESIRE_MF!B24-Jurnale_IESIRE_MF!B25 -> 0 | C12: =IF(ABS(Jurnale_IESIRE_MF!B24-Jurnale_IESIRE_MF!B25)<0.01,"OK","EROARE") -> OK

Sheet Declarații_APROV_TRANZIT
A1: MOD_APROV_TRANZIT — Declarații (input)
A2: Completează doar celulele galbene. Modulul acoperă: factură înainte de recepție (32x) + stingere la recepție. Cazul simetric 408 (marfă înainte de factură) se notează, dar se activează separat dacă e nevoie.
A4: 1. Antet
A5: Societate | B5: =Parametri!B5 -> SC EXEMPLU SRL
A6: CUI | B6: =Parametri!B6 -> RO00000000
A7: Luna (AAAA-LL) | B7: 2026-07
A8: Data factură (jurnal B1) | B8: 2026-07-10
A9: Data recepție NIR (jurnal B2) | B9: 2026-07-18
A10: Furnizor (denumire scurtă) | B10: Furnizor DEMO
A11: Nr. factură / document | B11: F-1234/10.07.2026
A13: 2. Sume factură
A14: Valoare netă (fără TVA) | B14: 8000
A15: Cota TVA | B15: 0.21
A16: TVA (calculat) | B16: =B14*B15 -> 1680
A17: Total factură | B17: =B14+B16 -> 9680
A19: 3. Politică de conturi
A20: Cont stoc final (după recepție) | B20: 371
A21: Cont tranzit (32x) | B21: 327
A22: Cont furnizor | B22: 401.RO
A23: Cont TVA deductibilă | B23: 4426
A24: Platitor TVA? (DA/NU) | B24: DA
A26: 4. Poartă — tip eveniment
A27: Factură înainte de marfă? (DA = tranzit 32x) | B27: DA
A28: Marfă înainte de factură? (DA = 408 — nu e acoperit de acest modul) | B28: NU
A29: Notă poartă | B29: =IF(AND(B27="DA",B28="NU"),"Cale standard F-302: 32x → stoc","Verifică: dacă ambele DA sau ambele NU, situația nu e tranzit clasic") -> Cale standard F-302: 32x → stoc
A31: 5. Sufix descriere (generat)
A32: Sufix | B32: ="— " & B7 & " — " & B10 & " — " & B11 -> — 2026-07 — Furnizor DEMO — F-1234/10.07.2026
A34: 6. Control modul
A35: Modul activ în Catalog? | B35: =IF(INDEX(CatalogModule!$A$1:$A$200,MATCH("MOD_APROV_TRANZIT",CatalogModule!$B$1:$B$200,0))="DA","ACTIV","INACTIV") -> INACTIV

Sheet Reguli_APROV_TRANZIT
A1: MOD_APROV_TRANZIT — Reguli (tabele fixe)
A2: Regula este dată, nu formulă. Se editează doar la schimbare de lege sau politică.
A4: Tabel A — Secvența de înregistrare (calea standard F-302)
A5: Pas | B5: Moment | C5: Cont Dr | D5: Cont Cr | E5: Sumă | F5: Temei / observație
A6: 1 | B6: Factură (marfă pe drum) | C6: 327 (tranzit) | D6: 401.RO | E6: Netă | F6: Rol: Tranzit / reflectare — destinația cunoscută, așteaptă recepția
A7: 2 | B7: Factură — TVA | C7: 4426 | D7: 401.RO | E7: TVA | F7: Tranzit TVA; se închide lunar în 4423/4424
A8: 3 | B8: Recepție NIR | C8: 371 (sau 301) | D8: 327 | E8: Netă | F8: Stingere tranzit → stoc real (pas revelator)
A10: Tabel B — Conturi din planul pe rol
A11: Cont | B11: Denumire | C11: Rol | D11: Observație
A12: 327 | B12: Mărfuri în curs de aprovizionare | C12: Tranzit / reflectare | D12: Se stinge 371=327 la recepție. Fără pasul de stingere → stoc subevaluat + 327 deschis
A13: 321-328 | B13: Familia 32x | C13: Tranzit / reflectare | D13: 321 materii, 322 consumabile, 323 obiecte inventar, 327 mărfuri, 328 ambalaje
A14: 371 / 301 | B14: Stoc real | C14: Patrimonial — Stoc | D14: Destinația finală după recepție
A15: 401.RO | B15: Furnizori RO | C15: Patrimonial — Datorie | D15: Analitic pe rezidență pentru D394
A16: 4426 | B16: TVA deductibilă | C16: Tranzit / reflectare | D16: Fără sold după închiderea lunară
A17: 408 | B17: Furnizori — facturi nesosite | C17: Intermediar / clarificare | D17: Cazul SIMETRIC (marfă înainte de factură) — modul separat MOD_INTERMEDIAR
A19: Tabel C — Porți de calitate
A20: • ΣDr = ΣCr pe fiecare bloc (B1 factură, B2 recepție)
A21: • După B2: sold 327 = 0
A22: • Dacă poarta „Factură înainte de marfă” = NU → modulul nu ar trebui activat (calea e F-301 direct)
A23: • 408 nu se folosește în acest modul (e oglinda simetrică)

Sheet Jurnale_APROV_TRANZIT
A1: MOD_APROV_TRANZIT — Jurnale (generate automat)
A2: Nu se scrie nimic manual. Sumele și descrierile vin din Declarații_APROV_TRANZIT.
A4: Bloc 1 — Factură (marfă pe drum) — rol Tranzit
A5: Data jurnal: | B5: =Declarații_APROV_TRANZIT!B8 -> 2026-07-10
A7: Nr | B7: Cont Dr | C7: Sumă Dr | D7: Descriere Dr | E7: Cont Cr | F7: Sumă Cr | G7: Descriere Cr
A8: 1 | B8: =Declarații_APROV_TRANZIT!B21 -> 327 | C8: =Declarații_APROV_TRANZIT!B14 -> 8000 | D8: ="Marfă în curs de aprovizionare " & Declarații_APROV_TRANZIT!B32 -> Marfă în curs de aprovizionare — 2026-07 — Furnizor DEMO — F-1234/10.07.2026 | E8: =Declarații_APROV_TRANZIT!B22 -> 401.RO | F8: =Declarații_APROV_TRANZIT!B14 -> 8000 | G8: ="Datorie furnizor (net) " & Declarații_APROV_TRANZIT!B32 -> Datorie furnizor (net) — 2026-07 — Furnizor DEMO — F-1234/10.07.2026
A9: 2 | B9: =Declarații_APROV_TRANZIT!B23 -> 4426 | C9: =IF(Declarații_APROV_TRANZIT!B24="DA",Declarații_APROV_TRANZIT!B16,0) -> 1680 | D9: ="TVA deductibilă pe factură în tranzit " & Declarații_APROV_TRANZIT!B32 -> TVA deductibilă pe factură în tranzit — 2026-07 — Furnizor DEMO — F-1234/10.07.2026 | E9: =Declarații_APROV_TRANZIT!B22 -> 401.RO | F9: =IF(Declarații_APROV_TRANZIT!B24="DA",Declarații_APROV_TRANZIT!B16,0) -> 1680 | G9: ="Datorie furnizor (TVA) " & Declarații_APROV_TRANZIT!B32 -> Datorie furnizor (TVA) — 2026-07 — Furnizor DEMO — F-1234/10.07.2026
A11: Sumar Bloc 1
A12: Total Dr | B12: =C8+C9 -> 9680
A13: Total Cr | B13: =F8+F9 -> 9680
A14: Check B1 | B14: =B12-B13 -> 0 | C14: =IF(ABS(B14)<0.01,"OK","EROARE") -> OK
A16: Bloc 2 — Recepție NIR — stingere tranzit (pas revelator)
A17: Data jurnal: | B17: =Declarații_APROV_TRANZIT!B9 -> 2026-07-18
A19: Nr | B19: Cont Dr | C19: Sumă Dr | D19: Descriere Dr | E19: Cont Cr | F19: Sumă Cr | G19: Descriere Cr
A20: 1 | B20: =Declarații_APROV_TRANZIT!B20 -> 371 | C20: =Declarații_APROV_TRANZIT!B14 -> 8000 | D20: ="Recepție stoc real (stingere tranzit) " & Declarații_APROV_TRANZIT!B32 -> Recepție stoc real (stingere tranzit) — 2026-07 — Furnizor DEMO — F-1234/10.07.2026 | E20: =Declarații_APROV_TRANZIT!B21 -> 327 | F20: =Declarații_APROV_TRANZIT!B14 -> 8000 | G20: ="Stingere 32x " & Declarații_APROV_TRANZIT!B32 -> Stingere 32x — 2026-07 — Furnizor DEMO — F-1234/10.07.2026
A22: Sumar Bloc 2
A23: Total Dr | B23: =C20 -> 8000
A24: Total Cr | B24: =F20 -> 8000
A25: Check B2 | B25: =B23-B24 -> 0 | C25: =IF(ABS(B25)<0.01,"OK","EROARE") -> OK
A27: Stare terminală așteptată
A28: Sold 327 = 0 | Stoc 371 (sau 301) reflectă marfa | 401 = total factură | 4426 conține TVA (se închide la final de lună cu MOD_INCHIDERE_TVA)
A30: Check global (toate blocurile) | B30: =ABS(B14)+ABS(B25) -> 0 | C30: =IF(B30<0.01,"OK — toate blocurile se închid","EROARE — cel puțin un bloc dezechilibrat") -> OK — toate blocurile se închid

Sheet NotaExport_APROV_TRANZIT
A1: MOD_APROV_TRANZIT — Notă pentru import
A2: Filtrează Include=DA. Bloc 1 = data facturii; Bloc 2 = data recepției (pot fi luni diferite).
A4: Nr | B4: Bloc | C4: Data | D4: Cont Dr | E4: Cont Cr | F4: Sumă | G4: Descriere | H4: Document | I4: Include
A5: 1 | B5: Bloc 1 — Factură tranzit | C5: =Declarații_APROV_TRANZIT!B8 -> 2026-07-10 | D5: =Jurnale_APROV_TRANZIT!B8 -> 327 | E5: =Jurnale_APROV_TRANZIT!E8 -> 401.RO | F5: =Jurnale_APROV_TRANZIT!C8 -> 8000 | G5: =Jurnale_APROV_TRANZIT!D8 -> Marfă în curs de aprovizionare — 2026-07 — Furnizor DEMO — F-1234/10.07.2026 | H5: =Declarații_APROV_TRANZIT!B11 -> F-1234/10.07.2026 | I5: =IF(F5>0,"DA","NU") -> DA
A6: 2 | B6: Bloc 1 — Factură tranzit | C6: =Declarații_APROV_TRANZIT!B8 -> 2026-07-10 | D6: =Jurnale_APROV_TRANZIT!B9 -> 4426 | E6: =Jurnale_APROV_TRANZIT!E9 -> 401.RO | F6: =Jurnale_APROV_TRANZIT!C9 -> 1680 | G6: =Jurnale_APROV_TRANZIT!D9 -> TVA deductibilă pe factură în tranzit — 2026-07 — Furnizor DEMO — F-1234/10.07.2026 | H6: =Declarații_APROV_TRANZIT!B11 -> F-1234/10.07.2026 | I6: =IF(F6>0,"DA","NU") -> DA
A7: 3 | B7: Bloc 2 — Recepție | C7: =Declarații_APROV_TRANZIT!B9 -> 2026-07-18 | D7: =Jurnale_APROV_TRANZIT!B20 -> 371 | E7: =Jurnale_APROV_TRANZIT!E20 -> 327 | F7: =Jurnale_APROV_TRANZIT!C20 -> 8000 | G7: =Jurnale_APROV_TRANZIT!D20 -> Recepție stoc real (stingere tranzit) — 2026-07 — Furnizor DEMO — F-1234/10.07.2026 | H7: NIR | I7: =IF(F7>0,"DA","NU") -> DA
A9: Rânduri de importat | B9: =COUNTIF(I5:I7,"DA") -> 3
A10: Check global | B10: =Jurnale_APROV_TRANZIT!B30 -> 0 | C10: =IF(ABS(B10)<0.01,"OK","EROARE") -> OK

Sheet Declarații_TAXARE_INVERSA
A1: MOD_TAXARE_INVERSA — Declarații (input)
A2: Două cazuri, același mecanism. Pune DA pe cel care s-a întâmplat — pot fi și amândouă în aceeași lună, pe facturi diferite.
A4: 1. Antet
A5: Societate | B5: =Parametri!B5 -> SC EXEMPLU SRL
A6: CUI | B6: =Parametri!B6 -> RO00000000
A7: Luna (AAAA-LL) | B7: 2026-07
A8: Data jurnal | B8: 2026-07-31
A9: Cota TVA | B9: 0.21
A11: 2. Cazul A — Achiziție intracomunitară
A12: Se aplică? (DA/NU) | B12: DA
A13: Furnizor UE | B13: Furnizor UE DEMO
A14: Cod TVA valid în VIES? (DA/NU) | B14: DA | C14: Verificat la DATA operațiunii, nu azi — VIES arată starea curentă
A15: Valoare în valută | B15: 15000
A16: Curs la data facturii | B16: 4.97
A17: Valoare în lei (auto) | B17: =ROUND(B15*B16,2) -> 74550
A18: TVA autolichidată (din autofactură) | B18: 15655.5
A19: TVA recalculată (auto) | B19: =ROUND(B17*B9,2) -> 15655.5
A20: Marfa e în tranzit? (DA = 327, NU = 371) | B20: NU
A22: 3. Cazul B — Taxare inversă internă
A23: Se aplică? (DA/NU) | B23: DA
A24: Furnizor RO (plătitor de TVA) | B24: Furnizor RO DEMO
A25: Operațiunea din art. 331 CF | B25: Cereale
A26: Valoare fără TVA | B26: 10000
A27: TVA autolichidată (din autofactură) | B27: 2100
A28: TVA recalculată (auto) | B28: =ROUND(B26*B9,2) -> 2100
A30: 4. Conturi
A31: Cont stoc / cheltuială | B31: 371
A32: Cont tranzit (32x) | B32: 327
A33: Cont furnizor UE | B33: 401.UE
A34: Cont furnizor RO | B34: 401.RO
A35: Cont TVA deductibilă | B35: 4426
A36: Cont TVA colectată | B36: 4427
A38: 5. Sufix
A39: Sufix | B39: ="— taxare inversă " & B7 -> — taxare inversă 2026-07
A41: 6. Control
A42: Modul activ? | B42: =IF(INDEX(CatalogModule!$A$1:$A$200,MATCH("MOD_TAXARE_INVERSA",CatalogModule!$B$1:$B$200,0))="DA","ACTIV","INACTIV") -> INACTIV
A43: Verificare: TVA de pe autofactură = cotă × bază | B43: =IF(AND(OR(B12<>"DA",ABS(B18-B19)<0.01),OR(B23<>"DA",ABS(B27-B28)<0.01)),"OK — TVA corect calculată pe ambele cazuri","EROARE — TVA de pe autofactură nu corespunde cotei") -> OK — TVA corect calculată pe ambele cazuri
A44: Verificare: intracomunitar fără cod VIES valid | B44: =IF(AND(B12="DA",B14<>"DA"),"ATENȚIE — fără cod VIES valid, operațiunea NU e scutită la furnizor și nu poate fi declarată în D390","OK") -> OK
A45: Declarații de depus (auto) | B45: =IF(B12="DA","D300 + D390 + D394","") & IF(AND(B12="DA",B23="DA")," · ","") & IF(B23="DA","D300 + D394 (fără D390)","") -> D300 + D390 + D394 · D300 + D394 (fără D390)
A46: Derogare art. 331 CF | B46: Taxarea inversă INTERNĂ se aplică pe baza unei derogări UE care expiră la 31.12.2026. La 21.08.2026 nu era publicată o prelungire — reverifică înainte de prima factură din 2027.

Sheet Reguli_TAXARE_INVERSA
A1: MOD_TAXARE_INVERSA — Reguli (tabele fixe)
A2: Regula e dată, nu formulă. Mecanismul contabil e identic în ambele cazuri; diferă partenerul și declarația.
A4: Tabel A — Cele două cazuri
A5: Caz | B5: Partener | C5: Cont furnizor | D5: Ce declară | E5: Condiție
A6: Achiziție intracomunitară | B6: Persoană impozabilă din alt stat membru | C6: 401.UE | D6: D300 (casete taxare inversă) + D390 + D394 | E6: Cod de TVA valid în VIES la data operațiunii
A7: Taxare inversă internă | B7: Plătitor de TVA din România | C7: 401.RO | D7: D300 (casete taxare inversă) + D394, FĂRĂ D390 | E7: Bunul sau serviciul e pe lista art. 331 CF
A9: Tabel B — Operațiuni cu taxare inversă internă (art. 331 CF)
A10: Operațiune | B10: Prag
A11: Cereale și plante tehnice | B11: fără prag valoric
A12: Certificate de emisii de gaze cu efect de seră | B12: fără prag valoric
A13: Energie electrică și gaze naturale către comercianți persoane impozabile | B13: fără prag valoric
A14: Certificate verzi | B14: fără prag valoric
A15: Telefoane mobile | B15: doar dacă valoarea fără TVA de pe factură ≥ 22.500 lei
A16: Dispozitive cu circuite integrate | B16: doar dacă valoarea fără TVA de pe factură ≥ 22.500 lei
A17: Console de jocuri | B17: doar dacă valoarea fără TVA de pe factură ≥ 22.500 lei
A18: Tablete și laptopuri | B18: doar dacă valoarea fără TVA de pe factură ≥ 22.500 lei
A19: Derogarea Consiliului UE pe baza căreia se aplică art. 331 expiră la 31.12.2026. Verificat la 21.08.2026: nicio prelungire publicată. Nu se presupune prelungirea automată.
A21: Tabel C — Porți de calitate
A22: • 4426 și 4427 primesc EXACT aceeași sumă — netul pe operațiune e zero
A23: • D390 doar la intracomunitar; un partener intern trecut acolo se vede la ANAF prin necorelare cu VIES
A24: • Codul VIES se verifică la DATA operațiunii, nu la data când te uiți
A25: • Fără TVA plătită efectiv: autolichidarea nu produce flux de trezorerie
A26: • La închiderea lunară, sumele astea intră în 4426/4427 ca oricare altele și se anulează reciproc — vezi MOD_INCHIDERE_TVA
A28: Temei legal
A29: Ce se sprijină pe el | B29: Temei
A30: Taxare inversă la achiziții intracomunitare de bunuri | B30: art. 307 alin. (2) Cod fiscal — persoana obligată la plată e beneficiarul
A31: Taxare inversă internă, pe lista limitativă de operațiuni | B31: art. 331 Cod fiscal — pe baza derogării UE, valabilă până la 31.12.2026
A32: Declarația recapitulativă pentru operațiunile intracomunitare | B32: art. 325 Cod fiscal — D390

Sheet Jurnale_TAXARE_INVERSA
A1: MOD_TAXARE_INVERSA — Jurnale (generate automat)
A2: Fiecare caz iese cu zero dacă nu e activat. Pasul de autolichidare are aceeași sumă pe ambele părți — asta e chiar mecanismul, nu o coincidență.
A4: Bloc A — Achiziție intracomunitară
A5: Data: | B5: =Declarații_TAXARE_INVERSA!B8 -> 2026-07-31
A6: Nr | B6: Cont Dr | C6: Sumă Dr | D6: Descriere Dr | E6: Cont Cr | F6: Sumă Cr | G6: Descriere Cr
A7: 1 | B7: =IF(Declarații_TAXARE_INVERSA!B20="DA",Declarații_TAXARE_INVERSA!B32,Declarații_TAXARE_INVERSA!B31) -> 371 | C7: =IF(Declarații_TAXARE_INVERSA!B12="DA",Declarații_TAXARE_INVERSA!B17,0) -> 74550 | D7: ="Achiziție intracomunitară " & Declarații_TAXARE_INVERSA!B13 & " " & Declarații_TAXARE_INVERSA!B39 -> Achiziție intracomunitară Furnizor UE DEMO — taxare inversă 2026-07 | E7: =Declarații_TAXARE_INVERSA!B33 -> 401.UE | F7: =IF(Declarații_TAXARE_INVERSA!B12="DA",Declarații_TAXARE_INVERSA!B17,0) -> 74550 | G7: ="Datorie furnizor UE " & Declarații_TAXARE_INVERSA!B39 -> Datorie furnizor UE — taxare inversă 2026-07
A8: Check A1 (factura) | B8: =C7-F7 -> 0 | C8: =IF(ABS(B8)<0.01,"OK","EROARE") -> OK
A9: 2 | B9: =Declarații_TAXARE_INVERSA!B35 -> 4426 | C9: =IF(Declarații_TAXARE_INVERSA!B12="DA",Declarații_TAXARE_INVERSA!B18,0) -> 15655.5 | D9: ="TVA deductibilă prin autolichidare " & Declarații_TAXARE_INVERSA!B39 -> TVA deductibilă prin autolichidare — taxare inversă 2026-07 | E9: =Declarații_TAXARE_INVERSA!B36 -> 4427 | F9: =IF(Declarații_TAXARE_INVERSA!B12="DA",Declarații_TAXARE_INVERSA!B18,0) -> 15655.5 | G9: ="TVA colectată prin autolichidare " & Declarații_TAXARE_INVERSA!B39 -> TVA colectată prin autolichidare — taxare inversă 2026-07
A10: Check A2 (autolichidare = cotă × bază) | B10: =C9-IF(Declarații_TAXARE_INVERSA!B12="DA",Declarații_TAXARE_INVERSA!B19,0) -> 0 | C10: =IF(ABS(B10)<0.01,"OK — 4426 = 4427 = cotă × bază","EROARE — suma din notă nu e cotă × bază") -> OK — 4426 = 4427 = cotă × bază
A12: Bloc B — Taxare inversă internă
A13: Nr | B13: Cont Dr | C13: Sumă Dr | D13: Descriere Dr | E13: Cont Cr | F13: Sumă Cr | G13: Descriere Cr
A14: 1 | B14: =Declarații_TAXARE_INVERSA!B31 -> 371 | C14: =IF(Declarații_TAXARE_INVERSA!B23="DA",Declarații_TAXARE_INVERSA!B26,0) -> 10000 | D14: ="Achiziție cu taxare inversă (" & Declarații_TAXARE_INVERSA!B25 & ") " & Declarații_TAXARE_INVERSA!B39 -> Achiziție cu taxare inversă (Cereale) — taxare inversă 2026-07 | E14: =Declarații_TAXARE_INVERSA!B34 -> 401.RO | F14: =IF(Declarații_TAXARE_INVERSA!B23="DA",Declarații_TAXARE_INVERSA!B26,0) -> 10000 | G14: ="Datorie furnizor RO " & Declarații_TAXARE_INVERSA!B39 -> Datorie furnizor RO — taxare inversă 2026-07
A15: Check B1 (factura) | B15: =C14-F14 -> 0 | C15: =IF(ABS(B15)<0.01,"OK","EROARE") -> OK
A16: 2 | B16: =Declarații_TAXARE_INVERSA!B35 -> 4426 | C16: =IF(Declarații_TAXARE_INVERSA!B23="DA",Declarații_TAXARE_INVERSA!B27,0) -> 2100 | D16: ="TVA deductibilă prin autolichidare " & Declarații_TAXARE_INVERSA!B39 -> TVA deductibilă prin autolichidare — taxare inversă 2026-07 | E16: =Declarații_TAXARE_INVERSA!B36 -> 4427 | F16: =IF(Declarații_TAXARE_INVERSA!B23="DA",Declarații_TAXARE_INVERSA!B27,0) -> 2100 | G16: ="TVA colectată prin autolichidare " & Declarații_TAXARE_INVERSA!B39 -> TVA colectată prin autolichidare — taxare inversă 2026-07
A17: Check B2 (autolichidare = cotă × bază) | B17: =C16-IF(Declarații_TAXARE_INVERSA!B23="DA",Declarații_TAXARE_INVERSA!B28,0) -> 0 | C17: =IF(ABS(B17)<0.01,"OK — 4426 = 4427 = cotă × bază","EROARE — suma din notă nu e cotă × bază") -> OK — 4426 = 4427 = cotă × bază
A19: Check global | B19: =ABS(B8)+ABS(B10)+ABS(B15)+ABS(B17) -> 0 | C19: =IF(B19<0.01,"OK — toate blocurile se închid","EROARE — cel puțin un bloc dezechilibrat") -> OK — toate blocurile se închid
A21: Stare terminală
A22: Nicio TVA de plată suplimentară din operațiunile astea: 4426 și 4427 s-au mișcat cu aceeași sumă și se anulează la închiderea lunară. Ce rămâne e raportarea: D300 la ambele, D390 doar la intracomunitar.

Sheet NotaExport_TAXARE_INVERSA
A1: MOD_TAXARE_INVERSA — Notă pentru import
A2: Filtrează Include=DA. Cazurile neactivate ies cu sumă 0 și apar ca NU.
A4: Nr | B4: Bloc | C4: Data | D4: Cont Dr | E4: Cont Cr | F4: Sumă | G4: Descriere | H4: Document | I4: Include
A5: 1 | B5: A Intracomunitar — factura | C5: =Declarații_TAXARE_INVERSA!B8 -> 2026-07-31 | D5: =Jurnale_TAXARE_INVERSA!B7 -> 371 | E5: =Jurnale_TAXARE_INVERSA!E7 -> 401.UE | F5: =Jurnale_TAXARE_INVERSA!C7 -> 74550 | G5: =Jurnale_TAXARE_INVERSA!D7 -> Achiziție intracomunitară Furnizor UE DEMO — taxare inversă 2026-07 | H5: Factură furnizor UE | I5: =IF(AND(ISNUMBER(F5),F5>0),"DA","NU") -> DA
A6: 2 | B6: A Intracomunitar — autolichidare | C6: =Declarații_TAXARE_INVERSA!B8 -> 2026-07-31 | D6: =Jurnale_TAXARE_INVERSA!B9 -> 4426 | E6: =Jurnale_TAXARE_INVERSA!E9 -> 4427 | F6: =Jurnale_TAXARE_INVERSA!C9 -> 15655.5 | G6: =Jurnale_TAXARE_INVERSA!D9 -> TVA deductibilă prin autolichidare — taxare inversă 2026-07 | H6: Autofactură | I6: =IF(AND(ISNUMBER(F6),F6>0),"DA","NU") -> DA
A7: 3 | B7: B Intern — factura | C7: =Declarații_TAXARE_INVERSA!B8 -> 2026-07-31 | D7: =Jurnale_TAXARE_INVERSA!B14 -> 371 | E7: =Jurnale_TAXARE_INVERSA!E14 -> 401.RO | F7: =Jurnale_TAXARE_INVERSA!C14 -> 10000 | G7: =Jurnale_TAXARE_INVERSA!D14 -> Achiziție cu taxare inversă (Cereale) — taxare inversă 2026-07 | H7: Factură (mențiune taxare inversă) | I7: =IF(AND(ISNUMBER(F7),F7>0),"DA","NU") -> DA
A8: 4 | B8: B Intern — autolichidare | C8: =Declarații_TAXARE_INVERSA!B8 -> 2026-07-31 | D8: =Jurnale_TAXARE_INVERSA!B16 -> 4426 | E8: =Jurnale_TAXARE_INVERSA!E16 -> 4427 | F8: =Jurnale_TAXARE_INVERSA!C16 -> 2100 | G8: =Jurnale_TAXARE_INVERSA!D16 -> TVA deductibilă prin autolichidare — taxare inversă 2026-07 | H8: Autofactură | I8: =IF(AND(ISNUMBER(F8),F8>0),"DA","NU") -> DA
A10: Rânduri de importat | B10: =COUNTIF(I5:I8,"DA") -> 4
A11: Check global | B11: =Jurnale_TAXARE_INVERSA!B19 -> 0 | C11: =IF(ABS(B11)<0.01,"OK","EROARE") -> OK

Sheet Declarații_AMANUNT
A1: MOD_VANZ_AMANUNT — Declarații (input)
A2: Gestiune amănunt la PVA. Corelații: 371×c/(100+c)=4428 și 707−607=rulaj D 378. Completează galben.
A4: 1. Antet
A5: Societate | B5: =Parametri!B5 -> SC EXEMPLU SRL
A6: Gestiune (analitic) | B6: AM.21
A7: Luna | B7: 2026-07
A8: Data aprovizionare | B8: 2026-07-05
A9: Data vânzare (Z-report) | B9: 2026-07-31
A11: 2. Aprovizionare
A12: Cost (fără TVA) | B12: 10000
A13: Adaos % | B13: 0.3
A14: Cotă TVA | B14: 0.21
A15: Adaos (lei) | B15: =B12*B13 -> 3000
A16: Bază PVA (cost+adaos) | B16: =B12+B15 -> 13000
A17: TVA în PVA | B17: =B16*B14 -> 2730
A18: PVA total (371) | B18: =B16+B17 -> 15730
A19: TVA deductibilă (pe cost) | B19: =B12*B14 -> 2100
A21: 3. Conturi
A22: Cont stoc (371.gest.cotă) | B22: 371.AM.21
A23: Cont adaos (378) | B23: 378.AM.21
A24: Cont TVA neexigibilă (4428) | B24: 4428.AM
A25: Cont furnizor | B25: 401.RO
A26: Cont TVA deductibilă | B26: 4426
A27: Cont cheltuială (607) | B27: 607
A28: Cont venit (707) | B28: 707
A29: Cont TVA colectată | B29: 4427
A30: Cont casă / bancă | B30: 531.1
A31: Cont TVA de plată | B31: 4423
A33: 4. Corelații (auto)
A34: Corelație 1: 371×c/(100+c) =? | B34: =B18*B14/(1+B14) -> 2730
A35: Trebuie = 4428 | B35: =IF(ABS(B34-B17)<0.01,"OK — corelație 1 ține","EROARE") -> OK — corelație 1 ține
A36: Corelație 2: 707−607 =? | B36: =B16-B12 -> 3000
A37: Trebuie = adaos (rulaj D 378) | B37: =IF(ABS(B36-B15)<0.01,"OK — corelație 2 ține","EROARE") -> OK — corelație 2 ține
A39: 5. Sufix
A40: Sufix | B40: ="— amănunt " & B6 & " — " & B7 -> — amănunt AM.21 — 2026-07

Sheet Reguli_AMANUNT
A1: MOD_VANZ_AMANUNT — Reguli (tabele fixe)
A2: Regula e dată, nu formulă. Se editează doar când se schimbă politica de gestiune sau cotele.
A4: Tabel A — Secvența operațională
A5: Pas | B5: Cont Dr | C5: Cont Cr | D5: Sumă (sursă) | E5: Condiție | F5: Temei / observație
A6: 1 | B6: 371.gest.cotă | C6: 401 + 378 + 4428 | D6: PVA = cost+adaos+TVA_PVA | E6: La aprovizionare amănunt | F6: Stoc la preț de vânzare cu amănuntul
A7: 2 | B7: 4426 | C7: 401 | D7: cost × cotă | E7: Din factură furnizor | F7: TVA deductibilă ≠ TVA din PVA
A8: 3 | B8: 607 + 378 + 4428 | C8: 371.gest.cotă | D8: proporțional pe PVA vândut | E8: La vânzare / Z-report | F8: Descărcare proporțională (nu doar cost)
A9: 4 | B9: 531/512 | C9: 707 + 4427 | D9: bază + TVA = PVA vândut | E9: La vânzare | F9: Venit pe bază (cost+adaos), TVA colectată
A10: 5 | B10: 4427 | C10: 4426 + 4423 | D10: rulaje lunare | E10: La închidere TVA | F10: Vezi MOD_INCHIDERE_TVA
A11: 6 | B11: 707 + 4427 | C11: 411/531 | D11: proporțional retur | E11: La retur client | F11: Storno venit+TVA; apoi reîncarcă 371+378+4428 (F-318)
A13: Tabel B — Corelații de control (obligatorii pe cifre)
A14: ID | B14: Formulă | C14: Când | D14: Ce o rupe legitim | E14: Ce o rupe suspect | F14: Flux
A15: C-01 | B15: sold 371 × c/(100+c) = sold 4428 | C15: Pe gestiune+cotă, oricând | D15: Vânzare parțială, retur, transfer gestiuni | E15: 4428 omis; descărcare fără 378/4428 | F15: F-316, F-318, F-317
A16: C-02 | B16: 707 − 607 = rulaj D 378 | C16: Pe perioadă | D16: Retur, 709, discount furnizor pe stoc vândut | E16: 607 greșit; 378 nestins | F16: F-316, F-318, F-317
A18: Tabel C — Porți
A19: • ΣDr=ΣCr pe fiecare bloc (verificare cu ABS la global — erorile nu se anulează)
A20: • După vânzare integrală: sold 371=378=4428=0 pe gestiune
A21: • Vânzare parțială: C-01 pe soldul RĂMAS, nu pe rulajul de la intrare
A22: • Retur: reîncarcă proporțional 371+378+4428 — omisiunea 378/4428 = ruptură suspectă C-01

Sheet Jurnale_AMANUNT
A1: MOD_VANZ_AMANUNT — Jurnale
A3: Bloc 1 — Aprovizionare la PVA
A4: Data: | B4: =Declarații_AMANUNT!B8 -> 2026-07-05
A5: Nr | B5: Cont Dr | C5: Sumă Dr | D5: Descriere Dr | E5: Cont Cr | F5: Sumă Cr | G5: Descriere Cr
A6: 1 | B6: =Declarații_AMANUNT!B22 -> 371.AM.21 | C6: =Declarații_AMANUNT!B18 -> 15730 | D6: ="Intrare stoc la PVA " & Declarații_AMANUNT!B40 -> Intrare stoc la PVA — amănunt AM.21 — 2026-07 | E6: =Declarații_AMANUNT!B25 -> 401.RO | F6: =Declarații_AMANUNT!B12 -> 10000 | G6: ="Datorie furnizor (cost) " & Declarații_AMANUNT!B40 -> Datorie furnizor (cost) — amănunt AM.21 — 2026-07
A7: 2 | B7: 0 | C7: 0 | E7: =Declarații_AMANUNT!B23 -> 378.AM.21 | F7: =Declarații_AMANUNT!B15 -> 3000 | G7: ="Adaos comercial " & Declarații_AMANUNT!B40 -> Adaos comercial — amănunt AM.21 — 2026-07
A8: 3 | B8: 0 | C8: 0 | E8: =Declarații_AMANUNT!B24 -> 4428.AM | F8: =Declarații_AMANUNT!B17 -> 2730 | G8: ="TVA neexigibilă în PVA " & Declarații_AMANUNT!B40 -> TVA neexigibilă în PVA — amănunt AM.21 — 2026-07
A9: Check B1 (371 = cost+adaos+TVA PVA) | B9: =C6-(F6+F7+F8) -> 0 | C9: =IF(ABS(B9)<0.01,"OK","EROARE") -> OK
A11: Bloc 2 — TVA deductibilă din factură
A12: Nr | B12: Cont Dr | C12: Sumă Dr | D12: Descriere Dr | E12: Cont Cr | F12: Sumă Cr | G12: Descriere Cr
A13: 1 | B13: =Declarații_AMANUNT!B26 -> 4426 | C13: =Declarații_AMANUNT!B19 -> 2100 | D13: ="TVA deductibilă pe cost " & Declarații_AMANUNT!B40 -> TVA deductibilă pe cost — amănunt AM.21 — 2026-07 | E13: =Declarații_AMANUNT!B25 -> 401.RO | F13: =Declarații_AMANUNT!B19 -> 2100 | G13: ="Datorie furnizor (TVA) " & Declarații_AMANUNT!B40 -> Datorie furnizor (TVA) — amănunt AM.21 — 2026-07
A14: Check B2 | B14: =C13-F13 -> 0 | C14: =IF(ABS(B14)<0.01,"OK","EROARE") -> OK
A16: Bloc 3 — Descărcare gestiune la PVA
A17: Data: | B17: =Declarații_AMANUNT!B9 -> 2026-07-31
A18: Nr | B18: Cont Dr | C18: Sumă Dr | D18: Descriere Dr | E18: Cont Cr | F18: Sumă Cr | G18: Descriere Cr
A19: 1 | B19: =Declarații_AMANUNT!B27 -> 607 | C19: =Declarații_AMANUNT!B12 -> 10000 | D19: ="Descărcare la cost " & Declarații_AMANUNT!B40 -> Descărcare la cost — amănunt AM.21 — 2026-07 | E19: =Declarații_AMANUNT!B22 -> 371.AM.21 | F19: =Declarații_AMANUNT!B18 -> 15730 | G19: ="Stingere stoc PVA " & Declarații_AMANUNT!B40 -> Stingere stoc PVA — amănunt AM.21 — 2026-07
A20: 2 | B20: =Declarații_AMANUNT!B23 -> 378.AM.21 | C20: =Declarații_AMANUNT!B15 -> 3000 | D20: ="Stingere adaos " & Declarații_AMANUNT!B40 -> Stingere adaos — amănunt AM.21 — 2026-07 | E20: 0 | F20: 0
A21: 3 | B21: =Declarații_AMANUNT!B24 -> 4428.AM | C21: =Declarații_AMANUNT!B17 -> 2730 | D21: ="Stingere TVA neexigibilă " & Declarații_AMANUNT!B40 -> Stingere TVA neexigibilă — amănunt AM.21 — 2026-07 | E21: 0 | F21: 0
A22: Check B3 | B22: =(C19+C20+C21)-F19 -> 0 | C22: =IF(ABS(B22)<0.01,"OK","EROARE") -> OK
A24: Bloc 4 — Venit + TVA colectată
A25: Nr | B25: Cont Dr | C25: Sumă Dr | D25: Descriere Dr | E25: Cont Cr | F25: Sumă Cr | G25: Descriere Cr
A26: 1 | B26: =Declarații_AMANUNT!B30 -> 531.1 | C26: =Declarații_AMANUNT!B18 -> 15730 | D26: ="Încasare amănunt " & Declarații_AMANUNT!B40 -> Încasare amănunt — amănunt AM.21 — 2026-07 | E26: =Declarații_AMANUNT!B28 -> 707 | F26: =Declarații_AMANUNT!B16 -> 13000 | G26: ="Venit amănunt (bază) " & Declarații_AMANUNT!B40 -> Venit amănunt (bază) — amănunt AM.21 — 2026-07
A27: 2 | B27: 0 | C27: 0 | E27: =Declarații_AMANUNT!B29 -> 4427 | F27: =Declarații_AMANUNT!B17 -> 2730 | G27: ="TVA colectată " & Declarații_AMANUNT!B40 -> TVA colectată — amănunt AM.21 — 2026-07
A28: Check B4 | B28: =C26-(F26+F27) -> 0 | C28: =IF(ABS(B28)<0.01,"OK","EROARE") -> OK
A30: Bloc 5 — Închidere TVA
A31: Nr | B31: Cont Dr | C31: Sumă Dr | D31: Descriere Dr | E31: Cont Cr | F31: Sumă Cr | G31: Descriere Cr
A32: 1 | B32: =Declarații_AMANUNT!B29 -> 4427 | C32: =Declarații_AMANUNT!B17 -> 2730 | D32: ="Închidere TVA colectată " & Declarații_AMANUNT!B40 -> Închidere TVA colectată — amănunt AM.21 — 2026-07 | E32: =Declarații_AMANUNT!B26 -> 4426 | F32: =Declarații_AMANUNT!B19 -> 2100 | G32: ="Închidere TVA deductibilă " & Declarații_AMANUNT!B40 -> Închidere TVA deductibilă — amănunt AM.21 — 2026-07
A33: 2 | B33: 0 | C33: 0 | E33: =Declarații_AMANUNT!B31 -> 4423 | F33: =Declarații_AMANUNT!B17-Declarații_AMANUNT!B19 -> 630 | G33: ="TVA de plată " & Declarații_AMANUNT!B40 -> TVA de plată — amănunt AM.21 — 2026-07
A34: Check B5 | B34: =C32-(F32+F33) -> 0 | C34: =IF(ABS(B34)<0.01,"OK","EROARE") -> OK
A36: Check global | B36: =ABS(B9)+ABS(B14)+ABS(B22)+ABS(B28)+ABS(B34) -> 0 | C36: =IF(B36<0.01,"OK — toate blocurile se închid","EROARE — cel puțin un bloc dezechilibrat") -> OK — toate blocurile se închid
A38: Corelații (din Declarații)
A39: =Declarații_AMANUNT!B35 -> OK — corelație 1 ține
A40: =Declarații_AMANUNT!B37 -> OK — corelație 2 ține

Sheet NotaExport_AMANUNT
A1: MOD_VANZ_AMANUNT — Notă pentru import
A4: Nr | B4: Bloc | C4: Data | D4: Cont Dr | E4: Cont Cr | F4: Sumă | G4: Descriere | H4: Document | I4: Include
A5: 1 | B5: B1 | C5: =Declarații_AMANUNT!B8 -> 2026-07-05 | D5: =Jurnale_AMANUNT!B6 -> 371.AM.21 | E5: =Jurnale_AMANUNT!E6 -> 401.RO | F5: =Jurnale_AMANUNT!F6 -> 10000 | G5: Cost | H5: Amănunt | I5: =IF(AND(ISNUMBER(F5),F5>0),"DA","NU") -> DA
A6: 2 | B6: B1 | C6: =Declarații_AMANUNT!B8 -> 2026-07-05 | D6: =Jurnale_AMANUNT!B6 -> 371.AM.21 | E6: =Jurnale_AMANUNT!E7 -> 378.AM.21 | F6: =Jurnale_AMANUNT!F7 -> 3000 | G6: Adaos | H6: Amănunt | I6: =IF(AND(ISNUMBER(F6),F6>0),"DA","NU") -> DA
A7: 3 | B7: B1 | C7: =Declarații_AMANUNT!B8 -> 2026-07-05 | D7: =Jurnale_AMANUNT!B6 -> 371.AM.21 | E7: =Jurnale_AMANUNT!E8 -> 4428.AM | F7: =Jurnale_AMANUNT!F8 -> 2730 | G7: TVA PVA | H7: Amănunt | I7: =IF(AND(ISNUMBER(F7),F7>0),"DA","NU") -> DA
A8: 4 | B8: B2 | C8: =Declarații_AMANUNT!B8 -> 2026-07-05 | D8: =Jurnale_AMANUNT!B13 -> 4426 | E8: =Jurnale_AMANUNT!E13 -> 401.RO | F8: =Jurnale_AMANUNT!C13 -> 2100 | G8: TVA ded | H8: Amănunt | I8: =IF(AND(ISNUMBER(F8),F8>0),"DA","NU") -> DA
A9: 5 | B9: B3 | C9: =Declarații_AMANUNT!B9 -> 2026-07-31 | D9: =Jurnale_AMANUNT!B19 -> 607 | E9: =Jurnale_AMANUNT!E19 -> 371.AM.21 | F9: =Jurnale_AMANUNT!C19 -> 10000 | G9: Desc cost | H9: Amănunt | I9: =IF(AND(ISNUMBER(F9),F9>0),"DA","NU") -> DA
A10: 6 | B10: B3 | C10: =Declarații_AMANUNT!B9 -> 2026-07-31 | D10: =Jurnale_AMANUNT!B20 -> 378.AM.21 | E10: =Jurnale_AMANUNT!E19 -> 371.AM.21 | F10: =Jurnale_AMANUNT!C20 -> 3000 | G10: Desc adaos | H10: Amănunt | I10: =IF(AND(ISNUMBER(F10),F10>0),"DA","NU") -> DA
A11: 7 | B11: B3 | C11: =Declarații_AMANUNT!B9 -> 2026-07-31 | D11: =Jurnale_AMANUNT!B21 -> 4428.AM | E11: =Jurnale_AMANUNT!E19 -> 371.AM.21 | F11: =Jurnale_AMANUNT!C21 -> 2730 | G11: Desc 4428 | H11: Amănunt | I11: =IF(AND(ISNUMBER(F11),F11>0),"DA","NU") -> DA
A12: 8 | B12: B4 | C12: =Declarații_AMANUNT!B9 -> 2026-07-31 | D12: =Jurnale_AMANUNT!B26 -> 531.1 | E12: =Jurnale_AMANUNT!E26 -> 707 | F12: =Jurnale_AMANUNT!F26 -> 13000 | G12: Venit | H12: Amănunt | I12: =IF(AND(ISNUMBER(F12),F12>0),"DA","NU") -> DA
A13: 9 | B13: B4 | C13: =Declarații_AMANUNT!B9 -> 2026-07-31 | D13: =Jurnale_AMANUNT!B26 -> 531.1 | E13: =Jurnale_AMANUNT!E27 -> 4427 | F13: =Jurnale_AMANUNT!F27 -> 2730 | G13: TVA col | H13: Amănunt | I13: =IF(AND(ISNUMBER(F13),F13>0),"DA","NU") -> DA
A14: 10 | B14: B5 | C14: =Declarații_AMANUNT!B9 -> 2026-07-31 | D14: =Jurnale_AMANUNT!B32 -> 4427 | E14: =Jurnale_AMANUNT!E32 -> 4426 | F14: =Jurnale_AMANUNT!F32 -> 2100 | G14: Înch 4426 | H14: Amănunt | I14: =IF(AND(ISNUMBER(F14),F14>0),"DA","NU") -> DA
A15: 11 | B15: B5 | C15: =Declarații_AMANUNT!B9 -> 2026-07-31 | D15: =Jurnale_AMANUNT!B32 -> 4427 | E15: =Jurnale_AMANUNT!E33 -> 4423 | F15: =Jurnale_AMANUNT!F33 -> 630 | G15: TVA plată | H15: Amănunt | I15: =IF(AND(ISNUMBER(F15),F15>0),"DA","NU") -> DA
A17: Check global | B17: =Jurnale_AMANUNT!B36 -> 0 | C17: =IF(ABS(B17)<0.01,"OK","EROARE") -> OK

Sheet Declarații_IMPORT
A1: MOD_IMPORT — Declarații (input)
A2: Două căi alternative. De regulă se aplică una singură pe un import — pune DA pe cea folosită.
A4: 1. Antet
A5: Societate | B5: =Parametri!B5 -> SC EXEMPLU SRL
A6: CUI | B6: =Parametri!B6 -> RO00000000
A7: Luna (AAAA-LL) | B7: 2026-07
A8: Data jurnal (DVI) | B8: 2026-07-31
A9: Cota TVA | B9: 0.21
A11: 2. Calea A — Import prin comisionar
A12: Se aplică? (DA/NU) | B12: DA
A13: Furnizor extern | B13: Furnizor EXT DEMO
A14: Comisionar vamal | B14: Comisionar DEMO
A15: Valoarea mărfii (lei) | B15: 100000 | C15: 15.000–20.000 EUR × cursul de la data DVI
A16: Taxe vamale | B16: 3000
A17: Transport INTERN (după vămuire) | B17: 2000 | C17: Intră în COST, dar NU în baza TVA vamală
A18: Baza TVA vamală (auto) = marfă + taxe | B18: =B15+B16 -> 103000 | C18: Fără transportul intern — acela are TVA-ul lui pe factura transportatorului
A19: TVA vamală (auto) | B19: =ROUND(B18*B9,2) -> 21630
A20: Costul final al stocului (auto) | B20: =B15+B16+B17 -> 105000
A22: 3. Calea B — Import cu plată directă în vamă
A23: Se aplică? (DA/NU) | B23: DA
A24: Furnizor extern | B24: Furnizor EXT DEMO 2
A25: Valoarea mărfii (lei) | B25: 50000
A26: Taxe vamale (plătite direct) | B26: 2000
A27: Baza TVA vamală (auto) = marfă + taxe | B27: =B25+B26 -> 52000
A28: TVA vamală (auto) | B28: =ROUND(B27*B9,2) -> 10920
A29: Costul final al stocului (auto) | B29: =B25+B26 -> 52000
A31: 4. Conturi
A32: Cont stoc | B32: 371
A33: Furnizor extern | B33: 401.EXT
A34: Intermediar TVA vamală | B34: 446.VAMA
A35: Furnizor comisionar | B35: 401
A36: Furnizor intern / transport | B36: 401.RO
A37: TVA deductibilă | B37: 4426
A38: Bancă | B38: 512.1
A40: 5. Sufix
A41: Sufix | B41: ="— import " & B7 -> — import 2026-07
A43: 6. Control
A44: Modul activ? | B44: =IF(INDEX(CatalogModule!$A$1:$A$200,MATCH("MOD_IMPORT",CatalogModule!$B$1:$B$200,0))="DA","ACTIV","INACTIV") -> INACTIV
A45: Verificare: baza TVA exclude transportul intern | B45: =IF(OR(B12<>"DA",ABS(B18-(B20-B17))<0.01),"OK — baza = marfă + taxe, fără transportul intern","EROARE — transportul intern a intrat în baza TVA") -> OK — baza = marfă + taxe, fără transportul intern
A46: Cât ar costa greșeala (informativ) | B46: =IF(B12="DA","TVA calculată pe cost în loc de bază: +" & TEXT(ROUND(B17*B9,2),"0.00") & " lei dedusă de două ori","—") -> TVA calculată pe cost în loc de bază: +420.00 lei dedusă de două ori | C46: Transportul intern are deja TVA pe factura transportatorului
A47: Cale aleasă | B47: =IF(AND(B12="DA",B23="DA"),"ATENȚIE — de regulă un import merge pe o singură cale",IF(B12="DA","Prin comisionar — 446.VAMA se stinge",IF(B23="DA","Plată directă — fără intermediar","—"))) -> ATENȚIE — de regulă un import merge pe o singură cale

Sheet Reguli_IMPORT
A1: MOD_IMPORT — Reguli (tabele fixe)
A2: Regula e dată, nu formulă. Tabelul A e cel care se citește cel mai des: spune ce intră unde.
A4: Tabel A — Ce intră în cost și ce intră în baza TVA vamală
A5: Element | B5: În cost? | C5: În baza TVA? | D5: Observație
A6: Valoarea mărfii de pe factura externă | B6: DA | C6: DA | D6: Convertită la cursul de la data DVI
A7: Taxe vamale | B7: DA | C7: DA | D7: Sunt parte din baza de impozitare la import
A8: Comisioane vamale, taxe de manipulare | B8: DA | C8: DA | D8: Dacă apar pe DVI, urmează același regim ca taxele
